Workbook

Sheet Resumo 2023
A1: Categoria | B1: Janeiro | C1: Fevereiro | D1: março | E1: abril | F1: maio | G1: jun | H1: jul | I1: Agosto | J1: setembro | K1: outubro | L1: novembro | M1: dezembro | N1: 45315 | O1: 45340 | P1: 45369 | Q1: 45400 | R1: 45430 | S1: 45461 | T1: 45545 | U1: 45682 | V1: 45713 | W1: 45741 | X1: 45772 | Y1: 45802 | Z1: 45833 | AA1: 45863 | AB1: 45894 | AC1: media 5meses
A2: escola/faculdade | B2: =Janeiro23!B67 -> 883 | C2: =fevereiro23!B102 -> 2797.99 | D2: =ifna(VLOOKUP(A2, marco23!$A$97:$B$119, 2, FALSE),0) -> 1593 | E2: =ifna(VLOOKUP(A2, abril23!$A$82:$B$103, 2, FALSE),0) -> 888 | F2: =ifna(VLOOKUP(A2, maio23!$A$95:$B$117, 2, FALSE),0) -> 1458.0273 | G2: =ifna(VLOOKUP(A2, junho23!$A$127:$B$152, 2, FALSE),0) -> 1458.0273 | H2: =ifna(VLOOKUP(A2, julho23!$A$139:$B$164, 2, FALSE),0) -> 1458.0273 | I2: =ifna(VLOOKUP(A2, Agosto23!$A$127:$B$152, 2, FALSE),0) -> 1724.0364 | J2: =ifna(VLOOKUP(A2, setembro23!$A$125:$B$151, 2, FALSE),0) -> 1268 | K2: =ifna(VLOOKUP(A2, outubro23!$A$121:$B$146, 2, FALSE),0) -> 1652 | L2: =ifna(VLOOKUP(A2, novembro23!$A$121:$B$146, 2, FALSE),0) -> 1652 | M2: =ifna(VLOOKUP(A2, Dezembro23!$A$127:$B$152, 2, FALSE),0) -> 2523.5 | N2: =ifna(VLOOKUP(A2, janneiro24!$A$127:$B$152, 2, FALSE),0) -> 799.49 | O2: =ifna(VLOOKUP(A2, fevereiro24!$A$127:$B$152, 2, FALSE),0) -> 2459.3928 | P2: =ifna(VLOOKUP(A2, marco24!$A$127:$B$152, 2, FALSE),0) -> 1808.31 | Q2: =ifna(VLOOKUP(A2, abril24!$A$127:$B$152, 2, FALSE),0) -> 1808.31 | R2: =ifna(VLOOKUP(A2, maio24!$A$127:$B$152, 2, FALSE),0) -> 1808.31 | S2: =ifna(VLOOKUP(A2, 'jun24'!$A$127:$B$152, 2, FALSE),0) -> 1819.3 | T2: =ifna(VLOOKUP(A2, 'set24'!$A$127:$B$152, 2, FALSE),0) -> 1490.22 | U2: =ifna(VLOOKUP(A2, 'jan25'!$A$127:$B$152, 2, FALSE),0) -> 1729.94 | V2: =ifna(VLOOKUP(A2, 'fev25'!$A$132:$B$157, 2, FALSE),0) -> 1345.63 | W2: =ifna(VLOOKUP(A2, 'mar25'!$A$125:$B$153, 2, FALSE),0) -> 1484.78 | X2: =ifna(VLOOKUP(A2, 'abr25'!$A$131:$B$157, 2, FALSE),0) -> 1474 | Y2: =ifna(VLOOKUP(A2, 'mai25'!$A$142:$B$174, 2, FALSE),0) -> 1474 | Z2: =ifna(VLOOKUP(A2, 'jun25'!$A$141:$B$169, 2, FALSE),0) -> 1474.78 | AA2: =ifna(VLOOKUP(A2, 'jul25'!$A$141:$B$170, 2, FALSE),0) -> 1639 | AB2: =ifna(VLOOKUP(A2, 'ago25'!$A$141:$B$170, 2, FALSE),0) -> 1639 | AC2: =AVERAGE(X2:AA2) -> 1515.445
A3: gift | B3: =Janeiro23!B52 -> 0 | C3: =fevereiro23!B97 -> 492.99 | D3: =ifna(VLOOKUP(A3, marco23!$A$97:$B$119, 2, FALSE),0) -> 492.99 | E3: =ifna(VLOOKUP(A3, abril23!$A$82:$B$103, 2, FALSE),0) -> 1911.33 | F3: =ifna(VLOOKUP(A3, maio23!$A$95:$B$117, 2, FALSE),0) -> 258.22 | G3: =ifna(VLOOKUP(A3, junho23!$A$127:$B$152, 2, FALSE),0) -> 238.8 | H3: =ifna(VLOOKUP(A3, julho23!$A$139:$B$164, 2, FALSE),0) -> 109.99 | I3: =ifna(VLOOKUP(A3, Agosto23!$A$127:$B$152, 2, FALSE),0) -> 0 | J3: =ifna(VLOOKUP(A3, setembro23!$A$125:$B$151, 2, FALSE),0) -> 362.95 | K3: =ifna(VLOOKUP(A3, outubro23!$A$121:$B$146, 2, FALSE),0) -> 224.99 | L3: =ifna(VLOOKUP(A3, novembro23!$A$121:$B$146, 2, FALSE),0) -> 0 | M3: =ifna(VLOOKUP(A3, Dezembro23!$A$127:$B$152, 2, FALSE),0) -> 188.9 | N3: =ifna(VLOOKUP(A3, janneiro24!$A$127:$B$152, 2, FALSE),0) -> 0 | O3: =ifna(VLOOKUP(A3, fevereiro24!$A$127:$B$152, 2, FALSE),0) -> 0 | P3: =ifna(VLOOKUP(A3, marco24!$A$127:$B$152, 2, FALSE),0) -> 69 | Q3: =ifna(VLOOKUP(A3, abril24!$A$127:$B$152, 2, FALSE),0) -> 323.56 | R3: =ifna(VLOOKUP(A3, maio24!$A$127:$B$152, 2, FALSE),0) -> 49.9 | S3: =ifna(VLOOKUP(A3, 'jun24'!$A$127:$B$152, 2, FALSE),0) -> 249.84 | T3: =ifna(VLOOKUP(A3, 'set24'!$A$127:$B$152, 2, FALSE),0) -> 124.79 | U3: =ifna(VLOOKUP(A3, 'jan25'!$A$127:$B$152, 2, FALSE),0) -> 0 | V3: =ifna(VLOOKUP(A3, 'fev25'!$A$132:$B$157, 2, FALSE),0) -> 533.59 | W3: =ifna(VLOOKUP(A3, 'mar25'!$A$125:$B$153, 2, FALSE),0) -> 252.09 | X3: =ifna(VLOOKUP(A3, 'abr25'!$A$131:$B$157, 2, FALSE),0) -> 937.38 | Y3: =ifna(VLOOKUP(A3, 'mai25'!$A$142:$B$174, 2, FALSE),0) -> 634.06 | Z3: =ifna(VLOOKUP(A3, 'jun25'!$A$141:$B$169, 2, FALSE),0) -> 590.17 | AA3: =ifna(VLOOKUP(A3, 'jul25'!$A$141:$B$170, 2, FALSE),0) -> 1049.91 | AB3: =ifna(VLOOKUP(A3, 'ago25'!$A$141:$B$170, 2, FALSE),0) -> 389.98 | AC3: =AVERAGE(X3:AA3) -> 802.88
A4: cursos | B4: =Janeiro23!B53 -> 37.9 | C4: =fevereiro23!B83 -> 37.9 | D4: =ifna(VLOOKUP(A4, marco23!$A$97:$B$119, 2, FALSE),0) -> 37.9 | E4: =ifna(VLOOKUP(A4, abril23!$A$82:$B$103, 2, FALSE),0) -> 37.9 | F4: =ifna(VLOOKUP(A4, maio23!$A$95:$B$117, 2, FALSE),0) -> 37.9 | G4: =ifna(VLOOKUP(A4, junho23!$A$127:$B$152, 2, FALSE),0) -> 0 | H4: =ifna(VLOOKUP(A4, julho23!$A$139:$B$164, 2, FALSE),0) -> 0 | I4: =ifna(VLOOKUP(A4, Agosto23!$A$127:$B$152, 2, FALSE),0) -> 0 | J4: =ifna(VLOOKUP(A4, setembro23!$A$125:$B$151, 2, FALSE),0) -> 0 | K4: =ifna(VLOOKUP(A4, outubro23!$A$121:$B$146, 2, FALSE),0) -> 1326.51 | L4: =ifna(VLOOKUP(A4, novembro23!$A$121:$B$146, 2, FALSE),0) -> 0 | M4: =ifna(VLOOKUP(A4, Dezembro23!$A$127:$B$152, 2, FALSE),0) -> 0 | N4: =ifna(VLOOKUP(A4, janneiro24!$A$127:$B$152, 2, FALSE),0) -> 0 | O4: =ifna(VLOOKUP(A4, fevereiro24!$A$127:$B$152, 2, FALSE),0) -> 0 | P4: =ifna(VLOOKUP(A4, marco24!$A$127:$B$152, 2, FALSE),0) -> 0 | Q4: =ifna(VLOOKUP(A4, abril24!$A$127:$B$152, 2, FALSE),0) -> 0 | R4: =ifna(VLOOKUP(A4, maio24!$A$127:$B$152, 2, FALSE),0) -> 0 | S4: =ifna(VLOOKUP(A4, 'jun24'!$A$127:$B$152, 2, FALSE),0) -> 0 | T4: =ifna(VLOOKUP(A4, 'set24'!$A$127:$B$152, 2, FALSE),0) -> 0 | U4: =ifna(VLOOKUP(A4, 'jan25'!$A$127:$B$152, 2, FALSE),0) -> 0 | V4: =ifna(VLOOKUP(A4, 'fev25'!$A$132:$B$157, 2, FALSE),0) -> 0 | W4: =ifna(VLOOKUP(A4, 'mar25'!$A$125:$B$153, 2, FALSE),0) -> 0 | X4: =ifna(VLOOKUP(A4, 'abr25'!$A$131:$B$157, 2, FALSE),0) -> 0 | Y4: =ifna(VLOOKUP(A4, 'mai25'!$A$142:$B$174, 2, FALSE),0) -> 2457.12 | Z4: =ifna(VLOOKUP(A4, 'jun25'!$A$141:$B$169, 2, FALSE),0) -> 380.12 | AA4: =ifna(VLOOKUP(A4, 'jul25'!$A$141:$B$170, 2, FALSE),0) -> 380 | AB4: =ifna(VLOOKUP(A4, 'ago25'!$A$141:$B$170, 2, FALSE),0) -> 380 | AC4: =AVERAGE(X4:AA4) -> 804.31
A5: streaming | B5: =Janeiro23!B54 -> 78.65 | C5: =fevereiro23!B85 -> 78.65 | D5: =ifna(VLOOKUP(A5, marco23!$A$97:$B$119, 2, FALSE),0) -> 78.65 | E5: =ifna(VLOOKUP(A5, abril23!$A$82:$B$103, 2, FALSE),0) -> 93.55 | F5: =ifna(VLOOKUP(A5, maio23!$A$95:$B$117, 2, FALSE),0) -> 93.55 | G5: =ifna(VLOOKUP(A5, junho23!$A$127:$B$152, 2, FALSE),0) -> 93.55 | H5: =ifna(VLOOKUP(A5, julho23!$A$139:$B$164, 2, FALSE),0) -> 102.14 | I5: =ifna(VLOOKUP(A5, Agosto23!$A$127:$B$152, 2, FALSE),0) -> 102.14 | J5: =ifna(VLOOKUP(A5, setembro23!$A$125:$B$151, 2, FALSE),0) -> 102.14 | K5: =ifna(VLOOKUP(A5, outubro23!$A$121:$B$146, 2, FALSE),0) -> 102.14 | L5: =ifna(VLOOKUP(A5, novembro23!$A$121:$B$146, 2, FALSE),0) -> 102.14 | M5: =ifna(VLOOKUP(A5, Dezembro23!$A$127:$B$152, 2, FALSE),0) -> 112.14 | N5: =ifna(VLOOKUP(A5, janneiro24!$A$127:$B$152, 2, FALSE),0) -> 90.24 | O5: =ifna(VLOOKUP(A5, fevereiro24!$A$127:$B$152, 2, FALSE),0) -> 90.24 | P5: =ifna(VLOOKUP(A5, marco24!$A$127:$B$152, 2, FALSE),0) -> 90.24 | Q5: =ifna(VLOOKUP(A5, abril24!$A$127:$B$152, 2, FALSE),0) -> 90.24 | R5: =ifna(VLOOKUP(A5, maio24!$A$127:$B$152, 2, FALSE),0) -> 90.24 | S5: =ifna(VLOOKUP(A5, 'jun24'!$A$127:$B$152, 2, FALSE),0) -> 242 | T5: =ifna(VLOOKUP(A5, 'set24'!$A$127:$B$152, 2, FALSE),0) -> 82.84 | U5: =ifna(VLOOKUP(A5, 'jan25'!$A$127:$B$152, 2, FALSE),0) -> 92.84 | V5: =ifna(VLOOKUP(A5, 'fev25'!$A$132:$B$157, 2, FALSE),0) -> 92.84 | W5: =ifna(VLOOKUP(A5, 'mar25'!$A$125:$B$153, 2, FALSE),0) -> 92.84 | X5: =ifna(VLOOKUP(A5, 'abr25'!$A$131:$B$157, 2, FALSE),0) -> 89.75 | Y5: =ifna(VLOOKUP(A5, 'mai25'!$A$142:$B$174, 2, FALSE),0) -> 89.75 | Z5: =ifna(VLOOKUP(A5, 'jun25'!$A$141:$B$169, 2, FALSE),0) -> 255.75 | AA5: =ifna(VLOOKUP(A5, 'jul25'!$A$141:$B$170, 2, FALSE),0) -> 89.75 | AB5: =ifna(VLOOKUP(A5, 'ago25'!$A$141:$B$170, 2, FALSE),0) -> 89.75 | AC5: =AVERAGE(X5:AA5) -> 131.25
A6: combustivel | B6: =Janeiro23!B55 -> 85.71 | C6: =fevereiro23!B91 -> 199.85 | D6: =ifna(VLOOKUP(A6, marco23!$A$97:$B$119, 2, FALSE),0) -> 228.26 | E6: =ifna(VLOOKUP(A6, abril23!$A$82:$B$103, 2, FALSE),0) -> 250 | F6: =ifna(VLOOKUP(A6, maio23!$A$95:$B$117, 2, FALSE),0) -> 201.84 | G6: =ifna(VLOOKUP(A6, junho23!$A$127:$B$152, 2, FALSE),0) -> 431.69 | H6: =ifna(VLOOKUP(A6, julho23!$A$139:$B$164, 2, FALSE),0) -> 118.08 | I6: =ifna(VLOOKUP(A6, Agosto23!$A$127:$B$152, 2, FALSE),0) -> 289.23 | J6: =ifna(VLOOKUP(A6, setembro23!$A$125:$B$151, 2, FALSE),0) -> 251.2 | K6: =ifna(VLOOKUP(A6, outubro23!$A$121:$B$146, 2, FALSE),0) -> 253.05 | L6: =ifna(VLOOKUP(A6, novembro23!$A$121:$B$146, 2, FALSE),0) -> 321.44 | M6: =ifna(VLOOKUP(A6, Dezembro23!$A$127:$B$152, 2, FALSE),0) -> 275.64 | N6: =ifna(VLOOKUP(A6, janneiro24!$A$127:$B$152, 2, FALSE),0) -> 168.12 | O6: =ifna(VLOOKUP(A6, fevereiro24!$A$127:$B$152, 2, FALSE),0) -> 168.12 | P6: =ifna(VLOOKUP(A6, marco24!$A$127:$B$152, 2, FALSE),0) -> 493.4 | Q6: =ifna(VLOOKUP(A6, abril24!$A$127:$B$152, 2, FALSE),0) -> 433.48 | R6: =ifna(VLOOKUP(A6, maio24!$A$127:$B$152, 2, FALSE),0) -> 568.77 | S6: =ifna(VLOOKUP(A6, 'jun24'!$A$127:$B$152, 2, FALSE),0) -> 253.43 | T6: =ifna(VLOOKUP(A6, 'set24'!$A$127:$B$152, 2, FALSE),0) -> 216.68 | U6: =ifna(VLOOKUP(A6, 'jan25'!$A$127:$B$152, 2, FALSE),0) -> 0 | V6: =ifna(VLOOKUP(A6, 'fev25'!$A$132:$B$157, 2, FALSE),0) -> 340.84 | W6: =ifna(VLOOKUP(A6, 'mar25'!$A$125:$B$153, 2, FALSE),0) -> 280.69 | X6: =ifna(VLOOKUP(A6, 'abr25'!$A$131:$B$157, 2, FALSE),0) -> 358.38 | Y6: =ifna(VLOOKUP(A6, 'mai25'!$A$142:$B$174, 2, FALSE),0) -> 334.45 | Z6: =ifna(VLOOKUP(A6, 'jun25'!$A$141:$B$169, 2, FALSE),0) -> 365.93 | AA6: =ifna(VLOOKUP(A6, 'jul25'!$A$141:$B$170, 2, FALSE),0) -> 382.92 | AB6: =ifna(VLOOKUP(A6, 'ago25'!$A$141:$B$170, 2, FALSE),0) -> 301.94 | AC6: =AVERAGE(X6:AA6) -> 360.42
A7: contabilidade | B7: =Janeiro23!B56 -> 89.9 | C7: =fevereiro23!B86 -> 89.9 | D7: =ifna(VLOOKUP(A7, marco23!$A$97:$B$119, 2, FALSE),0) -> 89.9 | E7: =ifna(VLOOKUP(A7, abril23!$A$82:$B$103, 2, FALSE),0) -> 89.9 | F7: =ifna(VLOOKUP(A7, maio23!$A$95:$B$117, 2, FALSE),0) -> 89.9 | G7: =ifna(VLOOKUP(A7, junho23!$A$127:$B$152, 2, FALSE),0) -> 89.9 | H7: =ifna(VLOOKUP(A7, julho23!$A$139:$B$164, 2, FALSE),0) -> 89.9 | I7: =ifna(VLOOKUP(A7, Agosto23!$A$127:$B$152, 2, FALSE),0) -> 89.9 | J7: =ifna(VLOOKUP(A7, setembro23!$A$125:$B$151, 2, FALSE),0) -> 89.9 | K7: =ifna(VLOOKUP(A7, outubro23!$A$121:$B$146, 2, FALSE),0) -> 89.9 | L7: =ifna(VLOOKUP(A7, novembro23!$A$121:$B$146, 2, FALSE),0) -> 89.9 | M7: =ifna(VLOOKUP(A7, Dezembro23!$A$127:$B$152, 2, FALSE),0) -> 89.9 | N7: =ifna(VLOOKUP(A7, janneiro24!$A$127:$B$152, 2, FALSE),0) -> 100 | O7: =ifna(VLOOKUP(A7, fevereiro24!$A$127:$B$152, 2, FALSE),0) -> 89.9 | P7: =ifna(VLOOKUP(A7, marco24!$A$127:$B$152, 2, FALSE),0) -> 100.46 | Q7: =ifna(VLOOKUP(A7, abril24!$A$127:$B$152, 2, FALSE),0) -> 100.46 | R7: =ifna(VLOOKUP(A7, maio24!$A$127:$B$152, 2, FALSE),0) -> 100.46 | S7: =ifna(VLOOKUP(A7, 'jun24'!$A$127:$B$152, 2, FALSE),0) -> 100.46 | T7: =ifna(VLOOKUP(A7, 'set24'!$A$127:$B$152, 2, FALSE),0) -> 100.46 | U7: =ifna(VLOOKUP(A7, 'jan25'!$A$127:$B$152, 2, FALSE),0) -> 0 | V7: =ifna(VLOOKUP(A7, 'fev25'!$A$132:$B$157, 2, FALSE),0) -> 0 | W7: =ifna(VLOOKUP(A7, 'mar25'!$A$125:$B$153, 2, FALSE),0) -> 0 | X7: =ifna(VLOOKUP(A7, 'abr25'!$A$131:$B$157, 2, FALSE),0) -> 0 | Y7: =ifna(VLOOKUP(A7, 'mai25'!$A$142:$B$174, 2, FALSE),0) -> 0 | Z7: =ifna(VLOOKUP(A7, 'jun25'!$A$141:$B$169, 2, FALSE),0) -> 0 | AA7: =ifna(VLOOKUP(A7, 'jul25'!$A$141:$B$170, 2, FALSE),0) -> 0 | AB7: =ifna(VLOOKUP(A7, 'ago25'!$A$141:$B$170, 2, FALSE),0) -> 0 | AC7: =AVERAGE(X7:AA7) -> 0
A8: estacionamentos | B8: =Janeiro23!B57 -> 92 | C8: =0 -> 0 | D8: =ifna(VLOOKUP(A8, marco23!$A$97:$B$119, 2, FALSE),0) -> 0 | E8: =ifna(VLOOKUP(A8, abril23!$A$82:$B$103, 2, FALSE),0) -> 0 | F8: =ifna(VLOOKUP(A8, maio23!$A$95:$B$117, 2, FALSE),0) -> 0 | G8: =ifna(VLOOKUP(A8, junho23!$A$127:$B$152, 2, FALSE),0) -> 0 | H8: =ifna(VLOOKUP(A8, julho23!$A$139:$B$164, 2, FALSE),0) -> 0 | I8: =ifna(VLOOKUP(A8, Agosto23!$A$127:$B$152, 2, FALSE),0) -> 0 | J8: =ifna(VLOOKUP(A8, setembro23!$A$125:$B$151, 2, FALSE),0) -> 0 | K8: =ifna(VLOOKUP(A8, outubro23!$A$121:$B$146, 2, FALSE),0) -> 36 | L8: =ifna(VLOOKUP(A8, novembro23!$A$121:$B$146, 2, FALSE),0) -> 17 | M8: =ifna(VLOOKUP(A8, Dezembro23!$A$127:$B$152, 2, FALSE),0) -> 25 | N8: =ifna(VLOOKUP(A8, janneiro24!$A$127:$B$152, 2, FALSE),0) -> 0 | O8: =ifna(VLOOKUP(A8, fevereiro24!$A$127:$B$152, 2, FALSE),0) -> 0 | P8: =ifna(VLOOKUP(A8, marco24!$A$127:$B$152, 2, FALSE),0) -> 0 | Q8: =ifna(VLOOKUP(A8, abril24!$A$127:$B$152, 2, FALSE),0) -> 40 | R8: =ifna(VLOOKUP(A8, maio24!$A$127:$B$152, 2, FALSE),0) -> 8 | S8: =ifna(VLOOKUP(A8, 'jun24'!$A$127:$B$152, 2, FALSE),0) -> 0 | T8: =ifna(VLOOKUP(A8, 'set24'!$A$127:$B$152, 2, FALSE),0) -> 5 | U8: =ifna(VLOOKUP(A8, 'jan25'!$A$127:$B$152, 2, FALSE),0) -> 0 | V8: =ifna(VLOOKUP(A8, 'fev25'!$A$132:$B$157, 2, FALSE),0) -> 10 | W8: =ifna(VLOOKUP(A8, 'mar25'!$A$125:$B$153, 2, FALSE),0) -> 8 | X8: =ifna(VLOOKUP(A8, 'abr25'!$A$131:$B$157, 2, FALSE),0) -> 16 | Y8: =ifna(VLOOKUP(A8, 'mai25'!$A$142:$B$174, 2, FALSE),0) -> 46 | Z8: =ifna(VLOOKUP(A8, 'jun25'!$A$141:$B$169, 2, FALSE),0) -> 27.4 | AA8: =ifna(VLOOKUP(A8, 'jul25'!$A$141:$B$170, 2, FALSE),0) -> 16 | AB8: =ifna(VLOOKUP(A8, 'ago25'!$A$141:$B$170, 2, FALSE),0) -> 42 | AC8: =AVERAGE(X8:AA8) -> 26.35
A9: Internet movel | B9: =Janeiro23!B58 -> 99 | C9: =fevereiro23!B88 -> 99 | D9: =ifna(VLOOKUP(A9, marco23!$A$97:$B$119, 2, FALSE),0) -> 99 | E9: =ifna(VLOOKUP(A9, abril23!$A$82:$B$103, 2, FALSE),0) -> 88 | F9: =ifna(VLOOKUP(A9, maio23!$A$95:$B$117, 2, FALSE),0) -> 88 | G9: =ifna(VLOOKUP(A9, junho23!$A$127:$B$152, 2, FALSE),0) -> 148 | H9: =ifna(VLOOKUP(A9, julho23!$A$139:$B$164, 2, FALSE),0) -> 88 | I9: =ifna(VLOOKUP(A9, Agosto23!$A$127:$B$152, 2, FALSE),0) -> 88 | J9: =ifna(VLOOKUP(A9, setembro23!$A$125:$B$151, 2, FALSE),0) -> 88 | K9: =ifna(VLOOKUP(A9, outubro23!$A$121:$B$146, 2, FALSE),0) -> 88 | L9: =ifna(VLOOKUP(A9, novembro23!$A$121:$B$146, 2, FALSE),0) -> 88 | M9: =ifna(VLOOKUP(A9, Dezembro23!$A$127:$B$152, 2, FALSE),0) -> 138 | N9: =ifna(VLOOKUP(A9, janneiro24!$A$127:$B$152, 2, FALSE),0) -> 88 | O9: =ifna(VLOOKUP(A9, fevereiro24!$A$127:$B$152, 2, FALSE),0) -> 88 | P9: =ifna(VLOOKUP(A9, marco24!$A$127:$B$152, 2, FALSE),0) -> 88 | Q9: =ifna(VLOOKUP(A9, abril24!$A$127:$B$152, 2, FALSE),0) -> 88 | R9: =ifna(VLOOKUP(A9, maio24!$A$127:$B$152, 2, FALSE),0) -> 88 | S9: =ifna(VLOOKUP(A9, 'jun24'!$A$127:$B$152, 2, FALSE),0) -> 88 | T9: =ifna(VLOOKUP(A9, 'set24'!$A$127:$B$152, 2, FALSE),0) -> 162.3 | U9: =ifna(VLOOKUP(A9, 'jan25'!$A$127:$B$152, 2, FALSE),0) -> 88 | V9: =ifna(VLOOKUP(A9, 'fev25'!$A$132:$B$157, 2, FALSE),0) -> 181.1 | W9: =ifna(VLOOKUP(A9, 'mar25'!$A$125:$B$153, 2, FALSE),0) -> 149.9 | X9: =ifna(VLOOKUP(A9, 'abr25'!$A$131:$B$157, 2, FALSE),0) -> 149.9 | Y9: =ifna(VLOOKUP(A9, 'mai25'!$A$142:$B$174, 2, FALSE),0) -> 138 | Z9: =ifna(VLOOKUP(A9, 'jun25'!$A$141:$B$169, 2, FALSE),0) -> 149.9 | AA9: =ifna(VLOOKUP(A9, 'jul25'!$A$141:$B$170, 2, FALSE),0) -> 99.9 | AB9: =ifna(VLOOKUP(A9, 'ago25'!$A$141:$B$170, 2, FALSE),0) -> 99.9 | AC9: =AVERAGE(X9:AA9) -> 134.425
A10: Internet | B10: =Janeiro23!B59 -> 104 | C10: =fevereiro23!B89 -> 104 | D10: =ifna(VLOOKUP(A10, marco23!$A$97:$B$119, 2, FALSE),0) -> 104 | E10: =ifna(VLOOKUP(A10, abril23!$A$82:$B$103, 2, FALSE),0) -> 119.83 | F10: =ifna(VLOOKUP(A10, maio23!$A$95:$B$117, 2, FALSE),0) -> 99 | G10: =ifna(VLOOKUP(A10, junho23!$A$127:$B$152, 2, FALSE),0) -> 99 | H10: =ifna(VLOOKUP(A10, julho23!$A$139:$B$164, 2, FALSE),0) -> 99 | I10: =ifna(VLOOKUP(A10, Agosto23!$A$127:$B$152, 2, FALSE),0) -> 99 | J10: =ifna(VLOOKUP(A10, setembro23!$A$125:$B$151, 2, FALSE),0) -> 99 | K10: =ifna(VLOOKUP(A10, outubro23!$A$121:$B$146, 2, FALSE),0) -> 99 | L10: =ifna(VLOOKUP(A10, novembro23!$A$121:$B$146, 2, FALSE),0) -> 99 | M10: =ifna(VLOOKUP(A10, Dezembro23!$A$127:$B$152, 2, FALSE),0) -> 99 | N10: =ifna(VLOOKUP(A10, janneiro24!$A$127:$B$152, 2, FALSE),0) -> 129 | O10: =ifna(VLOOKUP(A10, fevereiro24!$A$127:$B$152, 2, FALSE),0) -> 129 | P10: =ifna(VLOOKUP(A10, marco24!$A$127:$B$152, 2, FALSE),0) -> 129 | Q10: =ifna(VLOOKUP(A10, abril24!$A$127:$B$152, 2, FALSE),0) -> 129 | R10: =ifna(VLOOKUP(A10, maio24!$A$127:$B$152, 2, FALSE),0) -> 129 | S10: =ifna(VLOOKUP(A10, 'jun24'!$A$127:$B$152, 2, FALSE),0) -> 129 | T10: =ifna(VLOOKUP(A10, 'set24'!$A$127:$B$152, 2, FALSE),0) -> 1825.42 | U10: =ifna(VLOOKUP(A10, 'jan25'!$A$127:$B$152, 2, FALSE),0) -> 129 | V10: =ifna(VLOOKUP(A10, 'fev25'!$A$132:$B$157, 2, FALSE),0) -> 132.72 | W10: =ifna(VLOOKUP(A10, 'mar25'!$A$125:$B$153, 2, FALSE),0) -> 132.55 | X10: =ifna(VLOOKUP(A10, 'abr25'!$A$131:$B$157, 2, FALSE),0) -> 132.5 | Y10: =ifna(VLOOKUP(A10, 'mai25'!$A$142:$B$174, 2, FALSE),0) -> 132.55 | Z10: =ifna(VLOOKUP(A10, 'jun25'!$A$141:$B$169, 2, FALSE),0) -> 132.76 | AA10: =ifna(VLOOKUP(A10, 'jul25'!$A$141:$B$170, 2, FALSE),0) -> 132.76 | AB10: =ifna(VLOOKUP(A10, 'ago25'!$A$141:$B$170, 2, FALSE),0) -> 132.76 | AC10: =AVERAGE(X10:AA10) -> 132.6425
A11: academia | B11: =Janeiro23!B60 -> 109 | C11: =fevereiro23!B90 -> 109 | D11: =ifna(VLOOKUP(A11, marco23!$A$97:$B$119, 2, FALSE),0) -> 109 | E11: =ifna(VLOOKUP(A11, abril23!$A$82:$B$103, 2, FALSE),0) -> 109 | F11: =ifna(VLOOKUP(A11, maio23!$A$95:$B$117, 2, FALSE),0) -> 109 | G11: =ifna(VLOOKUP(A11, junho23!$A$127:$B$152, 2, FALSE),0) -> 69.9 | H11: =ifna(VLOOKUP(A11, julho23!$A$139:$B$164, 2, FALSE),0) -> 79.9 | I11: =ifna(VLOOKUP(A11, Agosto23!$A$127:$B$152, 2, FALSE),0) -> 286.2 | J11: =ifna(VLOOKUP(A11, setembro23!$A$125:$B$151, 2, FALSE),0) -> 679.8 | K11: =ifna(VLOOKUP(A11, outubro23!$A$121:$B$146, 2, FALSE),0) -> 679.8 | L11: =ifna(VLOOKUP(A11, novembro23!$A$121:$B$146, 2, FALSE),0) -> 679.8 | M11: =ifna(VLOOKUP(A11, Dezembro23!$A$127:$B$152, 2, FALSE),0) -> 679.8 | N11: =ifna(VLOOKUP(A11, janneiro24!$A$127:$B$152, 2, FALSE),0) -> 679.8 | O11: =ifna(VLOOKUP(A11, fevereiro24!$A$127:$B$152, 2, FALSE),0) -> 679.8 | P11: =ifna(VLOOKUP(A11, marco24!$A$127:$B$152, 2, FALSE),0) -> 679.8 | Q11: =ifna(VLOOKUP(A11, abril24!$A$127:$B$152, 2, FALSE),0) -> 679.8 | R11: =ifna(VLOOKUP(A11, maio24!$A$127:$B$152, 2, FALSE),0) -> 679.8 | S11: =ifna(VLOOKUP(A11, 'jun24'!$A$127:$B$152, 2, FALSE),0) -> 679.8 | T11: =ifna(VLOOKUP(A11, 'set24'!$A$127:$B$152, 2, FALSE),0) -> 695.8 | U11: =ifna(VLOOKUP(A11, 'jan25'!$A$127:$B$152, 2, FALSE),0) -> 715.8 | V11: =ifna(VLOOKUP(A11, 'fev25'!$A$132:$B$157, 2, FALSE),0) -> 215.8 | W11: =ifna(VLOOKUP(A11, 'mar25'!$A$125:$B$153, 2, FALSE),0) -> 215.8 | X11: =ifna(VLOOKUP(A11, 'abr25'!$A$131:$B$157, 2, FALSE),0) -> 729.8 | Y11: =ifna(VLOOKUP(A11, 'mai25'!$A$142:$B$174, 2, FALSE),0) -> 729.8 | Z11: =ifna(VLOOKUP(A11, 'jun25'!$A$141:$B$169, 2, FALSE),0) -> 457.96 | AA11: =ifna(VLOOKUP(A11, 'jul25'!$A$141:$B$170, 2, FALSE),0) -> 229.8 | AB11: =ifna(VLOOKUP(A11, 'ago25'!$A$141:$B$170, 2, FALSE),0) -> 229.8 | AC11: =AVERAGE(X11:AA11) -> 536.84
A12: Feira | B12: =Janeiro23!B61 -> 116.74 | C12: =fevereiro23!B82 -> 33 | D12: =ifna(VLOOKUP(A12, marco23!$A$97:$B$119, 2, FALSE),0) -> 34.32 | E12: =ifna(VLOOKUP(A12, abril23!$A$82:$B$103, 2, FALSE),0) -> 59.24 | F12: =ifna(VLOOKUP(A12, maio23!$A$95:$B$117, 2, FALSE),0) -> 0 | G12: =ifna(VLOOKUP(A12, junho23!$A$127:$B$152, 2, FALSE),0) -> 38.2 | H12: =ifna(VLOOKUP(A12, julho23!$A$139:$B$164, 2, FALSE),0) -> 12 | I12: =ifna(VLOOKUP(A12, Agosto23!$A$127:$B$152, 2, FALSE),0) -> 22.2 | J12: =ifna(VLOOKUP(A12, setembro23!$A$125:$B$151, 2, FALSE),0) -> 42.9 | K12: =ifna(VLOOKUP(A12, outubro23!$A$121:$B$146, 2, FALSE),0) -> 16.45 | L12: =ifna(VLOOKUP(A12, novembro23!$A$121:$B$146, 2, FALSE),0) -> 44.9 | M12: =ifna(VLOOKUP(A12, Dezembro23!$A$127:$B$152, 2, FALSE),0) -> 70.95 | N12: =ifna(VLOOKUP(A12, janneiro24!$A$127:$B$152, 2, FALSE),0) -> 0 | O12: =ifna(VLOOKUP(A12, fevereiro24!$A$127:$B$152, 2, FALSE),0) -> 0 | P12: =ifna(VLOOKUP(A12, marco24!$A$127:$B$152, 2, FALSE),0) -> 128.58 | Q12: =ifna(VLOOKUP(A12, abril24!$A$127:$B$152, 2, FALSE),0) -> 65.2 | R12: =ifna(VLOOKUP(A12, maio24!$A$127:$B$152, 2, FALSE),0) -> 169.12 | S12: =ifna(VLOOKUP(A12, 'jun24'!$A$127:$B$152, 2, FALSE),0) -> 161.05 | T12: =ifna(VLOOKUP(A12, 'set24'!$A$127:$B$152, 2, FALSE),0) -> 31 | U12: =ifna(VLOOKUP(A12, 'jan25'!$A$127:$B$152, 2, FALSE),0) -> 0 | V12: =ifna(VLOOKUP(A12, 'fev25'!$A$132:$B$157, 2, FALSE),0) -> 183.88 | W12: =ifna(VLOOKUP(A12, 'mar25'!$A$125:$B$153, 2, FALSE),0) -> 125.68 | X12: =ifna(VLOOKUP(A12, 'abr25'!$A$131:$B$157, 2, FALSE),0) -> 177.18 | Y12: =ifna(VLOOKUP(A12, 'mai25'!$A$142:$B$174, 2, FALSE),0) -> 310.15 | Z12: =ifna(VLOOKUP(A12, 'jun25'!$A$141:$B$169, 2, FALSE),0) -> 144.27 | AA12: =ifna(VLOOKUP(A12, 'jul25'!$A$141:$B$170, 2, FALSE),0) -> 217.82 | AB12: =ifna(VLOOKUP(A12, 'ago25'!$A$141:$B$170, 2, FALSE),0) -> 189.09 | AC12: =AVERAGE(X12:AA12) -> 212.355
A13: farmacia | B13: =Janeiro23!B62 -> 185.46 | C13: =0 -> 0 | D13: =ifna(VLOOKUP(A13, marco23!$A$97:$B$119, 2, FALSE),0) -> 150.32 | E13: =ifna(VLOOKUP(A13, abril23!$A$82:$B$103, 2, FALSE),0) -> 101.66 | F13: =ifna(VLOOKUP(A13, maio23!$A$95:$B$117, 2, FALSE),0) -> 168.62 | G13: =ifna(VLOOKUP(A13, junho23!$A$127:$B$152, 2, FALSE),0) -> 285.67 | H13: =ifna(VLOOKUP(A13, julho23!$A$139:$B$164, 2, FALSE),0) -> 67.23 | I13: =ifna(VLOOKUP(A13, Agosto23!$A$127:$B$152, 2, FALSE),0) -> 124.96 | J13: =ifna(VLOOKUP(A13, setembro23!$A$125:$B$151, 2, FALSE),0) -> 0 | K13: =ifna(VLOOKUP(A13, outubro23!$A$121:$B$146, 2, FALSE),0) -> 106.54 | L13: =ifna(VLOOKUP(A13, novembro23!$A$121:$B$146, 2, FALSE),0) -> 52.66 | M13: =ifna(VLOOKUP(A13, Dezembro23!$A$127:$B$152, 2, FALSE),0) -> 0 | N13: =ifna(VLOOKUP(A13, janneiro24!$A$127:$B$152, 2, FALSE),0) -> 60.48 | O13: =ifna(VLOOKUP(A13, fevereiro24!$A$127:$B$152, 2, FALSE),0) -> 60.48 | P13: =ifna(VLOOKUP(A13, marco24!$A$127:$B$152, 2, FALSE),0) -> 67.49 | Q13: =ifna(VLOOKUP(A13, abril24!$A$127:$B$152, 2, FALSE),0) -> 132.1 | R13: =ifna(VLOOKUP(A13, maio24!$A$127:$B$152, 2, FALSE),0) -> 34.17 | S13: =ifna(VLOOKUP(A13, 'jun24'!$A$127:$B$152, 2, FALSE),0) -> 167.73 | T13: =ifna(VLOOKUP(A13, 'set24'!$A$127:$B$152, 2, FALSE),0) -> 69.54 | U13: =ifna(VLOOKUP(A13, 'jan25'!$A$127:$B$152, 2, FALSE),0) -> 140 | V13: =ifna(VLOOKUP(A13, 'fev25'!$A$132:$B$157, 2, FALSE),0) -> 25.33 | W13: =ifna(VLOOKUP(A13, 'mar25'!$A$125:$B$153, 2, FALSE),0) -> 79.88 | X13: =ifna(VLOOKUP(A13, 'abr25'!$A$131:$B$157, 2, FALSE),0) -> 171.34 | Y13: =ifna(VLOOKUP(A13, 'mai25'!$A$142:$B$174, 2, FALSE),0) -> 167.34 | Z13: =ifna(VLOOKUP(A13, 'jun25'!$A$141:$B$169, 2, FALSE),0) -> 49.98 | AA13: =ifna(VLOOKUP(A13, 'jul25'!$A$141:$B$170, 2, FALSE),0) -> 71.97 | AB13: =ifna(VLOOKUP(A13, 'ago25'!$A$141:$B$170, 2, FALSE),0) -> 69.89 | AC13: =AVERAGE(X13:AA13) -> 115.1575
A14: seguro | B14: =Janeiro23!B63 -> 206.99 | C14: =fevereiro23!B93 -> 206.99 | D14: =ifna(VLOOKUP(A14, marco23!$A$97:$B$119, 2, FALSE),0) -> 206.99 | E14: =ifna(VLOOKUP(A14, abril23!$A$82:$B$103, 2, FALSE),0) -> 206.99 | F14: =ifna(VLOOKUP(A14, maio23!$A$95:$B$117, 2, FALSE),0) -> 206.99 | G14: =ifna(VLOOKUP(A14, junho23!$A$127:$B$152, 2, FALSE),0) -> 206.99 | H14: =ifna(VLOOKUP(A14, julho23!$A$139:$B$164, 2, FALSE),0) -> 206.99 | I14: =ifna(VLOOKUP(A14, Agosto23!$A$127:$B$152, 2, FALSE),0) -> 218.5 | J14: =ifna(VLOOKUP(A14, setembro23!$A$125:$B$151, 2, FALSE),0) -> 218.5 | K14: =ifna(VLOOKUP(A14, outubro23!$A$121:$B$146, 2, FALSE),0) -> 218.5 | L14: =ifna(VLOOKUP(A14, novembro23!$A$121:$B$146, 2, FALSE),0) -> 218.5 | M14: =ifna(VLOOKUP(A14, Dezembro23!$A$127:$B$152, 2, FALSE),0) -> 218.5 | N14: =ifna(VLOOKUP(A14, janneiro24!$A$127:$B$152, 2, FALSE),0) -> 218.5 | O14: =ifna(VLOOKUP(A14, fevereiro24!$A$127:$B$152, 2, FALSE),0) -> 218.5 | P14: =ifna(VLOOKUP(A14, marco24!$A$127:$B$152, 2, FALSE),0) -> 218.5 | Q14: =ifna(VLOOKUP(A14, abril24!$A$127:$B$152, 2, FALSE),0) -> 218.5 | R14: =ifna(VLOOKUP(A14, maio24!$A$127:$B$152, 2, FALSE),0) -> 218.5 | S14: =ifna(VLOOKUP(A14, 'jun24'!$A$127:$B$152, 2, FALSE),0) -> 218.5 | T14: =ifna(VLOOKUP(A14, 'set24'!$A$127:$B$152, 2, FALSE),0) -> 218.5 | U14: =ifna(VLOOKUP(A14, 'jan25'!$A$127:$B$152, 2, FALSE),0) -> 244.12 | V14: =ifna(VLOOKUP(A14, 'fev25'!$A$132:$B$157, 2, FALSE),0) -> 244.12 | W14: =ifna(VLOOKUP(A14, 'mar25'!$A$125:$B$153, 2, FALSE),0) -> 244.12 | X14: =ifna(VLOOKUP(A14, 'abr25'!$A$131:$B$157, 2, FALSE),0) -> 244.12 | Y14: =ifna(VLOOKUP(A14, 'mai25'!$A$142:$B$174, 2, FALSE),0) -> 244.12 | Z14: =ifna(VLOOKUP(A14, 'jun25'!$A$141:$B$169, 2, FALSE),0) -> 244.12 | AA14: =ifna(VLOOKUP(A14, 'jul25'!$A$141:$B$170, 2, FALSE),0) -> 244.12 | AB14: =ifna(VLOOKUP(A14, 'ago25'!$A$141:$B$170, 2, FALSE),0) -> 244.12 | AC14: =AVERAGE(X14:AA14) -> 244.12
A15: Energia | B15: =Janeiro23!B64 -> 450 | C15: =fevereiro23!B98 -> 510 | D15: =ifna(VLOOKUP(A15, marco23!$A$97:$B$119, 2, FALSE),0) -> 0 | E15: =ifna(VLOOKUP(A15, abril23!$A$82:$B$103, 2, FALSE),0) -> 1169.2 | F15: =ifna(VLOOKUP(A15, maio23!$A$95:$B$117, 2, FALSE),0) -> 550 | G15: =ifna(VLOOKUP(A15, junho23!$A$127:$B$152, 2, FALSE),0) -> 511 | H15: =ifna(VLOOKUP(A15, julho23!$A$139:$B$164, 2, FALSE),0) -> 511 | I15: =ifna(VLOOKUP(A15, Agosto23!$A$127:$B$152, 2, FALSE),0) -> 511 | J15: =ifna(VLOOKUP(A15, setembro23!$A$125:$B$151, 2, FALSE),0) -> 511 | K15: =ifna(VLOOKUP(A15, outubro23!$A$121:$B$146, 2, FALSE),0) -> 407 | L15: =ifna(VLOOKUP(A15, novembro23!$A$121:$B$146, 2, FALSE),0) -> 333.32 | M15: =ifna(VLOOKUP(A15, Dezembro23!$A$127:$B$152, 2, FALSE),0) -> 333.32 | N15: =ifna(VLOOKUP(A15, janneiro24!$A$127:$B$152, 2, FALSE),0) -> 333.32 | O15: =ifna(VLOOKUP(A15, fevereiro24!$A$127:$B$152, 2, FALSE),0) -> 800 | P15: =ifna(VLOOKUP(A15, marco24!$A$127:$B$152, 2, FALSE),0) -> 696.36 | Q15: =ifna(VLOOKUP(A15, abril24!$A$127:$B$152, 2, FALSE),0) -> 696.36 | R15: =ifna(VLOOKUP(A15, maio24!$A$127:$B$152, 2, FALSE),0) -> 696.36 | S15: =ifna(VLOOKUP(A15, 'jun24'!$A$127:$B$152, 2, FALSE),0) -> 696.36 | T15: =ifna(VLOOKUP(A15, 'set24'!$A$127:$B$152, 2, FALSE),0) -> 521.44 | U15: =ifna(VLOOKUP(A15, 'jan25'!$A$127:$B$152, 2, FALSE),0) -> 600 | V15: =ifna(VLOOKUP(A15, 'fev25'!$A$132:$B$157, 2, FALSE),0) -> 1160.14 | W15: =ifna(VLOOKUP(A15, 'mar25'!$A$125:$B$153, 2, FALSE),0) -> 0 | X15: =ifna(VLOOKUP(A15, 'abr25'!$A$131:$B$157, 2, FALSE),0) -> 600 | Y15: =ifna(VLOOKUP(A15, 'mai25'!$A$142:$B$174, 2, FALSE),0) -> 0 | Z15: =ifna(VLOOKUP(A15, 'jun25'!$A$141:$B$169, 2, FALSE),0) -> 356.67 | AA15: =ifna(VLOOKUP(A15, 'jul25'!$A$141:$B$170, 2, FALSE),0) -> 60 | AB15: =ifna(VLOOKUP(A15, 'ago25'!$A$141:$B$170, 2, FALSE),0) -> 118 | AC15: =AVERAGE(X15:AA15) -> 254.1675
A16: Pet | B16: =Janeiro23!B65 -> 544.55 | C16: =fevereiro23!B100 -> 772.97 | D16: =ifna(VLOOKUP(A16, marco23!$A$97:$B$119, 2, FALSE),0) -> 1115.05 | E16: =ifna(VLOOKUP(A16, abril23!$A$82:$B$103, 2, FALSE),0) -> 245.93 | F16: =ifna(VLOOKUP(A16, maio23!$A$95:$B$117, 2, FALSE),0) -> 1479.63 | G16: =ifna(VLOOKUP(A16, junho23!$A$127:$B$152, 2, FALSE),0) -> 2191.3 | H16: =ifna(VLOOKUP(A16, julho23!$A$139:$B$164, 2, FALSE),0) -> 2149.4 | I16: =ifna(VLOOKUP(A16, Agosto23!$A$127:$B$152, 2, FALSE),0) -> 623.87 | J16: =ifna(VLOOKUP(A16, setembro23!$A$125:$B$151, 2, FALSE),0) -> 1524.37 | K16: =ifna(VLOOKUP(A16, outubro23!$A$121:$B$146, 2, FALSE),0) -> 1903.49 | L16: =ifna(VLOOKUP(A16, novembro23!$A$121:$B$146, 2, FALSE),0) -> 860.2 | M16: =ifna(VLOOKUP(A16, Dezembro23!$A$127:$B$152, 2, FALSE),0) -> 3924.91 | N16: =ifna(VLOOKUP(A16, janneiro24!$A$127:$B$152, 2, FALSE),0) -> 5503.4 | O16: =ifna(VLOOKUP(A16, fevereiro24!$A$127:$B$152, 2, FALSE),0) -> 5503.4 | P16: =ifna(VLOOKUP(A16, marco24!$A$127:$B$152, 2, FALSE),0) -> 878.65 | Q16: =ifna(VLOOKUP(A16, abril24!$A$127:$B$152, 2, FALSE),0) -> 528.22 | R16: =ifna(VLOOKUP(A16, maio24!$A$127:$B$152, 2, FALSE),0) -> 1465.67 | S16: =ifna(VLOOKUP(A16, 'jun24'!$A$127:$B$152, 2, FALSE),0) -> 109.6 | T16: =ifna(VLOOKUP(A16, 'set24'!$A$127:$B$152, 2, FALSE),0) -> 919.52 | U16: =ifna(VLOOKUP(A16, 'jan25'!$A$127:$B$152, 2, FALSE),0) -> 0 | V16: =ifna(VLOOKUP(A16, 'fev25'!$A$132:$B$157, 2, FALSE),0) -> 697.2 | W16: =ifna(VLOOKUP(A16, 'mar25'!$A$125:$B$153, 2, FALSE),0) -> 1175.52 | X16: =ifna(VLOOKUP(A16, 'abr25'!$A$131:$B$157, 2, FALSE),0) -> 1194.88 | Y16: =ifna(VLOOKUP(A16, 'mai25'!$A$142:$B$174, 2, FALSE),0) -> 468.61 | Z16: =ifna(VLOOKUP(A16, 'jun25'!$A$141:$B$169, 2, FALSE),0) -> 771.5 | AA16: =ifna(VLOOKUP(A16, 'jul25'!$A$141:$B$170, 2, FALSE),0) -> 1370.74 | AB16: =ifna(VLOOKUP(A16, 'ago25'!$A$141:$B$170, 2, FALSE),0) -> 1214.68 | AC16: =AVERAGE(X16:AA16) -> 951.4325
A17: mercado | B17: =Janeiro23!B68 -> 1228.08 | C17: =fevereiro23!B99 -> 585.69 | D17: =ifna(VLOOKUP(A17, marco23!$A$97:$B$119, 2, FALSE),0) -> 1025.47 | E17: =ifna(VLOOKUP(A17, abril23!$A$82:$B$103, 2, FALSE),0) -> 648.42 | F17: =ifna(VLOOKUP(A17, maio23!$A$95:$B$117, 2, FALSE),0) -> 1382.2 | G17: =ifna(VLOOKUP(A17, junho23!$A$127:$B$152, 2, FALSE),0) -> 1493.65 | H17: =ifna(VLOOKUP(A17, julho23!$A$139:$B$164, 2, FALSE),0) -> 1015.78 | I17: =ifna(VLOOKUP(A17, Agosto23!$A$127:$B$152, 2, FALSE),0) -> 1151.82 | J17: =ifna(VLOOKUP(A17, setembro23!$A$125:$B$151, 2, FALSE),0) -> 1202.85 | K17: =ifna(VLOOKUP(A17, outubro23!$A$121:$B$146, 2, FALSE),0) -> 1284.31 | L17: =ifna(VLOOKUP(A17, novembro23!$A$121:$B$146, 2, FALSE),0) -> 1069.75 | M17: =ifna(VLOOKUP(A17, Dezembro23!$A$127:$B$152, 2, FALSE),0) -> 736.04 | N17: =ifna(VLOOKUP(A17, janneiro24!$A$127:$B$152, 2, FALSE),0) -> 269.24 | O17: =ifna(VLOOKUP(A17, fevereiro24!$A$127:$B$152, 2, FALSE),0) -> 269.24 | P17: =ifna(VLOOKUP(A17, marco24!$A$127:$B$152, 2, FALSE),0) -> 1213.51 | Q17: =ifna(VLOOKUP(A17, abril24!$A$127:$B$152, 2, FALSE),0) -> 1143.95 | R17: =ifna(VLOOKUP(A17, maio24!$A$127:$B$152, 2, FALSE),0) -> 1473.36 | S17: =ifna(VLOOKUP(A17, 'jun24'!$A$127:$B$152, 2, FALSE),0) -> 720.21 | T17: =ifna(VLOOKUP(A17, 'set24'!$A$127:$B$152, 2, FALSE),0) -> 558.25 | U17: =ifna(VLOOKUP(A17, 'jan25'!$A$127:$B$152, 2, FALSE),0) -> 0 | V17: =ifna(VLOOKUP(A17, 'fev25'!$A$132:$B$157, 2, FALSE),0) -> 1423.03 | W17: =ifna(VLOOKUP(A17, 'mar25'!$A$125:$B$153, 2, FALSE),0) -> 993.2 | X17: =ifna(VLOOKUP(A17, 'abr25'!$A$131:$B$157, 2, FALSE),0) -> 1177.36 | Y17: =ifna(VLOOKUP(A17, 'mai25'!$A$142:$B$174, 2, FALSE),0) -> 1670.69 | Z17: =ifna(VLOOKUP(A17, 'jun25'!$A$141:$B$169, 2, FALSE),0) -> 1179.08 | AA17: =ifna(VLOOKUP(A17, 'jul25'!$A$141:$B$170, 2, FALSE),0) -> 1083.14 | AB17: =ifna(VLOOKUP(A17, 'ago25'!$A$141:$B$170, 2, FALSE),0) -> 1151.27 | AC17: =AVERAGE(X17:AA17) -> 1277.5675
A18: Cabeleireiro | B18: =0 -> 0 | C18: =fevereiro23!B84 -> 38 | D18: =ifna(VLOOKUP(A18, marco23!$A$97:$B$119, 2, FALSE),0) -> 0 | E18: =ifna(VLOOKUP(A18, abril23!$A$82:$B$103, 2, FALSE),0) -> 0 | F18: =ifna(VLOOKUP(A18, maio23!$A$95:$B$117, 2, FALSE),0) -> 0 | G18: =ifna(VLOOKUP(A18, junho23!$A$127:$B$152, 2, FALSE),0) -> 0 | H18: =ifna(VLOOKUP(A18, julho23!$A$139:$B$164, 2, FALSE),0) -> 0 | I18: =ifna(VLOOKUP(A18, Agosto23!$A$127:$B$152, 2, FALSE),0) -> 0 | J18: =ifna(VLOOKUP(A18, setembro23!$A$125:$B$151, 2, FALSE),0) -> 0 | K18: =ifna(VLOOKUP(A18, outubro23!$A$121:$B$146, 2, FALSE),0) -> 0 | L18: =ifna(VLOOKUP(A18, novembro23!$A$121:$B$146, 2, FALSE),0) -> 0 | M18: =ifna(VLOOKUP(A18, Dezembro23!$A$127:$B$152, 2, FALSE),0) -> 55 | N18: =ifna(VLOOKUP(A18, janneiro24!$A$127:$B$152, 2, FALSE),0) -> 0 | O18: =ifna(VLOOKUP(A18, fevereiro24!$A$127:$B$152, 2, FALSE),0) -> 0 | P18: =ifna(VLOOKUP(A18, marco24!$A$127:$B$152, 2, FALSE),0) -> 0 | Q18: =ifna(VLOOKUP(A18, abril24!$A$127:$B$152, 2, FALSE),0) -> 105 | R18: =ifna(VLOOKUP(A18, maio24!$A$127:$B$152, 2, FALSE),0) -> 0 | S18: =ifna(VLOOKUP(A18, 'jun24'!$A$127:$B$152, 2, FALSE),0) -> 0 | T18: =ifna(VLOOKUP(A18, 'set24'!$A$127:$B$152, 2, FALSE),0) -> 0 | U18: =ifna(VLOOKUP(A18, 'jan25'!$A$127:$B$152, 2, FALSE),0) -> 0 | V18: =ifna(VLOOKUP(A18, 'fev25'!$A$132:$B$157, 2, FALSE),0) -> 0 | W18: =ifna(VLOOKUP(A18, 'mar25'!$A$125:$B$153, 2, FALSE),0) -> 40 | X18: =ifna(VLOOKUP(A18, 'abr25'!$A$131:$B$157, 2, FALSE),0) -> 0 | Y18: =ifna(VLOOKUP(A18, 'mai25'!$A$142:$B$174, 2, FALSE),0) -> 0 | Z18: =ifna(VLOOKUP(A18, 'jun25'!$A$141:$B$169, 2, FALSE),0) -> 40 | AA18: =ifna(VLOOKUP(A18, 'jul25'!$A$141:$B$170, 2, FALSE),0) -> 0 | AB18: =ifna(VLOOKUP(A18, 'ago25'!$A$141:$B$170, 2, FALSE),0) -> 0 | AC18: =AVERAGE(X18:AA18) -> 10
A19: Vestuario | B19: =0 -> 0 | C19: =fevereiro23!B87 -> 89.99 | D19: =ifna(VLOOKUP(A19, marco23!$A$97:$B$119, 2, FALSE),0) -> 274.92 | E19: =ifna(VLOOKUP(A19, abril23!$A$82:$B$103, 2, FALSE),0) -> 0 | F19: =ifna(VLOOKUP(A19, maio23!$A$95:$B$117, 2, FALSE),0) -> 266.14 | G19: =ifna(VLOOKUP(A19, junho23!$A$127:$B$152, 2, FALSE),0) -> 0 | H19: =ifna(VLOOKUP(A19, julho23!$A$139:$B$164, 2, FALSE),0) -> 29.99 | I19: =ifna(VLOOKUP(A19, Agosto23!$A$127:$B$152, 2, FALSE),0) -> 0 | J19: =ifna(VLOOKUP(A19, setembro23!$A$125:$B$151, 2, FALSE),0) -> 121.42 | K19: =ifna(VLOOKUP(A19, outubro23!$A$121:$B$146, 2, FALSE),0) -> 149.99 | L19: =ifna(VLOOKUP(A19, novembro23!$A$121:$B$146, 2, FALSE),0) -> 460.99 | M19: =ifna(VLOOKUP(A19, Dezembro23!$A$127:$B$152, 2, FALSE),0) -> 569.87 | N19: =ifna(VLOOKUP(A19, janneiro24!$A$127:$B$152, 2, FALSE),0) -> 109.95 | O19: =ifna(VLOOKUP(A19, fevereiro24!$A$127:$B$152, 2, FALSE),0) -> 109.95 | P19: =ifna(VLOOKUP(A19, marco24!$A$127:$B$152, 2, FALSE),0) -> 280.87 | Q19: =ifna(VLOOKUP(A19, abril24!$A$127:$B$152, 2, FALSE),0) -> 84.9 | R19: =ifna(VLOOKUP(A19, maio24!$A$127:$B$152, 2, FALSE),0) -> 386.68 | S19: =ifna(VLOOKUP(A19, 'jun24'!$A$127:$B$152, 2, FALSE),0) -> 204.69 | T19: =ifna(VLOOKUP(A19, 'set24'!$A$127:$B$152, 2, FALSE),0) -> 0 | U19: =ifna(VLOOKUP(A19, 'jan25'!$A$127:$B$152, 2, FALSE),0) -> 0 | V19: =ifna(VLOOKUP(A19, 'fev25'!$A$132:$B$157, 2, FALSE),0) -> 0 | W19: =ifna(VLOOKUP(A19, 'mar25'!$A$125:$B$153, 2, FALSE),0) -> 324.93 | X19: =ifna(VLOOKUP(A19, 'abr25'!$A$131:$B$157, 2, FALSE),0) -> 305.69 | Y19: =ifna(VLOOKUP(A19, 'mai25'!$A$142:$B$174, 2, FALSE),0) -> 199.96 | Z19: =ifna(VLOOKUP(A19, 'jun25'!$A$141:$B$169, 2, FALSE),0) -> 164.97 | AA19: =ifna(VLOOKUP(A19, 'jul25'!$A$141:$B$170, 2, FALSE),0) -> 364.93 | AB19: =ifna(VLOOKUP(A19, 'ago25'!$A$141:$B$170, 2, FALSE),0) -> 968.53 | AC19: =AVERAGE(X19:AA19) -> 258.8875
A20: outros | B20: =0 -> 0 | C20: =fevereiro23!B92 -> 200 | D20: =ifna(VLOOKUP(A20, marco23!$A$97:$B$119, 2, FALSE),0) -> 0 | E20: =ifna(VLOOKUP(A20, abril23!$A$82:$B$103, 2, FALSE),0) -> 100 | F20: =ifna(VLOOKUP(A20, maio23!$A$95:$B$117, 2, FALSE),0) -> 0 | G20: =ifna(VLOOKUP(A20, junho23!$A$127:$B$152, 2, FALSE),0) -> 0 | H20: =ifna(VLOOKUP(A20, julho23!$A$139:$B$164, 2, FALSE),0) -> 0 | I20: =ifna(VLOOKUP(A20, Agosto23!$A$127:$B$152, 2, FALSE),0) -> 100 | J20: =ifna(VLOOKUP(A20, setembro23!$A$125:$B$151, 2, FALSE),0) -> 175.54 | K20: =ifna(VLOOKUP(A20, outubro23!$A$121:$B$146, 2, FALSE),0) -> 156.9 | L20: =ifna(VLOOKUP(A20, novembro23!$A$121:$B$146, 2, FALSE),0) -> 385.26 | M20: =ifna(VLOOKUP(A20, Dezembro23!$A$127:$B$152, 2, FALSE),0) -> 525.9 | N20: =ifna(VLOOKUP(A20, janneiro24!$A$127:$B$152, 2, FALSE),0) -> 0 | O20: =ifna(VLOOKUP(A20, fevereiro24!$A$127:$B$152, 2, FALSE),0) -> 0 | P20: =ifna(VLOOKUP(A20, marco24!$A$127:$B$152, 2, FALSE),0) -> 215.36 | Q20: =ifna(VLOOKUP(A20, abril24!$A$127:$B$152, 2, FALSE),0) -> 89.99 | R20: =ifna(VLOOKUP(A20, maio24!$A$127:$B$152, 2, FALSE),0) -> 257.43 | S20: =ifna(VLOOKUP(A20, 'jun24'!$A$127:$B$152, 2, FALSE),0) -> 40.99 | T20: =ifna(VLOOKUP(A20, 'set24'!$A$127:$B$152, 2, FALSE),0) -> 41 | U20: =ifna(VLOOKUP(A20, 'jan25'!$A$127:$B$152, 2, FALSE),0) -> 0 | V20: =ifna(VLOOKUP(A20, 'fev25'!$A$132:$B$157, 2, FALSE),0) -> 282.25 | W20: =ifna(VLOOKUP(A20, 'mar25'!$A$125:$B$153, 2, FALSE),0) -> 814.77 | X20: =ifna(VLOOKUP(A20, 'abr25'!$A$131:$B$157, 2, FALSE),0) -> 406.27 | Y20: =ifna(VLOOKUP(A20, 'mai25'!$A$142:$B$174, 2, FALSE),0) -> 108.44 | Z20: =ifna(VLOOKUP(A20, 'jun25'!$A$141:$B$169, 2, FALSE),0) -> 631.82 | AA20: =ifna(VLOOKUP(A20, 'jul25'!$A$141:$B$170, 2, FALSE),0) -> 40 | AB20: =ifna(VLOOKUP(A20, 'ago25'!$A$141:$B$170, 2, FALSE),0) -> 153.71 | AC20: =AVERAGE(X20:AA20) -> 296.6325
A21: utilizades domesticas | B21: 0 | C21: =fevereiro23!B94 -> 261.83 | D21: =ifna(VLOOKUP(A21, marco23!$A$97:$B$119, 2, FALSE),0) -> 139.07 | E21: =ifna(VLOOKUP(A21, abril23!$A$82:$B$103, 2, FALSE),0) -> 142.18 | F21: =ifna(VLOOKUP(A21, maio23!$A$95:$B$117, 2, FALSE),0) -> 0 | G21: =ifna(VLOOKUP(A21, junho23!$A$127:$B$152, 2, FALSE),0) -> 0 | H21: =ifna(VLOOKUP(A21, julho23!$A$139:$B$164, 2, FALSE),0) -> 86.08 | I21: =ifna(VLOOKUP(A21, Agosto23!$A$127:$B$152, 2, FALSE),0) -> 226.33 | J21: =ifna(VLOOKUP(A21, setembro23!$A$125:$B$151, 2, FALSE),0) -> 180 | K21: =ifna(VLOOKUP(A21, outubro23!$A$121:$B$146, 2, FALSE),0) -> 252.36 | L21: =ifna(VLOOKUP(A21, novembro23!$A$121:$B$146, 2, FALSE),0) -> 0 | M21: =ifna(VLOOKUP(A21, Dezembro23!$A$127:$B$152, 2, FALSE),0) -> 25.99 | N21: =ifna(VLOOKUP(A21, janneiro24!$A$127:$B$152, 2, FALSE),0) -> 0 | O21: =ifna(VLOOKUP(A21, fevereiro24!$A$127:$B$152, 2, FALSE),0) -> 0 | P21: =ifna(VLOOKUP(A21, marco24!$A$127:$B$152, 2, FALSE),0) -> 0 | Q21: =ifna(VLOOKUP(A21, abril24!$A$127:$B$152, 2, FALSE),0) -> 0 | R21: =ifna(VLOOKUP(A21, maio24!$A$127:$B$152, 2, FALSE),0) -> 0 | S21: =ifna(VLOOKUP(A21, 'jun24'!$A$127:$B$152, 2, FALSE),0) -> 0 | T21: =ifna(VLOOKUP(A21, 'set24'!$A$127:$B$152, 2, FALSE),0) -> 0 | U21: =ifna(VLOOKUP(A21, 'jan25'!$A$127:$B$152, 2, FALSE),0) -> 0 | V21: =ifna(VLOOKUP(A21, 'fev25'!$A$132:$B$157, 2, FALSE),0) -> 33.5 | W21: =ifna(VLOOKUP(A21, 'mar25'!$A$125:$B$153, 2, FALSE),0) -> 96.4 | X21: =ifna(VLOOKUP(A21, 'abr25'!$A$131:$B$157, 2, FALSE),0) -> 180.87 | Y21: =ifna(VLOOKUP(A21, 'mai25'!$A$142:$B$174, 2, FALSE),0) -> 32.86 | Z21: =ifna(VLOOKUP(A21, 'jun25'!$A$141:$B$169, 2, FALSE),0) -> 17.94 | AA21: =ifna(VLOOKUP(A21, 'jul25'!$A$141:$B$170, 2, FALSE),0) -> 0 | AB21: =ifna(VLOOKUP(A21, 'ago25'!$A$141:$B$170, 2, FALSE),0) -> 0 | AC21: =AVERAGE(X21:AA21) -> 57.9175
A22: Lazer | B22: 0 | C22: =fevereiro23!B96 -> 454.76 | D22: =ifna(VLOOKUP(A22, marco23!$A$97:$B$119, 2, FALSE),0) -> 443.82 | E22: =ifna(VLOOKUP(A22, abril23!$A$82:$B$103, 2, FALSE),0) -> 155.1 | F22: =ifna(VLOOKUP(A22, maio23!$A$95:$B$117, 2, FALSE),0) -> 371.54 | G22: =ifna(VLOOKUP(A22, junho23!$A$127:$B$152, 2, FALSE),0) -> 515.7 | H22: =ifna(VLOOKUP(A22, julho23!$A$139:$B$164, 2, FALSE),0) -> 142.9 | I22: =ifna(VLOOKUP(A22, Agosto23!$A$127:$B$152, 2, FALSE),0) -> 655.65 | J22: =ifna(VLOOKUP(A22, setembro23!$A$125:$B$151, 2, FALSE),0) -> 199.6 | K22: =ifna(VLOOKUP(A22, outubro23!$A$121:$B$146, 2, FALSE),0) -> 423.42 | L22: =ifna(VLOOKUP(A22, novembro23!$A$121:$B$146, 2, FALSE),0) -> 457.02 | M22: =ifna(VLOOKUP(A22, Dezembro23!$A$127:$B$152, 2, FALSE),0) -> 414.68 | N22: =ifna(VLOOKUP(A22, janneiro24!$A$127:$B$152, 2, FALSE),0) -> 90 | O22: =ifna(VLOOKUP(A22, fevereiro24!$A$127:$B$152, 2, FALSE),0) -> 90 | P22: =ifna(VLOOKUP(A22, marco24!$A$127:$B$152, 2, FALSE),0) -> 90 | Q22: =ifna(VLOOKUP(A22, abril24!$A$127:$B$152, 2, FALSE),0) -> 357.45 | R22: =ifna(VLOOKUP(A22, maio24!$A$127:$B$152, 2, FALSE),0) -> 209.7 | S22: =ifna(VLOOKUP(A22, 'jun24'!$A$127:$B$152, 2, FALSE),0) -> 636.16 | T22: =ifna(VLOOKUP(A22, 'set24'!$A$127:$B$152, 2, FALSE),0) -> 169.9 | U22: =ifna(VLOOKUP(A22, 'jan25'!$A$127:$B$152, 2, FALSE),0) -> 60 | V22: =ifna(VLOOKUP(A22, 'fev25'!$A$132:$B$157, 2, FALSE),0) -> 546.88 | W22: =ifna(VLOOKUP(A22, 'mar25'!$A$125:$B$153, 2, FALSE),0) -> 282.49 | X22: =ifna(VLOOKUP(A22, 'abr25'!$A$131:$B$157, 2, FALSE),0) -> 354.38 | Y22: =ifna(VLOOKUP(A22, 'mai25'!$A$142:$B$174, 2, FALSE),0) -> 294.93 | Z22: =ifna(VLOOKUP(A22, 'jun25'!$A$141:$B$169, 2, FALSE),0) -> 768.33 | AA22: =ifna(VLOOKUP(A22, 'jul25'!$A$141:$B$170, 2, FALSE),0) -> 847.76 | AB22: =ifna(VLOOKUP(A22, 'ago25'!$A$141:$B$170, 2, FALSE),0) -> 1320.52 | AC22: =AVERAGE(X22:AA22) -> 566.35
A23: material escolar | B23: =0 -> 0 | C23: =fevereiro23!B101 -> 829.1 | D23: =ifna(VLOOKUP(A23, marco23!$A$97:$B$119, 2, FALSE),0) -> 737 | E23: =ifna(VLOOKUP(A23, abril23!$A$82:$B$103, 2, FALSE),0) -> 33.47 | F23: =ifna(VLOOKUP(A23, maio23!$A$95:$B$117, 2, FALSE),0) -> 32.94 | G23: =ifna(VLOOKUP(A23, junho23!$A$127:$B$152, 2, FALSE),0) -> 8.46 | H23: =ifna(VLOOKUP(A23, julho23!$A$139:$B$164, 2, FALSE),0) -> 0 | I23: =ifna(VLOOKUP(A23, Agosto23!$A$127:$B$152, 2, FALSE),0) -> 125.12 | J23: =ifna(VLOOKUP(A23, setembro23!$A$125:$B$151, 2, FALSE),0) -> 0 | K23: =ifna(VLOOKUP(A23, outubro23!$A$121:$B$146, 2, FALSE),0) -> 0 | L23: =ifna(VLOOKUP(A23, novembro23!$A$121:$B$146, 2, FALSE),0) -> 0 | M23: =ifna(VLOOKUP(A23, Dezembro23!$A$127:$B$152, 2, FALSE),0) -> 0 | N23: =ifna(VLOOKUP(A23, janneiro24!$A$127:$B$152, 2, FALSE),0) -> 0 | O23: =ifna(VLOOKUP(A23, fevereiro24!$A$127:$B$152, 2, FALSE),0) -> 0 | P23: =ifna(VLOOKUP(A23, marco24!$A$127:$B$152, 2, FALSE),0) -> 0 | Q23: =ifna(VLOOKUP(A23, abril24!$A$127:$B$152, 2, FALSE),0) -> 0 | R23: =ifna(VLOOKUP(A23, maio24!$A$127:$B$152, 2, FALSE),0) -> 0 | S23: =ifna(VLOOKUP(A23, 'jun24'!$A$127:$B$152, 2, FALSE),0) -> 0 | T23: =ifna(VLOOKUP(A23, 'set24'!$A$127:$B$152, 2, FALSE),0) -> 0 | U23: =ifna(VLOOKUP(A23, 'jan25'!$A$127:$B$152, 2, FALSE),0) -> 0 | V23: =ifna(VLOOKUP(A23, 'fev25'!$A$132:$B$157, 2, FALSE),0) -> 1638 | W23: =ifna(VLOOKUP(A23, 'mar25'!$A$125:$B$153, 2, FALSE),0) -> 0 | X23: =ifna(VLOOKUP(A23, 'abr25'!$A$131:$B$157, 2, FALSE),0) -> 0 | Y23: =ifna(VLOOKUP(A23, 'mai25'!$A$142:$B$174, 2, FALSE),0) -> 48.73 | Z23: =ifna(VLOOKUP(A23, 'jun25'!$A$141:$B$169, 2, FALSE),0) -> 0 | AA23: =ifna(VLOOKUP(A23, 'jul25'!$A$141:$B$170, 2, FALSE),0) -> 39.97 | AB23: =ifna(VLOOKUP(A23, 'ago25'!$A$141:$B$170, 2, FALSE),0) -> 26.5 | AC23: =AVERAGE(X23:AA23) -> 22.175
A24: Uber | B24: =0 -> 0 | C24: =0 -> 0 | D24: =ifna(VLOOKUP(A24, marco23!$A$97:$B$119, 2, FALSE),0) -> 40.83 | E24: =ifna(VLOOKUP(A24, abril23!$A$82:$B$103, 2, FALSE),0) -> 0 | F24: =ifna(VLOOKUP(A24, maio23!$A$95:$B$117, 2, FALSE),0) -> 0 | G24: =ifna(VLOOKUP(A24, junho23!$A$127:$B$152, 2, FALSE),0) -> 0 | H24: =ifna(VLOOKUP(A24, julho23!$A$139:$B$164, 2, FALSE),0) -> 0 | I24: =ifna(VLOOKUP(A24, Agosto23!$A$127:$B$152, 2, FALSE),0) -> 0 | J24: =ifna(VLOOKUP(A24, setembro23!$A$125:$B$151, 2, FALSE),0) -> 0 | K24: =ifna(VLOOKUP(A24, outubro23!$A$121:$B$146, 2, FALSE),0) -> 0 | L24: =ifna(VLOOKUP(A24, novembro23!$A$121:$B$146, 2, FALSE),0) -> 0 | M24: =ifna(VLOOKUP(A24, Dezembro23!$A$127:$B$152, 2, FALSE),0) -> 0 | N24: =ifna(VLOOKUP(A24, janneiro24!$A$127:$B$152, 2, FALSE),0) -> 0 | O24: =ifna(VLOOKUP(A24, fevereiro24!$A$127:$B$152, 2, FALSE),0) -> 0 | P24: =ifna(VLOOKUP(A24, marco24!$A$127:$B$152, 2, FALSE),0) -> 0 | Q24: =ifna(VLOOKUP(A24, abril24!$A$127:$B$152, 2, FALSE),0) -> 0 | R24: =ifna(VLOOKUP(A24, maio24!$A$127:$B$152, 2, FALSE),0) -> 0 | S24: =ifna(VLOOKUP(A24, 'jun24'!$A$127:$B$152, 2, FALSE),0) -> 0 | T24: =ifna(VLOOKUP(A24, 'set24'!$A$127:$B$152, 2, FALSE),0) -> 0 | U24: =ifna(VLOOKUP(A24, 'jan25'!$A$127:$B$152, 2, FALSE),0) -> 0 | V24: =ifna(VLOOKUP(A24, 'fev25'!$A$132:$B$157, 2, FALSE),0) -> 0 | W24: =ifna(VLOOKUP(A24, 'mar25'!$A$125:$B$153, 2, FALSE),0) -> 0 | X24: =ifna(VLOOKUP(A24, 'abr25'!$A$131:$B$157, 2, FALSE),0) -> 0 | Y24: =ifna(VLOOKUP(A24, 'mai25'!$A$142:$B$174, 2, FALSE),0) -> 0 | Z24: =ifna(VLOOKUP(A24, 'jun25'!$A$141:$B$169, 2, FALSE),0) -> 0 | AA24: =ifna(VLOOKUP(A24, 'jul25'!$A$141:$B$170, 2, FALSE),0) -> 0 | AB24: =ifna(VLOOKUP(A24, 'ago25'!$A$141:$B$170, 2, FALSE),0) -> 0 | AC24: =AVERAGE(X24:AA24) -> 0
A25: Iptu | B25: =0 -> 0 | C25: =0 -> 0 | D25: =ifna(VLOOKUP(A25, marco23!$A$97:$B$119, 2, FALSE),0) -> 64.9 | E25: =ifna(VLOOKUP(A25, abril23!$A$82:$B$103, 2, FALSE),0) -> 0 | F25: =ifna(VLOOKUP(A25, maio23!$A$95:$B$117, 2, FALSE),0) -> 0 | G25: =ifna(VLOOKUP(A25, junho23!$A$127:$B$152, 2, FALSE),0) -> 0 | H25: =ifna(VLOOKUP(A25, julho23!$A$139:$B$164, 2, FALSE),0) -> 0 | I25: =ifna(VLOOKUP(A25, Agosto23!$A$127:$B$152, 2, FALSE),0) -> 0 | J25: =ifna(VLOOKUP(A25, setembro23!$A$125:$B$151, 2, FALSE),0) -> 0 | K25: =ifna(VLOOKUP(A25, outubro23!$A$121:$B$146, 2, FALSE),0) -> 0 | L25: =ifna(VLOOKUP(A25, novembro23!$A$121:$B$146, 2, FALSE),0) -> 0 | M25: =ifna(VLOOKUP(A25, Dezembro23!$A$127:$B$152, 2, FALSE),0) -> 0 | N25: =ifna(VLOOKUP(A25, janneiro24!$A$127:$B$152, 2, FALSE),0) -> 0 | O25: =ifna(VLOOKUP(A25, fevereiro24!$A$127:$B$152, 2, FALSE),0) -> 0 | P25: =ifna(VLOOKUP(A25, marco24!$A$127:$B$152, 2, FALSE),0) -> 0 | Q25: =ifna(VLOOKUP(A25, abril24!$A$127:$B$152, 2, FALSE),0) -> 0 | R25: =ifna(VLOOKUP(A25, maio24!$A$127:$B$152, 2, FALSE),0) -> 0 | S25: =ifna(VLOOKUP(A25, 'jun24'!$A$127:$B$152, 2, FALSE),0) -> 0 | T25: =ifna(VLOOKUP(A25, 'set24'!$A$127:$B$152, 2, FALSE),0) -> 0 | U25: =ifna(VLOOKUP(A25, 'jan25'!$A$127:$B$152, 2, FALSE),0) -> 0 | V25: =ifna(VLOOKUP(A25, 'fev25'!$A$132:$B$157, 2, FALSE),0) -> 0 | W25: =ifna(VLOOKUP(A25, 'mar25'!$A$125:$B$153, 2, FALSE),0) -> 0 | X25: =ifna(VLOOKUP(A25, 'abr25'!$A$131:$B$157, 2, FALSE),0) -> 0 | Y25: =ifna(VLOOKUP(A25, 'mai25'!$A$142:$B$174, 2, FALSE),0) -> 0 | Z25: =ifna(VLOOKUP(A25, 'jun25'!$A$141:$B$169, 2, FALSE),0) -> 0 | AA25: =ifna(VLOOKUP(A25, 'jul25'!$A$141:$B$170, 2, FALSE),0) -> 0 | AB25: =ifna(VLOOKUP(A25, 'ago25'!$A$141:$B$170, 2, FALSE),0) -> 0 | AC25: =AVERAGE(X25:AA25) -> 0
A26: manutencao veiculo | B26: =0 -> 0 | C26: =0 -> 0 | D26: =ifna(VLOOKUP(A26, marco23!$A$97:$B$119, 2, FALSE),0) -> 693 | E26: =ifna(VLOOKUP(A26, abril23!$A$82:$B$103, 2, FALSE),0) -> 0 | F26: =ifna(VLOOKUP(A26, maio23!$A$95:$B$117, 2, FALSE),0) -> 0 | G26: =ifna(VLOOKUP(A26, junho23!$A$127:$B$152, 2, FALSE),0) -> 0 | H26: =ifna(VLOOKUP(A26, julho23!$A$139:$B$164, 2, FALSE),0) -> 72 | I26: =ifna(VLOOKUP(A26, Agosto23!$A$127:$B$152, 2, FALSE),0) -> 0 | J26: =ifna(VLOOKUP(A26, setembro23!$A$125:$B$151, 2, FALSE),0) -> 0 | K26: =ifna(VLOOKUP(A26, outubro23!$A$121:$B$146, 2, FALSE),0) -> 0 | L26: =ifna(VLOOKUP(A26, novembro23!$A$121:$B$146, 2, FALSE),0) -> 0 | M26: =ifna(VLOOKUP(A26, Dezembro23!$A$127:$B$152, 2, FALSE),0) -> 32 | N26: =ifna(VLOOKUP(A26, janneiro24!$A$127:$B$152, 2, FALSE),0) -> 0 | O26: =ifna(VLOOKUP(A26, fevereiro24!$A$127:$B$152, 2, FALSE),0) -> 0 | P26: =ifna(VLOOKUP(A26, marco24!$A$127:$B$152, 2, FALSE),0) -> 0 | Q26: =ifna(VLOOKUP(A26, abril24!$A$127:$B$152, 2, FALSE),0) -> 0 | R26: =ifna(VLOOKUP(A26, maio24!$A$127:$B$152, 2, FALSE),0) -> 0 | S26: =ifna(VLOOKUP(A26, 'jun24'!$A$127:$B$152, 2, FALSE),0) -> 0 | T26: =ifna(VLOOKUP(A26, 'set24'!$A$127:$B$152, 2, FALSE),0) -> 0 | U26: =ifna(VLOOKUP(A26, 'jan25'!$A$127:$B$152, 2, FALSE),0) -> 0 | V26: =ifna(VLOOKUP(A26, 'fev25'!$A$132:$B$157, 2, FALSE),0) -> 0 | W26: =ifna(VLOOKUP(A26, 'mar25'!$A$125:$B$153, 2, FALSE),0) -> 0 | X26: =ifna(VLOOKUP(A26, 'abr25'!$A$131:$B$157, 2, FALSE),0) -> 0 | Y26: =ifna(VLOOKUP(A26, 'mai25'!$A$142:$B$174, 2, FALSE),0) -> 80.38 | Z26: =ifna(VLOOKUP(A26, 'jun25'!$A$141:$B$169, 2, FALSE),0) -> 0 | AA26: =ifna(VLOOKUP(A26, 'jul25'!$A$141:$B$170, 2, FALSE),0) -> 0 | AB26: =ifna(VLOOKUP(A26, 'ago25'!$A$141:$B$170, 2, FALSE),0) -> 0 | AC26: =AVERAGE(X26:AA26) -> 20.095
A27: Padaria | B27: =0 -> 0 | C27: =0 -> 0 | D27: =ifna(VLOOKUP(A27, marco23!$A$97:$B$119, 2, FALSE),0) -> 0 | E27: =ifna(VLOOKUP(A27, abril23!$A$82:$B$103, 2, FALSE),0) -> 12 | F27: =ifna(VLOOKUP(A27, maio23!$A$95:$B$117, 2, FALSE),0) -> 0 | G27: =ifna(VLOOKUP(A27, junho23!$A$127:$B$152, 2, FALSE),0) -> 36 | H27: =ifna(VLOOKUP(A27, julho23!$A$139:$B$164, 2, FALSE),0) -> 8 | I27: =ifna(VLOOKUP(A27, Agosto23!$A$127:$B$152, 2, FALSE),0) -> 29 | J27: =ifna(VLOOKUP(A27, setembro23!$A$125:$B$151, 2, FALSE),0) -> 38.4 | K27: =ifna(VLOOKUP(A27, outubro23!$A$121:$B$146, 2, FALSE),0) -> 34 | L27: =ifna(VLOOKUP(A27, novembro23!$A$121:$B$146, 2, FALSE),0) -> 38 | M27: =ifna(VLOOKUP(A27, Dezembro23!$A$127:$B$152, 2, FALSE),0) -> 46.4 | N27: =ifna(VLOOKUP(A27, janneiro24!$A$127:$B$152, 2, FALSE),0) -> 24.6 | O27: =ifna(VLOOKUP(A27, fevereiro24!$A$127:$B$152, 2, FALSE),0) -> 24.6 | P27: =ifna(VLOOKUP(A27, marco24!$A$127:$B$152, 2, FALSE),0) -> 51.5 | Q27: =ifna(VLOOKUP(A27, abril24!$A$127:$B$152, 2, FALSE),0) -> 24 | R27: =ifna(VLOOKUP(A27, maio24!$A$127:$B$152, 2, FALSE),0) -> 42 | S27: =ifna(VLOOKUP(A27, 'jun24'!$A$127:$B$152, 2, FALSE),0) -> 69.99 | T27: =ifna(VLOOKUP(A27, 'set24'!$A$127:$B$152, 2, FALSE),0) -> 27 | U27: =ifna(VLOOKUP(A27, 'jan25'!$A$127:$B$152, 2, FALSE),0) -> 0 | V27: =ifna(VLOOKUP(A27, 'fev25'!$A$132:$B$157, 2, FALSE),0) -> 38 | W27: =ifna(VLOOKUP(A27, 'mar25'!$A$125:$B$153, 2, FALSE),0) -> 48 | X27: =ifna(VLOOKUP(A27, 'abr25'!$A$131:$B$157, 2, FALSE),0) -> 56.13 | Y27: =ifna(VLOOKUP(A27, 'mai25'!$A$142:$B$174, 2, FALSE),0) -> 82.8 | Z27: =ifna(VLOOKUP(A27, 'jun25'!$A$141:$B$169, 2, FALSE),0) -> 60.7 | AA27: =ifna(VLOOKUP(A27, 'jul25'!$A$141:$B$170, 2, FALSE),0) -> 64 | AB27: =ifna(VLOOKUP(A27, 'ago25'!$A$141:$B$170, 2, FALSE),0) -> 439.35 | AC27: =AVERAGE(X27:AA27) -> 65.9075
A28: Manutenção casa | D28: =ifna(VLOOKUP(A28, marco23!$A$97:$B$119, 2, FALSE),0) -> 0 | E28: =ifna(VLOOKUP(A28, abril23!$A$82:$B$103, 2, FALSE),0) -> 0 | F28: =ifna(VLOOKUP(A28, maio23!$A$95:$B$117, 2, FALSE),0) -> 0 | G28: =ifna(VLOOKUP(A28, junho23!$A$127:$B$152, 2, FALSE),0) -> 145 | H28: =ifna(VLOOKUP(A28, julho23!$A$139:$B$164, 2, FALSE),0) -> 644.16 | I28: =ifna(VLOOKUP(A28, Agosto23!$A$127:$B$152, 2, FALSE),0) -> 0 | J28: =ifna(VLOOKUP(A28, setembro23!$A$125:$B$151, 2, FALSE),0) -> 0 | K28: =ifna(VLOOKUP(A28, outubro23!$A$121:$B$146, 2, FALSE),0) -> 0 | L28: =ifna(VLOOKUP(A28, novembro23!$A$121:$B$146, 2, FALSE),0) -> 0 | M28: =ifna(VLOOKUP(A28, Dezembro23!$A$127:$B$152, 2, FALSE),0) -> 0 | N28: =ifna(VLOOKUP(A28, janneiro24!$A$127:$B$152, 2, FALSE),0) -> 136.2 | O28: =ifna(VLOOKUP(A28, fevereiro24!$A$127:$B$152, 2, FALSE),0) -> 136.2 | P28: =ifna(VLOOKUP(A28, marco24!$A$127:$B$152, 2, FALSE),0) -> 0 | Q28: =ifna(VLOOKUP(A28, abril24!$A$127:$B$152, 2, FALSE),0) -> 0 | R28: =ifna(VLOOKUP(A28, maio24!$A$127:$B$152, 2, FALSE),0) -> 0 | S28: =ifna(VLOOKUP(A28, 'jun24'!$A$127:$B$152, 2, FALSE),0) -> 0 | T28: =ifna(VLOOKUP(A28, 'set24'!$A$127:$B$152, 2, FALSE),0) -> 0 | U28: =ifna(VLOOKUP(A28, 'jan25'!$A$127:$B$152, 2, FALSE),0) -> 0 | V28: =ifna(VLOOKUP(A28, 'fev25'!$A$132:$B$157, 2, FALSE),0) -> 0 | W28: =ifna(VLOOKUP(A28, 'mar25'!$A$125:$B$153, 2, FALSE),0) -> 81.4 | X28: =ifna(VLOOKUP(A28, 'abr25'!$A$131:$B$157, 2, FALSE),0) -> 109 | Y28: =ifna(VLOOKUP(A28, 'mai25'!$A$142:$B$174, 2, FALSE),0) -> 26.1 | Z28: =ifna(VLOOKUP(A28, 'jun25'!$A$141:$B$169, 2, FALSE),0) -> 0 | AA28: =ifna(VLOOKUP(A28, 'jul25'!$A$141:$B$170, 2, FALSE),0) -> 19.99 | AB28: =ifna(VLOOKUP(A28, 'ago25'!$A$141:$B$170, 2, FALSE),0) -> 77.8 | AC28: =AVERAGE(X28:AA28) -> 38.7725
A29: manutenção domiciliar | D29: =ifna(VLOOKUP(A29, marco23!$A$97:$B$119, 2, FALSE),0) -> 0 | E29: =ifna(VLOOKUP(A29, abril23!$A$82:$B$103, 2, FALSE),0) -> 0 | F29: =ifna(VLOOKUP(A29, maio23!$A$95:$B$117, 2, FALSE),0) -> 0 | G29: =ifna(VLOOKUP(A29, junho23!$A$127:$B$152, 2, FALSE),0) -> 62.9 | H29: =ifna(VLOOKUP(A29, julho23!$A$139:$B$164, 2, FALSE),0) -> 4 | I29: =ifna(VLOOKUP(A29, Agosto23!$A$127:$B$152, 2, FALSE),0) -> 45.5 | J29: =ifna(VLOOKUP(A29, setembro23!$A$125:$B$151, 2, FALSE),0) -> 50 | K29: =ifna(VLOOKUP(A29, outubro23!$A$121:$B$146, 2, FALSE),0) -> 70.84 | L29: =ifna(VLOOKUP(A29, novembro23!$A$121:$B$146, 2, FALSE),0) -> 418.57 | M29: =ifna(VLOOKUP(A29, Dezembro23!$A$127:$B$152, 2, FALSE),0) -> 28 | N29: =ifna(VLOOKUP(A29, janneiro24!$A$127:$B$152, 2, FALSE),0) -> 0 | O29: =ifna(VLOOKUP(A29, fevereiro24!$A$127:$B$152, 2, FALSE),0) -> 0 | P29: =ifna(VLOOKUP(A29, marco24!$A$127:$B$152, 2, FALSE),0) -> 279.9 | Q29: =ifna(VLOOKUP(A29, abril24!$A$127:$B$152, 2, FALSE),0) -> 455.46 | R29: =ifna(VLOOKUP(A29, maio24!$A$127:$B$152, 2, FALSE),0) -> 326.14 | S29: =ifna(VLOOKUP(A29, 'jun24'!$A$127:$B$152, 2, FALSE),0) -> 88.48 | T29: =ifna(VLOOKUP(A29, 'set24'!$A$127:$B$152, 2, FALSE),0) -> 0 | U29: =ifna(VLOOKUP(A29, 'jan25'!$A$127:$B$152, 2, FALSE),0) -> 0 | V29: =ifna(VLOOKUP(A29, 'fev25'!$A$132:$B$157, 2, FALSE),0) -> 1052.36 | W29: =ifna(VLOOKUP(A29, 'mar25'!$A$125:$B$153, 2, FALSE),0) -> 20 | X29: =ifna(VLOOKUP(A29, 'abr25'!$A$131:$B$157, 2, FALSE),0) -> 20 | Y29: =ifna(VLOOKUP(A29, 'mai25'!$A$142:$B$174, 2, FALSE),0) -> 550.99 | Z29: =ifna(VLOOKUP(A29, 'jun25'!$A$141:$B$169, 2, FALSE),0) -> 20 | AA29: =ifna(VLOOKUP(A29, 'jul25'!$A$141:$B$170, 2, FALSE),0) -> 93.59 | AB29: =ifna(VLOOKUP(A29, 'ago25'!$A$141:$B$170, 2, FALSE),0) -> 20 | AC29: =AVERAGE(X29:AA29) -> 171.145
A30: manutencao veicular | D30: =ifna(VLOOKUP(A30, marco23!$A$97:$B$119, 2, FALSE),0) -> 0 | E30: =ifna(VLOOKUP(A30, abril23!$A$82:$B$103, 2, FALSE),0) -> 650 | F30: =ifna(VLOOKUP(A30, maio23!$A$95:$B$117, 2, FALSE),0) -> 2097 | G30: =ifna(VLOOKUP(A30, junho23!$A$127:$B$152, 2, FALSE),0) -> 136.68 | H30: =ifna(VLOOKUP(A30, julho23!$A$139:$B$164, 2, FALSE),0) -> 312 | I30: =ifna(VLOOKUP(A30, Agosto23!$A$127:$B$152, 2, FALSE),0) -> 168.66 | J30: =ifna(VLOOKUP(A30, setembro23!$A$125:$B$151, 2, FALSE),0) -> 999.28 | K30: =ifna(VLOOKUP(A30, outubro23!$A$121:$B$146, 2, FALSE),0) -> 610 | L30: =ifna(VLOOKUP(A30, novembro23!$A$121:$B$146, 2, FALSE),0) -> 51 | M30: =ifna(VLOOKUP(A30, Dezembro23!$A$127:$B$152, 2, FALSE),0) -> 1087 | N30: =ifna(VLOOKUP(A30, janneiro24!$A$127:$B$152, 2, FALSE),0) -> 0 | O30: =ifna(VLOOKUP(A30, fevereiro24!$A$127:$B$152, 2, FALSE),0) -> 0 | P30: =ifna(VLOOKUP(A30, marco24!$A$127:$B$152, 2, FALSE),0) -> 1357 | Q30: =ifna(VLOOKUP(A30, abril24!$A$127:$B$152, 2, FALSE),0) -> 0 | R30: =ifna(VLOOKUP(A30, maio24!$A$127:$B$152, 2, FALSE),0) -> 0 | S30: =ifna(VLOOKUP(A30, 'jun24'!$A$127:$B$152, 2, FALSE),0) -> 0 | T30: =ifna(VLOOKUP(A30, 'set24'!$A$127:$B$152, 2, FALSE),0) -> 411 | U30: =ifna(VLOOKUP(A30, 'jan25'!$A$127:$B$152, 2, FALSE),0) -> 0 | V30: =ifna(VLOOKUP(A30, 'fev25'!$A$132:$B$157, 2, FALSE),0) -> 0 | W30: =ifna(VLOOKUP(A30, 'mar25'!$A$125:$B$153, 2, FALSE),0) -> 208.46 | X30: =ifna(VLOOKUP(A30, 'abr25'!$A$131:$B$157, 2, FALSE),0) -> 489.75 | Y30: =ifna(VLOOKUP(A30, 'mai25'!$A$142:$B$174, 2, FALSE),0) -> 0 | Z30: =ifna(VLOOKUP(A30, 'jun25'!$A$141:$B$169, 2, FALSE),0) -> 45 | AA30: =ifna(VLOOKUP(A30, 'jul25'!$A$141:$B$170, 2, FALSE),0) -> 0 | AB30: =ifna(VLOOKUP(A30, 'ago25'!$A$141:$B$170, 2, FALSE),0) -> 68 | AC30: =AVERAGE(X30:AA30) -> 133.6875
A31: ferias | D31: =ifna(VLOOKUP(A31, marco23!$A$97:$B$119, 2, FALSE),0) -> 0 | E31: =ifna(VLOOKUP(A31, abril23!$A$82:$B$103, 2, FALSE),0) -> 0 | F31: =ifna(VLOOKUP(A31, maio23!$A$95:$B$117, 2, FALSE),0) -> 0 | G31: =ifna(VLOOKUP(A31, junho23!$A$127:$B$152, 2, FALSE),0) -> 0 | H31: =ifna(VLOOKUP(A31, julho23!$A$139:$B$164, 2, FALSE),0) -> 3816.74 | I31: =ifna(VLOOKUP(A31, Agosto23!$A$127:$B$152, 2, FALSE),0) -> 0 | J31: =ifna(VLOOKUP(A31, setembro23!$A$125:$B$151, 2, FALSE),0) -> 160 | K31: =ifna(VLOOKUP(A31, outubro23!$A$121:$B$146, 2, FALSE),0) -> 0 | L31: =ifna(VLOOKUP(A31, novembro23!$A$121:$B$146, 2, FALSE),0) -> 0 | M31: =ifna(VLOOKUP(A31, Dezembro23!$A$127:$B$152, 2, FALSE),0) -> 0 | N31: =ifna(VLOOKUP(A31, janneiro24!$A$127:$B$152, 2, FALSE),0) -> 0 | O31: =ifna(VLOOKUP(A31, fevereiro24!$A$127:$B$152, 2, FALSE),0) -> 0 | P31: =ifna(VLOOKUP(A31, marco24!$A$127:$B$152, 2, FALSE),0) -> 0 | Q31: =ifna(VLOOKUP(A31, abril24!$A$127:$B$152, 2, FALSE),0) -> 0 | R31: =ifna(VLOOKUP(A31, maio24!$A$127:$B$152, 2, FALSE),0) -> 0 | S31: =ifna(VLOOKUP(A31, 'jun24'!$A$127:$B$152, 2, FALSE),0) -> 0 | T31: =ifna(VLOOKUP(A31, 'set24'!$A$127:$B$152, 2, FALSE),0) -> 0 | U31: =ifna(VLOOKUP(A31, 'jan25'!$A$127:$B$152, 2, FALSE),0) -> 0 | V31: =ifna(VLOOKUP(A31, 'fev25'!$A$132:$B$157, 2, FALSE),0) -> 0 | W31: =ifna(VLOOKUP(A31, 'mar25'!$A$125:$B$153, 2, FALSE),0) -> 0 | X31: =ifna(VLOOKUP(A31, 'abr25'!$A$131:$B$157, 2, FALSE),0) -> 0 | Y31: =ifna(VLOOKUP(A31, 'mai25'!$A$142:$B$174, 2, FALSE),0) -> 0 | Z31: =ifna(VLOOKUP(A31, 'jun25'!$A$141:$B$169, 2, FALSE),0) -> 0 | AA31: =ifna(VLOOKUP(A31, 'jul25'!$A$141:$B$170, 2, FALSE),0) -> 0 | AB31: =ifna(VLOOKUP(A31, 'ago25'!$A$141:$B$170, 2, FALSE),0) -> 0 | AC31: =AVERAGE(X31:AA31) -> 0
A32: projetos | D32: =ifna(VLOOKUP(A32, marco23!$A$97:$B$119, 2, FALSE),0) -> 0 | E32: =ifna(VLOOKUP(B32, marco23!$A$97:$B$119, 2, FALSE),0) -> 0 | F32: =ifna(VLOOKUP(C32, marco23!$A$97:$B$119, 2, FALSE),0) -> 0 | G32: =ifna(VLOOKUP(D32, marco23!$A$97:$B$119, 2, FALSE),0) -> 0 | H32: =ifna(VLOOKUP(E32, marco23!$A$97:$B$119, 2, FALSE),0) -> 0 | I32: =ifna(VLOOKUP(F32, marco23!$A$97:$B$119, 2, FALSE),0) -> 0 | J32: =ifna(VLOOKUP(G32, marco23!$A$97:$B$119, 2, FALSE),0) -> 0 | K32: =ifna(VLOOKUP(H32, marco23!$A$97:$B$119, 2, FALSE),0) -> 0 | ... P32: =ifna(VLOOKUP(M32, marco23!$A$97:$B$119, 2, FALSE),0) -> 0 | Q32: =ifna(VLOOKUP(A32, abril24!$A$127:$B$152, 2, FALSE),0) -> 0 | R32: =ifna(VLOOKUP(A32, maio24!$A$127:$B$152, 2, FALSE),0) -> 591.51 | S32: =ifna(VLOOKUP(A32, 'jun24'!$A$127:$B$152, 2, FALSE),0) -> 0 | T32: =ifna(VLOOKUP(A32, 'set24'!$A$127:$B$152, 2, FALSE),0) -> 0 | U32: =ifna(VLOOKUP(A32, 'jan25'!$A$127:$B$152, 2, FALSE),0) -> 0 | V32: =ifna(VLOOKUP(A32, 'fev25'!$A$132:$B$157, 2, FALSE),0) -> 111.28 | W32: =ifna(VLOOKUP(A32, 'mar25'!$A$125:$B$153, 2, FALSE),0) -> 0 | X32: =ifna(VLOOKUP(A32, 'abr25'!$A$131:$B$157, 2, FALSE),0) -> 0 | Y32: =ifna(VLOOKUP(A32, 'mai25'!$A$142:$B$174, 2, FALSE),0) -> 1596.5 | Z32: =ifna(VLOOKUP(A32, 'jun25'!$A$141:$B$169, 2, FALSE),0) -> 13.8 | AA32: =ifna(VLOOKUP(A32, 'jul25'!$A$141:$B$170, 2, FALSE),0) -> 297.52 | AB32: =ifna(VLOOKUP(A32, 'ago25'!$A$141:$B$170, 2, FALSE),0) -> 248.79 | AC32: =AVERAGE(X32:AA32) -> 476.955
A33: pix aline | U33: =ifna(VLOOKUP(A33, 'jan25'!$A$127:$B$152, 2, FALSE),0) -> 0 | V33: =ifna(VLOOKUP(A33, 'fev25'!$A$132:$B$157, 2, FALSE),0) -> 100 | W33: =ifna(VLOOKUP(A33, 'mar25'!$A$125:$B$153, 2, FALSE),0) -> 630 | X33: =ifna(VLOOKUP(A33, 'abr25'!$A$131:$B$157, 2, FALSE),0) -> 600 | Y33: =ifna(VLOOKUP(A33, 'mai25'!$A$142:$B$174, 2, FALSE),0) -> 150 | Z33: =ifna(VLOOKUP(A33, 'jun25'!$A$141:$B$169, 2, FALSE),0) -> 778 | AA33: =ifna(VLOOKUP(A33, 'jul25'!$A$141:$B$170, 2, FALSE),0) -> 500 | AB33: =ifna(VLOOKUP(A33, 'ago25'!$A$141:$B$170, 2, FALSE),0) -> 1337.62 | AC33: =AVERAGE(X33:AA33) -> 507
A34: painel solar | U34: =ifna(VLOOKUP(A34, 'jan25'!$A$127:$B$152, 2, FALSE),0) -> 0 | V34: =ifna(VLOOKUP(A34, 'fev25'!$A$132:$B$157, 2, FALSE),0) -> 0 | W34: =ifna(VLOOKUP(A34, 'mar25'!$A$125:$B$153, 2, FALSE),0) -> 2177.64 | X34: =ifna(VLOOKUP(A34, 'abr25'!$A$131:$B$157, 2, FALSE),0) -> 6446.76 | Y34: =ifna(VLOOKUP(A34, 'mai25'!$A$142:$B$174, 2, FALSE),0) -> 777.56 | Z34: =ifna(VLOOKUP(A34, 'jun25'!$A$141:$B$169, 2, FALSE),0) -> 777.56 | AA34: =ifna(VLOOKUP(A34, 'jul25'!$A$141:$B$170, 2, FALSE),0) -> 777.56 | AB34: =ifna(VLOOKUP(A34, 'ago25'!$A$141:$B$170, 2, FALSE),0) -> 777.56 | AC34: =AVERAGE(X34:AA34) -> 2194.86
A35: dentista | U35: =ifna(VLOOKUP(A35, 'jan25'!$A$127:$B$152, 2, FALSE),0) -> 0 | V35: =ifna(VLOOKUP(A35, 'fev25'!$A$132:$B$157, 2, FALSE),0) -> 140 | W35: =ifna(VLOOKUP(A35, 'mar25'!$A$125:$B$153, 2, FALSE),0) -> 140 | X35: =ifna(VLOOKUP(A35, 'abr25'!$A$131:$B$157, 2, FALSE),0) -> 140 | Y35: =ifna(VLOOKUP(A35, 'mai25'!$A$142:$B$174, 2, FALSE),0) -> 140 | Z35: =ifna(VLOOKUP(A35, 'jun25'!$A$141:$B$169, 2, FALSE),0) -> 140 | AA35: =ifna(VLOOKUP(A35, 'jul25'!$A$141:$B$170, 2, FALSE),0) -> 140 | AB35: =ifna(VLOOKUP(A35, 'ago25'!$A$141:$B$170, 2, FALSE),0) -> 0 | AC35: =AVERAGE(X35:AA35) -> 140
A36: reforma casa | U36: =ifna(VLOOKUP(A36, 'jan25'!$A$127:$B$152, 2, FALSE),0) -> 0 | V36: =ifna(VLOOKUP(A36, 'fev25'!$A$132:$B$157, 2, FALSE),0) -> 328.57 | W36: =ifna(VLOOKUP(A36, 'mar25'!$A$125:$B$153, 2, FALSE),0) -> 328.55 | X36: =ifna(VLOOKUP(A36, 'abr25'!$A$131:$B$157, 2, FALSE),0) -> 0 | Y36: =ifna(VLOOKUP(A36, 'mai25'!$A$142:$B$174, 2, FALSE),0) -> 328.55 | Z36: =ifna(VLOOKUP(A36, 'jun25'!$A$141:$B$169, 2, FALSE),0) -> 328.55 | AA36: =ifna(VLOOKUP(A36, 'jul25'!$A$141:$B$170, 2, FALSE),0) -> 328.55 | AB36: =ifna(VLOOKUP(A36, 'ago25'!$A$141:$B$170, 2, FALSE),0) -> 328.55 | AC36: =AVERAGE(X36:AA36) -> 246.4125
A37: boleto | V37: =ifna(VLOOKUP(A37, 'fev25'!$A$132:$B$157, 2, FALSE),0) -> 0 | W37: =ifna(VLOOKUP(A37, 'mar25'!$A$125:$B$153, 2, FALSE),0) -> 0 | X37: =ifna(VLOOKUP(A37, 'abr25'!$A$131:$B$157, 2, FALSE),0) -> 0 | Y37: =ifna(VLOOKUP(A37, 'mai25'!$A$142:$B$174, 2, FALSE),0) -> 0 | Z37: =ifna(VLOOKUP(A37, 'jun25'!$A$141:$B$169, 2, FALSE),0) -> 0 | AA37: =ifna(VLOOKUP(A37, 'jul25'!$A$141:$B$170, 2, FALSE),0) -> 0 | AB37: =ifna(VLOOKUP(A37, 'ago25'!$A$141:$B$170, 2, FALSE),0) -> 2056 | AC37: =AVERAGE(X37:AA37) -> 0
A39: total | B39: =SUM(B2:B27) -> 4310.98 | C39: =SUM(C2:C27) -> 7991.61 | D39: =SUM(D2:D27) -> 7758.39 | E39: =SUM(E2:E27) -> 6461.7 | F39: =SUM(F2:F27) -> 6893.4973 | G39: =SUM(G2:G30) -> 8260.4173 | H39: =SUM(H2:H31) -> 11223.307 | I39: =SUM(I2:I31) -> 6681.1164 | J39: =SUM(J2:J31) -> 8364.85 | K39: =SUM(K2:K31) -> 10185.19 | L39: =SUM(L2:L32) -> 7439.45 | M39: =SUM(M2:M32) -> 12200.44 | N39: =SUM(N2:N32) -> 8800.34 | O39: =SUM(O2:O32) -> 10916.823 | P39: =SUM(P2:P32) -> 8935.93 | Q39: =SUM(Q2:Q32) -> 7593.98 | R39: =SUM(R2:R32) -> 9393.12 | S39: =SUM(S2:S32) -> 6675.59 | ... U39: =SUM(U2:U32) -> 3799.7 | V39: =SUM(V2:V37) -> 10857.06 | W39: =SUM(W2:W37) -> 10427.69 | X39: =SUM(X2:X37) -> 16561.44 | Y39: =SUM(Y2:Y37) -> 13314.44 | Z39: =SUM(Z2:Z37) -> 10367.06 | AA39: =SUM(AA2:AA37) -> 10581.7 | AB39: =SUM(AB2:AB37) -> 14115.11 | AC39: =AVERAGE(X39:AA39) -> 12706.16
A41: Receitas liquidas | P41: =P42-14000 -> -9217.49 | Q41: =Q42-14000 -> -9217.49 | R41: =R42 -> 10167.279 | S41: =S42 -> 9167.279 | T41: =S42 -> 9167.279 | U41: =S42 -> 9167.279 | V41: =S42 -> 9167.279 | W41: =S42 -> 9167.279 | X41: =S42 -> 9167.279 | Y41: =5092.58+5495.73 -> 10588.31 | Z41: =C68 -> 10497.05 | AA41: =AA68 -> 10497.05 | AB41: =AB68 -> 10497.05
A42: Avanade | B42: =8968.96 -> 8968.96 | C42: =8968.96 -> 8968.96 | D42: =8968.96 -> 8968.96 | E42: =8968.96 -> 8968.96 | F42: =8968.96 -> 8968.96 | G42: =8968.96 -> 8968.96 | H42: =8968.96 -> 8968.96 | I42: =8968.96 -> 8968.96 | J42: =8968.96 -> 8968.96 | K42: =D65 | L42: =D65 | M42: =D65+7008 -> 7008 | N42: =D65 | O42: =D65 | P42: =D65+4782.51 -> 4782.51 | Q42: =E65+4782.51 -> 4782.51 | R42: =C65+1000 -> 10167.279 | S42: =C65 -> 9167.279 | T42: =C65 -> 9167.279 | U42: =C65 -> 9167.279 | V42: =C64 -> 9827.829 | W42: =C64 -> 9827.829 | X42: =C64 -> 9827.829 | Y42: =5092.58+5495.73 -> 10588.31 | Z42: =C68 -> 10497.05 | AA42: =AA68 -> 10497.05 | AB42: =AB68 -> 10497.05 | AC42: 9167.28
A43: Vale alimentacao | B43: 792 | C43: 792 | D43: 792 | E43: 792 | F43: 792 | G43: 792 | H43: 792 | I43: 792 | J43: 792 | K43: 792 | L43: 792 | M43: =850+200 -> 1050 | N43: =850 -> 850 | O43: =850 -> 850 | P43: =850 -> 850 | Q43: =850 -> 850 | R43: =850 -> 850 | S43: =850 -> 850 | T43: 850 | U43: 850 | V43: 850 | W43: 850 | X43: 850 | Y43: 850 | Z43: 850 | AA43: 850 | AB43: 850 | AC43: =AVERAGE(G43:S43) -> 838.61538
A44: beneficio | B44: 150 | C44: 150 | D44: 150 | E44: 150 | F44: 150 | G44: 150 | H44: 150 | I44: 150 | J44: 150 | K44: 150 | L44: 150 | M44: 150 | N44: 150 | O44: 150 | P44: 150 | Q44: 150 | R44: 150 | S44: 150 | T44: 150 | U44: 150 | V44: 150 | W44: 150 | X44: 150 | Y44: 150 | Z44: 150 | AA44: 150 | AB44: 150 | AC44: =AVERAGE(G44:S44) -> 150
A46: Receitas liquidas variaveis
A47: - | B47: 0 | C47: 0 | D47: 0 | E47: 0 | F47: 0 | G47: 0 | H47: 0 | I47: 0 | J47: 0 | K47: 0 | L47: 0
A49: Resumo
A50: Despesas Essenciais (55%) | B50: =sum(B2,B5:B7,B9:B19,B25,B27) -> 4181.08 | C50: =sum(C2,C5:C7,C9:C19,C25,C27) -> 5715.03 | D50: =sum(D2,D5:D7,D9:D19,D25,D27) -> 5173.78 | E50: =sum(E2,E5:E7,E9:E19,E25,E27) -> 4081.72 | F50: =sum(F2,F5:F7,F9:F19,F25,F27) -> 6192.8973 | G50: =sum(G2,G5:G7,G9:G19,G25,G27) -> 7152.8773 | H50: =sum(H2,H5:H7,H9:H19,H25,H27) -> 6035.4373 | I50: =sum(I2,I5:I7,I9:I19,I25,I27,I26,I30) -> 5528.5164 | J50: =sum(J2,J5:J7,J9:J19,J25,J27,J26,J30) -> 7236.76 | K50: =sum(K2,K5:K7,K9:K19,K25,K27,K26,K30) -> 7694.17 | L50: =sum(L2,L5:L7,L9:L19,L25,L27,L26,L30) -> 6161.6 | M50: =sum(M2,M5:M7,M9:M19,M25,M27,M26,M30) -> 10991.97 | N50: =sum(N2,N5:N7,N9:N19,N25,N27,N26,N30) -> 8574.14 | O50: =sum(O2,O5:O7,O9:O19,O25,O27,O26,O30) -> 10690.623 | P50: =sum(P2,P5:P7,P9:P19,P25,P27,P26,P30) -> 8281.67 | ... AC50: =sum(AC2,AC5:AC7,AC9:AC19,AC25,AC27,AC26,AC30) -> 6354.4
A51: =SUM(B42:B44)*0.55 -> 5451.028 | B51: =IFERROR(B50/SUM(B42:B44),0) -> 0.42186428 | C51: =IFERROR(C50/SUM(C42:C44),0) -> 0.57663738 | D51: =IFERROR(D50/SUM(D42:D44),0) -> 0.52202612 | E51: =IFERROR(E50/SUM(E42:E44),0) -> 0.41183901 | F51: =IFERROR(F50/SUM(F42:F44),0) -> 0.62485342 | G51: =IFERROR(G50/SUM(G42:G44),0) -> 0.72171387 | H51: =IFERROR(H50/SUM(H42:H44),0) -> 0.60896596 | I51: =IFERROR(I50/SUM(I42:I44),0) -> 0.55781846 | ... AC51: =IFERROR(AC50/SUM(AC42:AC44),0) -> 0.62568585
A52: Despesas Educação (5%) | B52: =B4 -> 37.9 | C52: =C4 -> 37.9 | D52: =D4 -> 37.9 | E52: =E4 -> 37.9 | F52: =F4 -> 37.9 | G52: =G4 -> 0 | H52: =H4 -> 0 | I52: =I4 -> 0 | ... AC52: =AC4 -> 804.31
A53: =B42*0.05 -> 448.448 | B53: =IFERROR(B52/SUM(B42:B44),0) -> 0.0038240493 | C53: =IFERROR(C52/SUM(C42:C44),0) -> 0.0038240493 | D53: =IFERROR(D52/SUM(D42:D44),0) -> 0.0038240493 | E53: =IFERROR(E52/SUM(E42:E44),0) -> 0.0038240493 | F53: =IFERROR(F52/SUM(F42:F44),0) -> 0.0038240493 | G53: =IFERROR(G52/SUM(G42:G44),0) -> 0 | H53: =IFERROR(H52/SUM(H42:H44),0) -> 0 | I53: =IFERROR(I52/SUM(I42:I44),0) -> 0 | ... AC53: =IFERROR(AC52/SUM(AC42:AC44),0) -> 0.079196365
A54: Gastos livres (10%) | B54: =sum(B3,B8,B20,B21,B22,B23,B24,B26,B28,B29,B30) -> 92 | C54: =sum(C3,C8,C20,C21,C22,C23,C24,C26,C28,C29,C30) -> 2238.68 | D54: =sum(D3,D8,D20,D21,D22,D23,D24,D26,D28,D29,D30) -> 2546.71 | E54: =sum(E3,E8,E20,E21,E22,E23,E24,E26,E28,E29,E30) -> 2992.08 | F54: =sum(F3,F8,F20,F21,F22,F23,F24,F26,F28,F29,F30) -> 2759.7 | G54: =sum(G3,G8,G20,G21,G22,G23,G24,G26,G28,G29,G30) -> 1107.54 | H54: =sum(H3,H8,H20,H21,H22,H23,H24,H26,H28,H29,H30) -> 1371.13 | I54: =sum(I3,I8,I20,I21,I22,I23,I24,I28,I29) -> 1152.6 | J54: =sum(J3,J8,J20,J21,J22,J23,J24,J28,J29) -> 968.09 | K54: =sum(K3,K8,K20,K21,K22,K23,K24,K28,K29) -> 1164.51 | L54: =sum(L3,L8,L20,L21,L22,L23,L24,L28,L29) -> 1277.85 | M54: =sum(M3,M8,M20,M21,M22,M23,M24,M28,M29) -> 1208.47 | N54: =sum(N3,N8,N20,N21,N22,N23,N24,N28,N29) -> 226.2 | O54: =sum(O3,O8,O20,O21,O22,O23,O24,O28,O29) -> 226.2 | P54: =sum(P3,P8,P20,P21,P22,P23,P24,P28,P29) -> 654.26 | ... AC54: =sum(AC3,AC8,AC20,AC21,AC22,AC23,AC24,AC28,AC29) -> 1982.2225
A55: =SUM(B42,B44)*0.1 -> 911.896 | B55: =IFERROR(B54/SUM(B42,B44),0) -> 0.01008887 | C55: =IFERROR(C54/SUM(C42,C44),0) -> 0.24549729 | D55: =IFERROR(D54/SUM(D42,D44),0) -> 0.27927636 | E55: =IFERROR(E54/SUM(E42,E44),0) -> 0.32811636 | F55: =IFERROR(F54/SUM(F42,F44),0) -> 0.3026332 | G55: =IFERROR(G54/SUM(G42,G44),0) -> 0.12145464 | H55: =IFERROR(H54/SUM(H42,H44),0) -> 0.15036035 | I55: =IFERROR(I54/SUM(I42,I44),0) -> 0.12639599 | ... AC55: =IFERROR(AC54/SUM(AC42,AC44),0) -> 0.21274691
A56: Boleto Pessoal (30%) | B56: =IFERROR(SUM(B42)*0.3-633.9,0) -> 2056.788 | C56: =IFERROR(SUM(C42)*0.3-633.9,0) -> 2056.788 | D56: =IFERROR(SUM(D42)*0.3-633.9,0) -> 2056.788 | E56: =IFERROR(SUM(E42)*0.3-633.9,0) -> 2056.788 | F56: =IFERROR(SUM(F42)*0.3-633.9,0) -> 2056.788 | G56: =IFERROR(SUM(G42)*0.3-633.9,0) -> 2056.788 | H56: =IFERROR(SUM(H42)*0.3-633.9,0) -> 2056.788 | I56: =IFERROR(SUM(I42)*0.3-633.9,0) -> 2056.788 | J56: 1500 | K56: 0 | L56: =IFERROR(SUM(L42)*0.3-633.9,0) -> -633.9 | M56: =IFERROR(SUM(M42)*0.3-633.9,0) -> 1468.5 | N56: =IFERROR(SUM(N42)*0.3-633.9,0) -> -633.9 | O56: =IFERROR(SUM(O42)*0.3-633.9,0) -> -633.9 | P56: =IFERROR(SUM(P42)*0.3-633.9,0) -> 800.853 | Q56: =IFERROR(SUM(Q42)*0.3-633.9,0) -> 800.853 | R56: =IFERROR(SUM(R42)*0.3-633.9,0) -> 2416.2837 | S56: =IFERROR(SUM(S42)*0.3-633.9,0) -> 2116.2837 | ... Z56: =IFERROR(SUM(Z42)*0.3-633.9,0) -> 2515.215 | AA56: =AA37 -> 0 | AB56: =AB37 -> 2056 | AC56: =IFERROR(SUM(AC42)*0.3-633.9,0) -> 2116.284
AA57: =IFERROR(AA56/SUM(AA42*0.3-250),0) -> 0 | AB57: =IFERROR(AB56/SUM(AB42*0.3-250),0) -> 0.70918194
A58: rest | B58: =B42-SUM(B50,B52,B54,B56) -> 2601.192 | C58: =C42-SUM(C50,C52,C54,C56) -> -1079.438 | D58: =D42-SUM(D50,D52,D54,D56) -> -846.218 | E58: =E42-SUM(E50,E52,E54,E56) -> -199.528 | F58: =F42-SUM(F50,F52,F54,F56) -> -2078.3253 | G58: =G42-SUM(G50,G52,G54,G56) -> -1348.2453 | H58: =H42-SUM(H50,H52,H54,H56) -> -494.3953 | I58: =I42-SUM(I50,I52,I54,I56) -> 231.0556 | ... AC58: =AC42-SUM(AC50,AC52,AC54,AC56) -> -2089.9365
A61: Bruto | B61: =12900+(12900*0) -> 12900 | C61: =13210.89 -> 13210.89
A62: Bruto - inss - dependentes | B62: =B61-876.95-sum(189) -> 11834.05 | C62: =C61-908.85 -> 12302.04
A63: IRRF | B63: =B62*0.275-875 -> 2379.3637 | C63: =C62*0.275-908.85 -> 2474.211
A64: liquido | B64: =B62-B63 -> 9454.6863 | C64: =C62-C63 -> 9827.829
A65: liquido - prev + ações | B65: =B64-630 -> 8824.6863 | C65: =C64-(264.22+396.33) -> 9167.279
A68: liquido | B68: 45833 | C68: =5495.73+5001.32 -> 10497.05 | Z68: =5495.73+5001.32 -> 10497.05 | AA68: =5495.73+5001.32 -> 10497.05 | AB68: =5495.73+5001.32 -> 10497.05
C70: 13 - 6869,67
A72: Despesas Essenciais (55%) | Z72: =Z68*0.55 -> 5773.3775 | AA72: =(AA68*0.55)-(AA50) -> -277.4725 | AB72: =(AB68*0.55)-(AB50) -> -1182.7025
A73: Despesas Educação (5%) | Z73: =Z68*0.05 -> 524.8525 | AA73: =(AA68*0.05)-AA52 -> 144.8525 | AB73: =(AB68*0.05)-AB52 -> 144.8525
A74: Gastos livres (10%) | Z74: =Z68*0.1 -> 1049.705 | AA74: =(AA68*0.1)-(AA54) -> -1057.515 | AB74: =(AB68*0.1)-(AB54) -> -980.805
A75: Boleto Pessoal (30%) | Z75: =Z68*0.3 -> 3149.115 | AA75: =((AA68*0.3)-250)-AA37 -> 2899.115 | AB75: =((AB68*0.3)-250)-AB37 -> 843.115
B77: 120000
B78: =15000+3000 -> 18000
B79: =SUM(B77:B78) -> 138000
B80: =2111*11 -> 23221
B81: =SUM(B79:B80) -> 161221
B82: =200000-B81 -> 38779

Sheet amount
B1: cc | C1: cdi
A2: Bradesco | B2: 88.72
A3: Nubank | B3: 1065.95 | C3: 22297.21
A4: Santander | B4: 34353.86
A5: PagBank | B5: 0 | C5: 5151
A6: N26 | B6: 0
A7: Wise | B7: =IFERROR(__xludf.DUMMYFUNCTION("GOOGLEFINANCE(""currency:EURBRL"")*492.99"),2906.78489265) -> 2906.7849
A8: Binance | B8: =IFERROR(__xludf.DUMMYFUNCTION("GOOGLEFINANCE(""CURRENCY:USDBRL"")*610"),3072.631) -> 3072.631
A9: Inter | B9: 16859.02
A10: InterEmpresa | B10: 38562.6
A11: rico | B11: 0
A13: Total | B13: =SUM(B2:B11,C2:C11) -> 124357.78
B16: =2986.85+1000 -> 3986.85

Sheet jan26
A1: ma | B1: dia | C1: valor | D1: situacao | E1: forma de pagamento | F1: beneficiado | G1: outcome | H1: subclassificacao | I1: centro de custo | J1: categoria | L1: tipo de despesas | M1: tag
A2: escolar Arthur | B2: 5 | C2: 0 | D2: pg | E2: boleto | F2: Arthur | G2: bradesco conta | H2: despesas pessoais | I2: despesas essenciais | J2: escola/faculdade | L2: fixa
A3: Faculdade Aline | B3: 5 | C3: 901.84 | D3: pg | E3: boleto | F3: Aline | G3: bradesco conta | H3: despesas pessoais | I3: despesas essenciais | J3: escola/faculdade | L3: fixa
A4: Dentista Arthur | B4: 5 | C4: 0 | D4: pg | E4: Bradesco cartoes | F4: Arthur | G4: bradesco conta | H4: despesas pessoais | I4: despesas essenciais | J4: dentista | L4: fixa
A5: Conta de energia | B5: 14 | C5: 145.27 | D5: pg | E5: boleto | F5: familia | G5: santander conta | H5: habitacao | I5: despesas essenciais | J5: Energia | L5: variavel
A6: internet fixa | B6: 11 | C6: 129.96 | D6: open | E6: boleto | F6: familia | G6: bradesco conta | H6: habitacao | I6: despesas essenciais | J6: Internet | L6: fixa
A7: internet TIM móvel | B7: 25 | C7: 106.9 | D7: pg | E7: debito automatico | F7: Alex | G7: bradesco conta | H7: habitacao | I7: despesas essenciais | J7: Internet movel | L7: fixa
A8: streaming HBO | B8: 30 | C8: 19.95 | D8: open | E8: nubank card | F8: familia | G8: nubank conta | H8: habitacao | J8: streaming | L8: fixa
A9: Apple Tv | B9: 16 | C9: 0 | D9: closed | E9: nubank card | F9: familia | G9: nubank conta | H9: habitacao | J9: streaming | L9: fixa
A10: streaming amazonPrime | B10: 5 | C10: 0 | D10: pg | E10: nubank card | F10: familia | G10: nubank conta | H10: habitacao | J10: streaming | L10: fixa
A11: assinatura mercado livre | B11: 2 | C11: 19.9 | D11: pg | E11: nubank card | F11: familia | G11: nubank conta | H11: habitacao | J11: streaming | L11: fixa
A12: contra contabilidade | B12: 15 | C12: 0 | D12: closed | E12: nubank card | F12: Alex | G12: nubank conta | H12: despesas pessoais | J12: contabilidade | L12: fixa
A13: assinatura NETFLIX | B13: 8 | C13: 44.9 | D13: pg | E13: nubank card | F13: familia | G13: nubank conta | H13: habitacao | J13: streaming | L13: fixa
A14: assinatura GamePass | B14: 15 | C14: 0 | D14: open | E14: nubank card | F14: familia | G14: nubank conta | H14: habitacao | J14: streaming | L14: fixa
A15: seguro PIER carro | B15: 27 | C15: 309.73 | D15: open | E15: nubank card | F15: familia | G15: nubank conta | H15: transporte | I15: despesas essenciais | J15: seguro | L15: fixa
A16: curso rocketseatPlus | B16: 2 | C16: 0 | D16: open | E16: nubank card | F16: Alex | G16: nubank conta | H16: educacao | I16: educacao | J16: cursos | L16: fixa | N16: 45992
A17: gympass | B17: 27 | C17: =89.9+139.9 -> 229.8 | D17: open | E17: nubank card | F17: Alex | G17: nubank conta | H17: despesas pessoais | I17: despesas essenciais | J17: academia | L17: fixa
A18: Condominio | B18: 10 | C18: 20 | D18: open | E18: Pix | F18: familia | G18: nubank conta | H18: habitacao | I18: despesas essenciais | J18: manutenção domiciliar
A19: pix aline | B19: 8 | C19: 500 | D19: pg | E19: Pix | G19: bradesco conta | H19: habitacao | J19: pix aline
B20: 15 | D20: pg | E20: Pix | G20: bradesco conta | H20: habitacao | J20: cursos
B21: 6 | D21: open | E21: bradesco cartoes | G21: bradesco conta | H21: habitacao | J21: reforma casa
A22: Painel solar 11/12 | B22: 17 | C22: 777.56 | D22: open | E22: bradesco cartoes | G22: bradesco conta | H22: habitacao | J22: painel solar
A23: futebol domingo | B23: 10 | C23: 60 | D23: open | E23: Pix | G23: bradesco conta | H23: habitacao | J23: Lazer
A24: Atacadao | B24: 0 | C24: 138.74 | D24: pg | E24: Pix | G24: bradesco conta | H24: habitacao | J24: combustivel | N24: 45324
A25: Mercado Ideal | B25: 0 | C25: 24 | D25: pg | E25: bradesco cartoes | G25: bradesco conta | H25: habitacao | J25: Feira
A26: Indigo | B26: 0 | C26: 23 | D26: pg | E26: bradesco cartoes | G26: bradesco conta | J26: Cabeleireiro | N26: 45354
A27: Auto posto TOP | B27: 0 | C27: 47.38 | D27: pg | E27: bradesco cartoes | G27: bradesco conta | H27: habitacao | J27: Manutenção casa
A28: Delirio Tropical | B28: 0 | C28: 56 | D28: pg | E28: bradesco cartoes | G28: bradesco conta | J28: Padaria
A29: Burguer king | B29: 0 | C29: 44.9 | D29: pg | E29: bradesco cartoes | G29: bradesco conta | J29: mercado | N29: 45872
A30: Estacionamento | B30: 0 | C30: 7 | D30: pg | E30: bradesco cartoes | G30: bradesco conta | J30: outros | N30: 45993
A31: O boticario | B31: 0 | C31: 105.8 | D31: pg | E31: bradesco cartoes | G31: nubank conta | H31: habitacao | J31: mercado
A32: Chavao | B32: 0 | C32: 32 | D32: pg | E32: bradesco cartoes | G32: bradesco conta | J32: Lazer
A33: Padaria | B33: 0 | C33: 4 | D33: pg | E33: bradesco cartoes | G33: bradesco conta | J33: farmacia
A34: 283 sao goncalo | B34: 0 | C34: 39.99 | D34: pg | E34: bradesco cartoes | G34: bradesco conta | J34: Feira
A35: Mundo da Refrigeracao | B35: 0 | C35: 24.9 | D35: pg | E35: bradesco cartoes | G35: bradesco conta | J35: Feira
A36: Lojas Nalin | B36: 0 | C36: 79.98 | D36: pg | E36: bradesco cartoes | G36: bradesco conta | J36: combustivel
A37: Pagamento | B37: 0 | C37: 310 | D37: pg | E37: bradesco cartoes | G37: bradesco conta | J37: mercado
A38: Hortifruit dayse | B38: 0 | C38: 9 | D38: pg | E38: bradesco cartoes | G38: bradesco conta | J38: Padaria | M38: ferias
A39: Nova fruit | B39: 0 | C39: 16.62 | D39: pg | E39: bradesco cartoes | G39: bradesco conta | J39: Lazer
A40: Breyas Especiais lan | B40: 0 | C40: 7 | D40: pg | E40: bradesco cartoes | G40: bradesco conta | J40: outros
A41: Pes e patas | B41: 0 | C41: 56.87 | D41: pg | E41: bradesco cartoes | G41: bradesco conta | J41: Pet
A42: Burguer king | B42: 2 | C42: 77.8 | D42: pg | E42: bradesco cartoes | G42: bradesco conta | J42: Lazer
A43: Amigao | B43: 3 | C43: 77.88 | D43: pg | E43: bradesco cartoes | G43: bradesco conta | J43: manutenção domiciliar
A44: padaria | B44: 3 | C44: 4 | D44: pg | E44: bradesco cartoes | G44: bradesco conta | J44: Padaria
A45: to aki estacionamento | B45: 3 | C45: 9 | D45: pg | E45: pix | G45: bradesco conta | J45: projetos
A46: Silva modas | B46: 3 | C46: 29.99 | D46: pg | E46: pix | G46: bradesco conta | J46: projetos
A47: ki chopp | B47: 3 | C47: 175.22 | D47: pg | E47: pix | G47: bradesco conta | J47: Internet movel
A48: Cruzverde | B48: 4 | C48: 32.99 | D48: pg | E48: pix | G48: bradesco conta | J48: estacionamentos
A49: Bmb Material de Construcao | B49: 4 | C49: 343.76 | D49: pg | E49: pix | G49: bradesco conta | J49: manutenção domiciliar
A50: Assai | B50: 4 | C50: 119.32 | D50: pg | E50: bradesco cartoes | G50: bradesco conta | J50: Padaria
... A54: Jusimerefernandes | B54: 7 | C54: 1050 | D54: pg | E54: bradesco cartoes | G54: bradesco conta | J54: manutencao veiculo
A55: Katarynemotta | B55: 8 | C55: 12 | D55: pg | E55: bradesco cartoes | J55: combustivel
A56: assai | B56: 10 | C56: 217.88 | D56: pg | E56: bradesco cartoes | J56: Lazer
A57: padaria | B57: 13 | C57: 4 | D57: pg | E57: bradesco cartoes | J57: outros
A58: Nova fruit | B58: 13 | C58: 30.35 | D58: pg | E58: bradesco cartoes | J58: mercado
A59: Mercado Ideal | B59: 13 | C59: 36 | E59: bradesco cartoes | J59: mercado
A60: cosechas | B60: 13 | C60: 37 | D60: pg | E60: bradesco cartoes | J60: Pet
A61: padaria | B61: 15 | C61: 9 | D61: pg | E61: bradesco cartoes | J61: Pet
A62: Danielsantos | B62: 15 | C62: 8 | D62: pg | E62: bradesco cartoes | J62: Padaria
A63: hortifruit nova safra | B63: 15 | C63: 9.04 | D63: pg | E63: bradesco cartoes | J63: mercado
A64: Auto posto TOP | B64: 17 | C64: 175.13 | D64: pg | E64: bradesco cartoes | J64: ferias | M64: ferias
A65: Guarema | B65: 17 | C65: 5.4 | D65: pg | E65: bradesco cartoes | J65: ferias
A66: capava | B66: 17 | C66: 5.5 | D66: pg | E66: bradesco cartoes | J66: ferias
A67: Supermercado vila das | B67: 17 | C67: 25.47 | D67: pg | E67: bradesco cartoes | J67: ferias
A68: sao jose | B68: 17 | C68: 5.4 | D68: pg | E68: bradesco cartoes | J68: ferias
A69: Concessionaria Spmar | B69: 17 | C69: 4.1 | D69: pg | E69: bradesco cartoes | J69: ferias
A70: Caneco 90 P. | B70: 17 | C70: 150 | D70: pg | E70: bradesco cartoes | J70: ferias
A71: Concessionaria do Sist | B71: 17 | C71: 16.9 | D71: pg | E71: bradesco cartoes | J71: ferias
A72: Concessionaria do Sist | B72: 17 | C72: 15.5 | D72: pg | E72: bradesco cartoes | J72: ferias
A73: Drograrias JM ltda | B73: 17 | C73: 72.46 | D73: pg | E73: bradesco cartoes | J73: ferias
A74: spvias | B74: 18 | C74: 19.4 | D74: pg | E74: bradesco cartoes | J74: ferias
A75: Via colinas | B75: 18 | C75: 13.8 | D75: pg | E75: bradesco cartoes | J75: ferias
A76: Osasco | B76: 18 | C76: 4 | D76: pg | E76: bradesco cartoes | J76: ferias
... A117: Rodovias Integradas Do | B117: 25 | C117: 19.4 | D117: pg | E117: bradesco cartoes | J117: ferias
A118: Rodovias Integradas Do | B118: 25 | C118: 13.2 | E118: bradesco cartoes | J118: ferias
A119: Concessionara do | B119: 26 | C119: 4.5 | E119: bradesco cartoes | J119: ferias
A120: Concessionara do | B120: 26 | C120: 4.5 | E120: bradesco cartoes | J120: ferias
A121: Concessionara do | B121: 26 | C121: 8.1 | E121: bradesco cartoes | J121: ferias
A122: Concessionara do | B122: 26 | C122: 16.9 | E122: bradesco cartoes | J122: ferias
A123: Concessionara do | B123: 26 | C123: 14.5 | E123: bradesco cartoes | J123: ferias
A124: Kioque do alemao | B124: 26 | C124: 17.9 | E124: bradesco cartoes | J124: ferias
A125: Viuva | B125: 26 | C125: 16.4 | E125: bradesco cartoes | J125: ferias
A126: Burguer king | B126: 26 | C126: 77.8 | E126: bradesco cartoes | J126: ferias
A127: magalupay | B127: 5 | C127: 189.89 | E127: pix | J127: Vestuario
A128: Recarga Pre pago | B128: 5 | C128: 20 | E128: pix | J128: Internet movel
A129: Estacionamento | B129: 5 | C129: 6 | E129: pix | J129: estacionamentos
A130: Sacolao barateiro | B130: 5 | C130: 7.18 | E130: pix | J130: Feira
A131: Spotify | B131: 8 | C131: =40+0.9 -> 40.9 | E131: pix | J131: streaming
A132: Aibr Instituicao | B132: 12 | C132: 83.98 | E132: pix | J132: projetos
A133: Recarga Pre pago | B133: 15 | C133: 30 | E133: pix | J133: Internet movel
A134: SOnia de Aguiar | B134: 16 | C134: 25 | E134: pix | J134: outros
A135: Compras China | B135: 16 | C135: 627 | E135: pix | J135: outros
A136: Compras china | B136: 16 | C136: 50 | E136: pix | J136: outros
A137: Keeta | B137: 19 | C137: 41.26 | E137: pix | J137: ferias
A138: 99food | B138: 17 | C138: 62.48 | E138: pix | J138: ferias
A139: UltraFarma | B139: 18 | C139: 67.05 | E139: pix | J139: ferias
A140: Novanex | B140: 21 | C140: 3208.2 | E140: pix | J140: ferias
A141: Resort Animal | B141: 20 | C141: 70 | E141: pix | J141: ferias
A142: Resort Animal | B142: 21 | C142: 50 | E142: pix | J142: ferias
A143: Sandra Regina | B143: 21 | C143: 40 | E143: pix | J143: ferias
...

Sheet nov25
A1: ma | B1: dia | C1: valor | D1: situacao | E1: forma de pagamento | F1: beneficiado | G1: outcome | H1: subclassificacao | I1: centro de custo | J1: categoria | L1: tipo de despesas | M1: tag
A2: escolar Arthur | B2: 5 | C2: 789 | D2: pg | E2: boleto | F2: Arthur | G2: bradesco conta | H2: despesas pessoais | I2: despesas essenciais | J2: escola/faculdade | L2: fixa
A3: Faculdade Aline | B3: 5 | C3: 850 | D3: pg | E3: boleto | F3: Aline | G3: bradesco conta | H3: despesas pessoais | I3: despesas essenciais | J3: escola/faculdade | L3: fixa
A4: Dentista Arthur | B4: 5 | C4: 0 | D4: pg | E4: Bradesco cartoes | F4: Arthur | G4: bradesco conta | H4: despesas pessoais | I4: despesas essenciais | J4: dentista | L4: fixa
A5: Conta de energia | B5: 14 | C5: 118 | D5: pg | E5: boleto | F5: familia | G5: santander conta | H5: habitacao | I5: despesas essenciais | J5: Energia | L5: variavel
A6: internet fixa | B6: 11 | C6: 132.76 | D6: open | E6: boleto | F6: familia | G6: bradesco conta | H6: habitacao | I6: despesas essenciais | J6: Internet | L6: fixa
A7: internet TIM móvel | B7: 25 | C7: 99.9 | D7: pg | E7: debito automatico | F7: Alex | G7: bradesco conta | H7: habitacao | I7: despesas essenciais | J7: Internet movel | L7: fixa
A8: streaming HBO | B8: 30 | C8: 19.95 | D8: open | E8: nubank card | F8: familia | G8: nubank conta | H8: habitacao | J8: streaming | L8: fixa
A9: Apple Tv | B9: 16 | C9: 0 | D9: closed | E9: nubank card | F9: familia | G9: nubank conta | H9: habitacao | J9: streaming | L9: fixa
A10: streaming amazonPrime | B10: 5 | C10: 0 | D10: pg | E10: nubank card | F10: familia | G10: nubank conta | H10: habitacao | J10: streaming | L10: fixa
A11: assinatura mercado livre | B11: 2 | C11: 24.9 | D11: pg | E11: nubank card | F11: familia | G11: nubank conta | H11: habitacao | J11: streaming | L11: fixa
A12: contra contabilidade | B12: 15 | C12: 0 | D12: closed | E12: nubank card | F12: Alex | G12: nubank conta | H12: despesas pessoais | J12: contabilidade | L12: fixa
A13: assinatura NETFLIX | B13: 8 | C13: 44.9 | D13: pg | E13: nubank card | F13: familia | G13: nubank conta | H13: habitacao | J13: streaming | L13: fixa
A14: assinatura GamePass | B14: 15 | C14: 0 | D14: open | E14: nubank card | F14: familia | G14: nubank conta | H14: habitacao | J14: streaming | L14: fixa
A15: seguro PIER carro | B15: 27 | C15: 244.12 | D15: open | E15: nubank card | F15: familia | G15: nubank conta | H15: transporte | I15: despesas essenciais | J15: seguro | L15: fixa
A16: curso rocketseatPlus | B16: 2 | C16: 0 | D16: open | E16: nubank card | F16: Alex | G16: nubank conta | H16: educacao | I16: educacao | J16: cursos | L16: fixa | N16: 45992
A17: gympass | B17: 27 | C17: =89.9+139.9 -> 229.8 | D17: open | E17: nubank card | F17: Alex | G17: nubank conta | H17: despesas pessoais | I17: despesas essenciais | J17: academia | L17: fixa
A18: Condominio | B18: 10 | C18: 20 | D18: open | E18: Pix | F18: familia | G18: nubank conta | H18: habitacao | I18: despesas essenciais | J18: manutenção domiciliar
A19: pix aline | B19: 8 | C19: 500 | D19: pg | E19: Pix | G19: bradesco conta | H19: habitacao | J19: pix aline
B20: 15 | D20: pg | E20: Pix | G20: bradesco conta | H20: habitacao | J20: cursos
B21: 6 | D21: open | E21: bradesco cartoes | G21: bradesco conta | H21: habitacao | J21: reforma casa
A22: Painel solar 9/12 | B22: 17 | C22: 777.56 | D22: open | E22: bradesco cartoes | G22: bradesco conta | H22: habitacao | J22: painel solar
A23: futebol domingo | B23: 10 | C23: 60 | D23: open | E23: Pix | G23: bradesco conta | H23: habitacao | J23: Lazer
A24: auto posto top | B24: 0 | C24: 53.73 | D24: pg | E24: Pix | G24: bradesco conta | H24: habitacao | J24: combustivel | N24: 45324
A25: katarynedamota | B25: 0 | C25: 24 | D25: pg | E25: bradesco cartoes | G25: bradesco conta | H25: habitacao | J25: Feira
A26: perfumaria kennedy | B26: 0 | C26: 69.98 | D26: pg | E26: bradesco cartoes | G26: bradesco conta | J26: Cabeleireiro | N26: 45354
A27: mundodarefrigeracao | B27: 0 | C27: 49.9 | D27: pg | E27: bradesco cartoes | G27: bradesco conta | H27: habitacao | J27: Manutenção casa
A28: padaria | B28: 0 | C28: 9 | D28: pg | E28: bradesco cartoes | G28: bradesco conta | J28: Padaria
A29: padaria | B29: 1 | C29: 3 | D29: pg | E29: bradesco cartoes | G29: bradesco conta | J29: mercado | N29: 45872
A30: convem sao goncalo | B30: 1 | C30: 76.8 | D30: pg | E30: bradesco cartoes | G30: bradesco conta | J30: outros | N30: 45993
A31: atacadao | B31: 1 | C31: 3.49 | D31: pg | E31: bradesco cartoes | G31: nubank conta | H31: habitacao | J31: mercado
A32: top arena | B32: 2 | C32: 10 | D32: pg | E32: bradesco cartoes | G32: bradesco conta | J32: Lazer
A33: drogaria pacheco | B33: 3 | C33: 31.58 | D33: pg | E33: bradesco cartoes | G33: bradesco conta | J33: farmacia
A34: cassel frutas | B34: 3 | C34: 19.41 | D34: pg | E34: bradesco cartoes | G34: bradesco conta | J34: Feira
A35: sacolao do barateiro | B35: 5 | C35: 6.25 | D35: pg | E35: bradesco cartoes | G35: bradesco conta | J35: Feira
A36: auto posto top | B36: 6 | C36: 61.01 | D36: pg | E36: bradesco cartoes | G36: bradesco conta | J36: combustivel
A37: casas pedroq6 | B37: 6 | C37: 47.97 | D37: pg | E37: bradesco cartoes | G37: bradesco conta | J37: mercado
A38: padaria | B38: 7 | C38: 9 | D38: pg | E38: bradesco cartoes | G38: bradesco conta | J38: Padaria | M38: ferias
A39: burguerking | B39: 7 | C39: 77.8 | D39: pg | E39: bradesco cartoes | G39: bradesco conta | J39: Lazer
A40: boticario | B40: 8 | C40: 50.93 | D40: pg | E40: bradesco cartoes | G40: bradesco conta | J40: outros
A41: petz | B41: 8 | C41: 299.99 | D41: pg | E41: bradesco cartoes | G41: bradesco conta | J41: Pet
A42: cairofirminoda-oleo | B42: 10 | C42: 336 | D42: pg | E42: bradesco cartoes | G42: bradesco conta | J42: manutencao veiculo
A43: cairofirminoda-oleo | B43: 10 | C43: 10 | D43: pg | E43: bradesco cartoes | G43: bradesco conta | J43: manutencao veiculo
A44: frankjose-trocadeoleo | B44: 10 | C44: 150 | D44: pg | E44: bradesco cartoes | G44: bradesco conta | J44: manutencao veiculo
A45: shoppe | B45: 3 | C45: 24.66 | D45: pg | E45: pix | G45: bradesco conta | J45: projetos
A46: shoppe | B46: 3 | C46: 457.19 | D46: pg | E46: pix | G46: bradesco conta | J46: projetos
A47: claro recarga | B47: 6 | C47: 20 | D47: pg | E47: pix | G47: bradesco conta | J47: Internet movel
A48: kleyton diego | B48: 6 | C48: 7 | D48: pg | E48: pix | G48: bradesco conta | J48: estacionamentos
A49: aldecir-lavaajato | B49: 10 | C49: 120 | D49: pg | E49: pix | G49: bradesco conta | J49: manutencao veiculo
A50: guanabara | B50: 20 | C50: 83.33 | D50: pg | E50: bradesco cartoes | G50: bradesco conta | J50: Padaria
... A54: estacionamento | B54: 12 | C54: 8 | D54: pg | E54: bradesco cartoes | G54: bradesco conta | J54: estacionamentos
A55: auto posto top | B55: 12 | C55: 60 | D55: pg | E55: bradesco cartoes | J55: combustivel
A56: lovcafe | B56: 13 | C56: 53 | D56: pg | E56: bradesco cartoes | J56: Lazer
A57: wallacedossantos | B57: 13 | C57: 28 | D57: pg | E57: bradesco cartoes | J57: outros
A58: mercadoideal | B58: 14 | C58: 12 | D58: pg | E58: bradesco cartoes | J58: mercado
A59: supermarket | B59: 14 | C59: 70.05 | E59: bradesco cartoes | J59: mercado
A60: g pet shop | B60: 14 | C60: 23.9 | D60: pg | E60: bradesco cartoes | J60: Pet
A61: g pet shop | B61: 14 | C61: 138.9 | D61: pg | E61: bradesco cartoes | J61: Pet
A62: padaria | B62: 15 | C62: 8 | D62: pg | E62: bradesco cartoes | J62: Padaria
A63: assai | B63: 15 | C63: 176.47 | D63: pg | E63: bradesco cartoes | J63: mercado
A64: puro gas | B64: 15 | C64: 30 | D64: pg | E64: bradesco cartoes | J64: combustivel
A65: puro gas | B65: 15 | C65: 30 | D65: pg | E65: bradesco cartoes | J65: combustivel
A66: farmacia | B66: 16 | C66: 19.98 | D66: pg | E66: bradesco cartoes | J66: farmacia
A67: carrefour | B67: 16 | C67: 145.46 | D67: pg | E67: bradesco cartoes | J67: mercado
A68: auto posto top | B68: 18 | C68: 52.54 | D68: pg | E68: bradesco cartoes | J68: combustivel
A69: puro gas | B69: 18 | C69: 40 | D69: pg | E69: bradesco cartoes | J69: combustivel
A70: supermarket | B70: 18 | C70: 39.95 | D70: pg | E70: bradesco cartoes | J70: mercado
B71: 12 | C71: 0 | D71: pg | E71: nubank card | J71: projetos
B72: 23 | C72: 0 | D72: pg | E72: bradesco cartoes | J72: Pet
B73: 15 | C73: 0 | D73: pg | E73: bradesco cartoes | J73: material escolar
B74: 15 | C74: 0 | D74: pg | E74: bradesco cartoes | J74: gift
B75: 15 | C75: 0 | D75: pg | E75: bradesco cartoes | J75: Lazer
B76: 13 | C76: 0 | D76: pg | E76: bradesco cartoes | J76: Pet
B77: 17 | C77: 0 | D77: pg | E77: pix | J77: Vestuario
B78: 13 | C78: 0 | D78: pg | E78: bradesco cartoes | J78: Padaria
B79: 15 | C79: 0 | D79: pg | E79: bradesco cartoes | J79: combustivel
B80: 16 | C80: 0 | D80: pg | E80: bradesco cartoes | J80: Padaria
B81: 19 | C81: 0 | D81: pg | E81: bradesco cartoes | J81: Vestuario
B82: 19 | C82: 0 | D82: pg | E82: bradesco cartoes | J82: Padaria
... B117: 29 | C117: 0 | D117: pg | E117: pix | J117: estacionamentos
B118: 28 | C118: 0 | E118: nubank card
A120: boleto pessoal | C120: =('Resumo 2023'!C68)*0.3-(250) -> 2899.115
A121: total | C121: =SUM(C2:C118) -> 7246.8 | D121: =('Resumo 2023'!AA68)-C121-C120 -> 351.135
E132: total pago | F132: =SUMIF(D2:D118,"pg",C2:C118) -> 5692.56
M149: bra

Sheet ago25
A1: ma | B1: dia | C1: valor | D1: situacao | E1: forma de pagamento | F1: beneficiado | G1: outcome | H1: subclassificacao | I1: centro de custo | J1: categoria | L1: tipo de despesas | M1: tag
A2: escolar Arthur | B2: 5 | C2: 789 | D2: pg | E2: boleto | F2: Arthur | G2: bradesco conta | H2: despesas pessoais | I2: despesas essenciais | J2: escola/faculdade | L2: fixa
A3: Faculdade Aline | B3: 5 | C3: 850 | D3: pg | E3: boleto | F3: Aline | G3: bradesco conta | H3: despesas pessoais | I3: despesas essenciais | J3: escola/faculdade | L3: fixa
A4: Dentista Arthur | B4: 5 | C4: 0 | D4: pg | E4: Bradesco cartoes | F4: Arthur | G4: bradesco conta | H4: despesas pessoais | I4: despesas essenciais | J4: dentista | L4: fixa
A5: Conta de energia | B5: 14 | C5: 118 | D5: pg | E5: boleto | F5: familia | G5: santander conta | H5: habitacao | I5: despesas essenciais | J5: Energia | L5: variavel
A6: internet fixa | B6: 11 | C6: 132.76 | D6: open | E6: boleto | F6: familia | G6: bradesco conta | H6: habitacao | I6: despesas essenciais | J6: Internet | L6: fixa
A7: internet TIM móvel | B7: 25 | C7: 99.9 | D7: pg | E7: debito automatico | F7: Alex | G7: bradesco conta | H7: habitacao | I7: despesas essenciais | J7: Internet movel | L7: fixa
A8: streaming HBO | B8: 30 | C8: 19.95 | D8: open | E8: nubank card | F8: familia | G8: nubank conta | H8: habitacao | J8: streaming | L8: fixa
A9: Apple Tv | B9: 16 | C9: 0 | D9: closed | E9: nubank card | F9: familia | G9: nubank conta | H9: habitacao | J9: streaming | L9: fixa
A10: streaming amazonPrime | B10: 5 | C10: 0 | D10: pg | E10: nubank card | F10: familia | G10: nubank conta | H10: habitacao | J10: streaming | L10: fixa
A11: assinatura mercado livre | B11: 2 | C11: 24.9 | D11: pg | E11: nubank card | F11: familia | G11: nubank conta | H11: habitacao | J11: streaming | L11: fixa
A12: contra contabilidade | B12: 15 | C12: 0 | D12: closed | E12: nubank card | F12: Alex | G12: nubank conta | H12: despesas pessoais | J12: contabilidade | L12: fixa
A13: assinatura NETFLIX | B13: 8 | C13: 44.9 | D13: pg | E13: nubank card | F13: familia | G13: nubank conta | H13: habitacao | J13: streaming | L13: fixa
A14: assinatura GamePass | B14: 15 | C14: 0 | D14: open | E14: nubank card | F14: familia | G14: nubank conta | H14: habitacao | J14: streaming | L14: fixa
A15: seguro PIER carro | B15: 27 | C15: 244.12 | D15: open | E15: nubank card | F15: familia | G15: nubank conta | H15: transporte | I15: despesas essenciais | J15: seguro | L15: fixa
A16: curso rocketseatPlus | B16: 2 | C16: 0 | D16: open | E16: nubank card | F16: Alex | G16: nubank conta | H16: educacao | I16: educacao | J16: cursos | L16: fixa | N16: 45992
A17: gympass | B17: 27 | C17: =89.9+139.9 -> 229.8 | D17: open | E17: nubank card | F17: Alex | G17: nubank conta | H17: despesas pessoais | I17: despesas essenciais | J17: academia | L17: fixa
A18: Condominio | B18: 10 | C18: 20 | D18: open | E18: Pix | F18: familia | G18: nubank conta | H18: habitacao | I18: despesas essenciais | J18: manutenção domiciliar
A19: pix aline | B19: 8 | C19: 500 | D19: pg | E19: Pix | G19: bradesco conta | H19: habitacao | J19: pix aline
A20: Curso Ingles | B20: 15 | C20: 380 | D20: pg | E20: Pix | G20: bradesco conta | H20: habitacao | J20: cursos
A21: carrefour Tv 7/8 | B21: 6 | C21: 328.55 | D21: open | E21: bradesco cartoes | G21: bradesco conta | H21: habitacao | J21: reforma casa
A22: Painel solar 6/12 | B22: 17 | C22: 777.56 | D22: open | E22: bradesco cartoes | G22: bradesco conta | H22: habitacao | J22: painel solar
A23: futebol domingo | B23: 10 | C23: 60 | D23: open | E23: Pix | G23: bradesco conta | H23: habitacao | J23: Lazer
A24: padaria | B24: 0 | C24: 4 | D24: pg | E24: Pix | G24: bradesco conta | H24: habitacao | J24: Padaria | N24: 45324
A25: egaalimentos | B25: 0 | C25: 16 | D25: pg | E25: bradesco cartoes | G25: bradesco conta | H25: habitacao | J25: mercado
A26: gladiador pet shop | B26: 0 | C26: 405 | D26: pg | E26: bradesco cartoes | G26: bradesco conta | J26: Pet | N26: 45354
A27: rodo gril | B27: 0 | C27: 99.1 | D27: pg | E27: bradesco cartoes | G27: bradesco conta | H27: habitacao | J27: Lazer
A28: atacadao | B28: 0 | C28: 295.94 | D28: pg | E28: bradesco cartoes | G28: bradesco conta | J28: mercado
A29: novo rio agua | B29: 1 | C29: 28 | D29: pg | E29: bradesco cartoes | G29: bradesco conta | J29: mercado | N29: 45872
A30: icaroduarte | B30: 1 | C30: 8 | D30: pg | E30: bradesco cartoes | G30: bradesco conta | J30: outros | N30: 45993
A31: padaria | B31: 1 | C31: 9.5 | D31: pg | E31: bradesco cartoes | G31: nubank conta | H31: habitacao | J31: Padaria
A32: drogaria | B32: 2 | C32: 8 | D32: pg | E32: bradesco cartoes | G32: bradesco conta | J32: farmacia
A33: petz | B33: 2 | C33: 920.05 | D33: pg | E33: bradesco cartoes | G33: bradesco conta | J33: Pet
A34: hzie variedades | B34: 2 | C34: 29.99 | D34: pg | E34: bradesco cartoes | G34: bradesco conta | J34: outros
A35: estacionamento | B35: 2 | C35: 5 | D35: pg | E35: bradesco cartoes | G35: bradesco conta | J35: estacionamentos
A36: cacula | B36: 2 | C36: 15.04 | D36: pg | E36: bradesco cartoes | G36: bradesco conta | J36: material escolar
A37: puro gas | B37: 2 | C37: 64.7 | D37: pg | E37: bradesco cartoes | G37: bradesco conta | J37: combustivel
A38: padaria | B38: 3 | C38: 10.4 | D38: pg | E38: bradesco cartoes | G38: bradesco conta | J38: Padaria | M38: ferias
A39: drogaria tamoio | B39: 3 | C39: 32.3 | D39: pg | E39: bradesco cartoes | G39: bradesco conta | J39: farmacia
A40: assai | B40: 3 | C40: 139.55 | D40: pg | E40: bradesco cartoes | G40: bradesco conta | J40: mercado
A41: garfo e faca | B41: 4 | C41: 98.58 | D41: pg | E41: bradesco cartoes | G41: bradesco conta | J41: Lazer
A42: cantina alfredo backer | B42: 5 | C42: 105 | D42: pg | E42: bradesco cartoes | G42: bradesco conta | J42: Vestuario
A43: sacolao barateiro | B43: 6 | C43: 28.22 | D43: pg | E43: bradesco cartoes | G43: bradesco conta | J43: Feira
A44: katarynemotta | B44: 8 | C44: 12 | D44: pg | E44: bradesco cartoes | G44: bradesco conta | J44: Feira
A45: padaria | B45: 8 | C45: 4 | D45: pg | E45: bradesco cartoes | G45: bradesco conta | J45: Padaria
A46: auto posto top | B46: 8 | C46: 56.24 | D46: pg | E46: bradesco cartoes | G46: bradesco conta | J46: combustivel
A47: farmelhor | B47: 8 | C47: 29.59 | D47: pg | E47: bradesco cartoes | G47: bradesco conta | J47: farmacia
A48: grupo genius brasil p | B48: 8 | C48: 89.5 | D48: pg | E48: bradesco cartoes | G48: bradesco conta | J48: mercado
A49: guanabara | B49: 8 | C49: 269.21 | D49: pg | E49: bradesco cartoes | G49: bradesco conta | J49: mercado
A50: padaria | B50: 9 | C50: 4 | D50: pg | E50: bradesco cartoes | G50: bradesco conta | J50: Padaria
... A54: indigo | B54: 10 | C54: 32 | D54: pg | E54: bradesco cartoes | G54: bradesco conta | J54: estacionamentos
A55: delirio tropical | B55: 10 | C55: 45 | D55: pg | E55: bradesco cartoes | J55: Lazer
A56: padaria | B56: 12 | C56: 4 | D56: pg | E56: bradesco cartoes | J56: Padaria
A57: auto posto top | B57: 12 | C57: 50 | D57: pg | E57: bradesco cartoes | J57: combustivel
A58: leandro mayer | B58: 14 | C58: 47 | D58: pg | E58: bradesco cartoes | J58: Lazer
A59: padaria | B59: 14 | C59: 4 | E59: bradesco cartoes | J59: Padaria
A60: dayse10comercio | B60: 14 | C60: 29.44 | D60: pg | E60: bradesco cartoes | J60: Feira
A61: paraiso | B61: 14 | C61: 267.9 | D61: pg | E61: bradesco cartoes | J61: Vestuario
A62: oboticario | B62: 14 | C62: 152.99 | D62: pg | E62: bradesco cartoes | J62: mercado
A63: posto luna | B63: 15 | C63: 50 | D63: pg | E63: bradesco cartoes | J63: combustivel
A64: casa pedro | B64: 16 | C64: 79.81 | D64: pg | E64: bradesco cartoes | J64: mercado
A65: boleriadavo | B65: 16 | C65: 45.9 | D65: pg | E65: bradesco cartoes | J65: Lazer
A66: padaria | B66: 16 | C66: 7 | D66: pg | E66: bradesco cartoes | J66: Padaria
A67: emallafrios | B67: 16 | C67: 23.1 | D67: pg | E67: bradesco cartoes | J67: mercado
A68: rafael custodio d | B68: 17 | C68: 7.56 | D68: pg | E68: bradesco cartoes | J68: Feira
A69: boleto | B69: 12 | C69: 2056 | D69: pg | E69: pix | J69: boleto
A70: tapete higienico | B70: 13 | C70: 51 | D70: pg | E70: nubank card | J70: Pet
A71: mercado livre projeto | B71: 12 | C71: =72.92+16.88-C70 -> 38.8 | D71: pg | E71: nubank card | J71: projetos
A72: acumputura | B72: 23 | C72: 440 | D72: pg | E72: pix | J72: Pet
A73: cacula | B73: 15 | C73: 11.46 | D73: pg | E73: bradesco cartoes | J73: material escolar
A74: centauro | B74: 15 | C74: 359.98 | D74: pg | E74: bradesco cartoes | J74: gift
A75: burguer king | B75: 15 | C75: 79.8 | D75: pg | E75: bradesco cartoes | J75: Lazer
A76: deposito racao | B76: 13 | C76: -750 | D76: pg | E76: bradesco cartoes | J76: Pet
A77: camisa treino | B77: 17 | C77: 55 | D77: pg | E77: pix | J77: Vestuario
A78: cacula | B78: 15 | C78: 11.46 | D78: pg | E78: bradesco cartoes | J78: Padaria
A79: leandro mayer | B79: 19 | C79: 47 | D79: pg | E79: bradesco cartoes | J79: combustivel
A80: egaalimentos | B80: 19 | C80: 18 | D80: pg | E80: bradesco cartoes | J80: Padaria
A81: nova fruit | B81: 21 | C81: 15.25 | D81: pg | E81: bradesco cartoes | J81: Vestuario
A82: puro gas | B82: 21 | C82: 50 | D82: pg | E82: bradesco cartoes | J82: Padaria
A83: lgm distribuidora | B83: 22 | C83: 11 | D83: pg | E83: bradesco cartoes | J83: Lazer
... A109: petz | B109: 31 | C109: 837.62 | D109: pg | E109: pix | J109: pix aline
C110: 0 | D110: pg | E110: pix | J110: pix aline
B111: 15 | C111: 0 | D111: pg | E111: pix | J111: mercado
B112: 15 | C112: 0 | D112: pg | E112: pix | J112: gift
B113: 16 | C113: 0 | D113: pg | E113: pix | J113: outros
B114: 16 | C114: 0 | D114: pg | E114: pix | J114: estacionamentos
B115: 21 | C115: 0 | D115: pg | E115: pix | J115: pix aline
B116: 27 | C116: 0 | D116: pg | E116: pix | J116: pix aline
B117: 29 | C117: 0 | D117: pg | E117: pix | J117: estacionamentos
B118: 28 | C118: 0 | E118: nubank card
A120: boleto pessoal | C120: =('Resumo 2023'!C68)*0.3-(250) -> 2899.115
A121: total | C121: =SUM(C2:C118) -> 14115.11 | D121: =('Resumo 2023'!AA68)-C121-C120 -> -6517.175
E132: total pago | F132: =SUMIF(D2:D118,"pg",C2:C118) -> 12298.37
M149: bra

Sheet set25
A1: ma | B1: dia | C1: valor | D1: situacao | E1: forma de pagamento | F1: beneficiado | G1: outcome | H1: subclassificacao | I1: centro de custo | J1: categoria | L1: tipo de despesas | M1: tag
A2: escolar Arthur | B2: 5 | C2: 789 | D2: pg | E2: boleto | F2: Arthur | G2: bradesco conta | H2: despesas pessoais | I2: despesas essenciais | J2: escola/faculdade | L2: fixa
A3: Faculdade Aline | B3: 5 | C3: 850 | D3: pg | E3: boleto | F3: Aline | G3: bradesco conta | H3: despesas pessoais | I3: despesas essenciais | J3: escola/faculdade | L3: fixa
A4: Dentista Arthur | B4: 5 | C4: 0 | D4: pg | E4: Bradesco cartoes | F4: Arthur | G4: bradesco conta | H4: despesas pessoais | I4: despesas essenciais | J4: dentista | L4: fixa
A5: Conta de energia | B5: 14 | C5: 118 | D5: pg | E5: boleto | F5: familia | G5: santander conta | H5: habitacao | I5: despesas essenciais | J5: Energia | L5: variavel
A6: internet fixa | B6: 11 | C6: 132.76 | D6: open | E6: boleto | F6: familia | G6: bradesco conta | H6: habitacao | I6: despesas essenciais | J6: Internet | L6: fixa
A7: internet TIM móvel | B7: 25 | C7: 99.9 | D7: pg | E7: debito automatico | F7: Alex | G7: bradesco conta | H7: habitacao | I7: despesas essenciais | J7: Internet movel | L7: fixa
A8: streaming HBO | B8: 30 | C8: 19.95 | D8: open | E8: nubank card | F8: familia | G8: nubank conta | H8: habitacao | J8: streaming | L8: fixa
A9: Apple Tv | B9: 16 | C9: 0 | D9: closed | E9: nubank card | F9: familia | G9: nubank conta | H9: habitacao | J9: streaming | L9: fixa
A10: streaming amazonPrime | B10: 5 | C10: 0 | D10: pg | E10: nubank card | F10: familia | G10: nubank conta | H10: habitacao | J10: streaming | L10: fixa
A11: assinatura mercado livre | B11: 2 | C11: 24.9 | D11: pg | E11: nubank card | F11: familia | G11: nubank conta | H11: habitacao | J11: streaming | L11: fixa
A12: contra contabilidade | B12: 15 | C12: 0 | D12: closed | E12: nubank card | F12: Alex | G12: nubank conta | H12: despesas pessoais | J12: contabilidade | L12: fixa
A13: assinatura NETFLIX | B13: 8 | C13: 44.9 | D13: pg | E13: nubank card | F13: familia | G13: nubank conta | H13: habitacao | J13: streaming | L13: fixa
A14: assinatura GamePass | B14: 15 | C14: 0 | D14: open | E14: nubank card | F14: familia | G14: nubank conta | H14: habitacao | J14: streaming | L14: fixa
A15: seguro PIER carro | B15: 27 | C15: 244.12 | D15: open | E15: nubank card | F15: familia | G15: nubank conta | H15: transporte | I15: despesas essenciais | J15: seguro | L15: fixa
A16: curso rocketseatPlus | B16: 2 | C16: 0 | D16: open | E16: nubank card | F16: Alex | G16: nubank conta | H16: educacao | I16: educacao | J16: cursos | L16: fixa | N16: 45992
A17: gympass | B17: 27 | C17: =89.9+139.9 -> 229.8 | D17: open | E17: nubank card | F17: Alex | G17: nubank conta | H17: despesas pessoais | I17: despesas essenciais | J17: academia | L17: fixa
A18: Condominio | B18: 10 | C18: 20 | D18: open | E18: Pix | F18: familia | G18: nubank conta | H18: habitacao | I18: despesas essenciais | J18: manutenção domiciliar
A19: pix aline | B19: 8 | C19: 500 | D19: pg | E19: Pix | G19: bradesco conta | H19: habitacao | J19: pix aline
C20: 380 | D20: pg | E20: Pix | G20: bradesco conta | H20: habitacao | J20: cursos
A21: carrefour Tv 8/8 | B21: 6 | C21: 328.55 | D21: open | E21: bradesco cartoes | G21: bradesco conta | H21: habitacao | J21: reforma casa
A22: Painel solar 7/12 | B22: 17 | C22: 777.56 | D22: open | E22: bradesco cartoes | G22: bradesco conta | H22: habitacao | J22: painel solar
A23: padaria | B23: 0 | C23: 4 | D23: open | E23: bradesco cartoes | G23: bradesco conta | H23: habitacao | J23: Lazer
A24: egaalimentos | B24: 26 | C24: 36 | D24: pg | E24: bradesco cartoes | G24: bradesco conta | H24: habitacao | J24: Padaria | N24: 45324
A25: katarynedamotta | B25: 0 | C25: 24 | D25: pg | E25: bradesco cartoes | G25: bradesco conta | H25: habitacao | J25: mercado
A26: purogras | B26: 0 | C26: 40 | D26: pg | E26: bradesco cartoes | G26: bradesco conta | J26: Pet | N26: 45354
A27: padaria | B27: 0 | C27: 3 | D27: pg | E27: bradesco cartoes | G27: bradesco conta | H27: habitacao | J27: Lazer
A28: assim assado | B28: 0 | C28: 23 | D28: pg | E28: bradesco cartoes | G28: bradesco conta | J28: mercado
A29: padaria | B29: 0 | C29: 4.2 | D29: pg | E29: bradesco cartoes | G29: bradesco conta | J29: mercado | N29: 45872
A30: atacadao | B30: 0 | C30: 235.14 | D30: pg | E30: bradesco cartoes | G30: bradesco conta | J30: outros | N30: 45993
A31: daniel | B31: 0 | C31: 9 | D31: pg | E31: bradesco cartoes | G31: nubank conta | H31: habitacao | J31: Padaria
A32: atacadao posto 13 | B32: 0 | C32: 64.88 | D32: pg | E32: bradesco cartoes | G32: bradesco conta | J32: farmacia
A33: boulevard 425 comerci | B33: 0 | C33: 79.8 | D33: pg | E33: bradesco cartoes | G33: bradesco conta | J33: Pet
A34: Auto posto | B34: 1 | C34: 50 | D34: pg | E34: bradesco cartoes | G34: bradesco conta | J34: outros
A35: padaria | B35: 1 | C35: 3 | D35: pg | E35: bradesco cartoes | G35: bradesco conta | J35: estacionamentos
A36: egaalimentos | B36: 1 | C36: 56 | D36: pg | E36: bradesco cartoes | G36: bradesco conta | J36: material escolar
A37: drogaria tamoio | B37: 1 | C37: 28.99 | D37: pg | E37: bradesco cartoes | G37: bradesco conta | J37: combustivel
A38: dayse10comercio | B38: 2 | C38: 27.6 | D38: pg | E38: bradesco cartoes | G38: bradesco conta | J38: Padaria | M38: ferias
A39: guanabara | B39: 2 | C39: 287.07 | D39: pg | E39: bradesco cartoes | G39: bradesco conta | J39: farmacia
A40: Airbnb | B40: 3 | C40: 754.08 | D40: pg | E40: bradesco cartoes | G40: bradesco conta | J40: mercado
A41: burguer king | B41: 4 | C41: 77.8 | D41: pg | E41: bradesco cartoes | G41: bradesco conta | J41: Lazer
A42: clube da sfiha | B42: 5 | C42: 164.89 | D42: pg | E42: bradesco cartoes | G42: bradesco conta | J42: Vestuario
A43: Auto posto | B43: 5 | C43: 55.78 | D43: pg | E43: bradesco cartoes | G43: bradesco conta | J43: Feira
A44: egaalimentos | B44: 5 | C44: 38 | D44: pg | E44: bradesco cartoes | G44: bradesco conta | J44: Feira
A45: padaria | B45: 5 | C45: 4 | D45: pg | E45: bradesco cartoes | G45: bradesco conta | J45: Padaria
A46: mercado extra | B46: 5 | C46: 154.94 | D46: pg | E46: bradesco cartoes | G46: bradesco conta | J46: combustivel
A47: posto rasa | B47: 5 | C47: 68.14 | D47: pg | E47: bradesco cartoes | G47: bradesco conta | J47: farmacia
A48: via lagos rio bonito | B48: 5 | C48: 30.6 | D48: pg | E48: bradesco cartoes | G48: bradesco conta | J48: mercado
A49: tubarao inoa | B49: 5 | C49: 34.95 | G49: bradesco conta | J49: mercado
A50: lojas americanas | B50: 6 | C50: 52.95 | D50: pg | E50: bradesco cartoes | G50: bradesco conta | J50: Padaria
A51: samsara | B51: 6 | C51: 253 | D51: pg | E51: bradesco cartoes | G51: bradesco conta | J51: mercado
A52: mcdonalds | B52: 6 | C52: 25 | D52: pg | E52: bradesco cartoes | G52: bradesco conta | J52: Lazer
A53: hortifruit | B53: 6 | C53: 25.44 | D53: pg | E53: bradesco cartoes | G53: bradesco conta | J53: Feira
A54: posto rasa | B54: 7 | C54: 46.6 | D54: pg | E54: bradesco cartoes | G54: bradesco conta | J54: estacionamentos
A55: via lagos rio bonito | B55: 7 | C55: 30.6 | D55: pg | E55: bradesco cartoes | J55: Lazer
A56: churrascaria m3c00 del | B56: 7 | C56: 276.2 | D56: pg | E56: bradesco cartoes | J56: Padaria
A57: padaria | B57: 8 | C57: 9 | D57: pg | E57: bradesco cartoes | J57: combustivel
A58: to aky estacionamento | B58: 8 | C58: 8 | D58: pg | E58: bradesco cartoes | J58: Lazer
A59: burguer king | B59: 8 | C59: 38.9 | E59: bradesco cartoes | J59: Padaria
A60: ki chopp | B60: 9 | C60: 104.05 | D60: pg | E60: bradesco cartoes | J60: Feira
A61: rosilenemontalvao | B61: 9 | C61: 34.61 | D61: pg | E61: bradesco cartoes | J61: Vestuario
A62: Auto posto | B62: 10 | C62: 67.51 | D62: pg | E62: bradesco cartoes | J62: mercado
A63: egaalimentos | B63: 10 | C63: 38 | D63: pg | E63: bradesco cartoes | J63: combustivel
A64: cassel frutas | B64: 11 | C64: 29.07 | D64: pg | E64: bradesco cartoes | J64: mercado
A65: padaria | B65: 12 | C65: 7 | D65: pg | E65: bradesco cartoes | J65: Lazer
A66: leandro mayer | B66: 12 | C66: 50 | D66: pg | E66: bradesco cartoes | J66: Padaria
A67: padaria | B67: 12 | C67: 4 | D67: pg | E67: bradesco cartoes | J67: mercado
A68: ac cortes | B68: 12 | C68: 34.44 | D68: pg | E68: bradesco cartoes | J68: Feira
A69: atacadao | B69: 13 | C69: 91.57 | D69: pg | E69: bradesco cartoes | J69: boleto
A70: outback | B70: 14 | C70: 281.68 | D70: pg | E70: bradesco cartoes | J70: Pet
A71: kibarato | B71: 14 | C71: 67.7 | D71: pg | E71: bradesco cartoes | J71: projetos
... A109: Vulcabras Sp(tenis | B109: 14 | C109: 581.38 | D109: pg | E109: pix | J109: pix aline
A110: Aliexpress | B110: 17 | C110: =14.58+104.67+85.7 -> 204.95 | D110: pg | E110: pix | J110: pix aline
A111: petz | B111: 21 | C111: 793.45 | D111: pg | E111: pix | J111: mercado
A112: pagleve | B112: 21 | C112: 137.75 | D112: pg | E112: pix | J112: gift
A113: shopee | B113: 22 | C113: 86.9 | D113: pg | E113: pix | J113: outros
A114: ana clara | B114: 26 | C114: 8 | D114: pg | E114: pix | J114: estacionamentos
A115: Alex | B115: 27 | C115: 200 | D115: pg | E115: pix | J115: pix aline
A116: Diego Morares | B116: 27 | C116: 15 | D116: pg | E116: pix | J116: pix aline
A117: Acumputura | B117: 27 | C117: 440 | D117: pg | E117: pix | J117: estacionamentos
A118: Alex | B118: 10 | C118: 7000 | D118: pg | E118: pix
A120: boleto pessoal | C120: =('Resumo 2023'!C68)*0.3-(250) -> 2899.115
A121: total | C121: =SUM(C2:C118) -> 20630.8 | D121: =('Resumo 2023'!AA68)-C121-C120 -> -13032.865
E132: total pago | F132: =SUMIF(D2:D118,"pg",C2:C118) -> 18800.21
M149: bra

Sheet out25
A1: ma | B1: dia | C1: valor | D1: situacao | E1: forma de pagamento | F1: beneficiado | G1: outcome | H1: subclassificacao | I1: centro de custo | J1: categoria | L1: tipo de despesas | M1: tag
A2: escolar Arthur | B2: 5 | C2: 789 | D2: pg | E2: boleto | F2: Arthur | G2: bradesco conta | H2: despesas pessoais | I2: despesas essenciais | J2: escola/faculdade | L2: fixa
A3: Faculdade Aline | B3: 5 | C3: 850 | D3: pg | E3: boleto | F3: Aline | G3: bradesco conta | H3: despesas pessoais | I3: despesas essenciais | J3: escola/faculdade | L3: fixa
A4: Dentista Arthur | B4: 5 | C4: 0 | D4: pg | E4: Bradesco cartoes | F4: Arthur | G4: bradesco conta | H4: despesas pessoais | I4: despesas essenciais | J4: dentista | L4: fixa
A5: Conta de energia | B5: 14 | C5: 117.03 | D5: pg | E5: boleto | F5: familia | G5: santander conta | H5: habitacao | I5: despesas essenciais | J5: Energia | L5: variavel
A6: internet fixa | B6: 11 | C6: 132.76 | D6: open | E6: boleto | F6: familia | G6: bradesco conta | H6: habitacao | I6: despesas essenciais | J6: Internet | L6: fixa
A7: internet TIM móvel | B7: 25 | C7: 106.9 | D7: pg | E7: debito automatico | F7: Alex | G7: bradesco conta | H7: habitacao | I7: despesas essenciais | J7: Internet movel | L7: fixa
A8: streaming HBO | B8: 30 | C8: 19.95 | D8: open | E8: nubank card | F8: familia | G8: nubank conta | H8: habitacao | J8: streaming | L8: fixa
A9: Apple Tv | B9: 16 | C9: 0 | D9: closed | E9: nubank card | F9: familia | G9: nubank conta | H9: habitacao | J9: streaming | L9: fixa
A10: streaming amazonPrime | B10: 5 | C10: 0 | D10: pg | E10: nubank card | F10: familia | G10: nubank conta | H10: habitacao | J10: streaming | L10: fixa
A11: assinatura mercado livre | B11: 2 | C11: 24.9 | D11: pg | E11: nubank card | F11: familia | G11: nubank conta | H11: habitacao | J11: streaming | L11: fixa
A12: contra contabilidade | B12: 15 | C12: 0 | D12: closed | E12: nubank card | F12: Alex | G12: nubank conta | H12: despesas pessoais | J12: contabilidade | L12: fixa
A13: assinatura NETFLIX | B13: 8 | C13: 44.9 | D13: pg | E13: nubank card | F13: familia | G13: nubank conta | H13: habitacao | J13: streaming | L13: fixa
A14: assinatura GamePass | B14: 15 | C14: 0 | D14: open | E14: nubank card | F14: familia | G14: nubank conta | H14: habitacao | J14: streaming | L14: fixa
A15: seguro PIER carro | B15: 27 | C15: 244.12 | D15: open | E15: nubank card | F15: familia | G15: nubank conta | H15: transporte | I15: despesas essenciais | J15: seguro | L15: fixa
A16: curso rocketseatPlus | B16: 2 | C16: 0 | D16: open | E16: nubank card | F16: Alex | G16: nubank conta | H16: educacao | I16: educacao | J16: cursos | L16: fixa | N16: 45992
A17: gympass | B17: 27 | C17: =89.9+139.9 -> 229.8 | D17: open | E17: nubank card | F17: Alex | G17: nubank conta | H17: despesas pessoais | I17: despesas essenciais | J17: academia | L17: fixa
A18: Condominio | B18: 10 | C18: 20 | D18: open | E18: Pix | F18: familia | G18: nubank conta | H18: habitacao | I18: despesas essenciais | J18: manutenção domiciliar
A19: pix aline | B19: 8 | C19: 500 | D19: pg | E19: Pix | G19: bradesco conta | H19: habitacao | J19: pix aline
B20: 15 | C20: 0 | D20: pg | E20: Pix | G20: bradesco conta | H20: habitacao | J20: cursos
B21: 6 | C21: 328.55 | D21: open | E21: bradesco cartoes | G21: bradesco conta | H21: habitacao | J21: reforma casa
A22: Painel solar 8/12 | B22: 17 | C22: 777.56 | D22: open | E22: bradesco cartoes | G22: bradesco conta | H22: habitacao | J22: painel solar
A23: futebol domingo | B23: 10 | C23: 60 | D23: open | E23: Pix | G23: bradesco conta | H23: habitacao | J23: Lazer
A24: horta carioca | B24: 0 | C24: 28.89 | D24: pg | E24: Pix | G24: bradesco conta | H24: habitacao | J24: Padaria | N24: 45324
A25: pada | B25: 0 | C25: 4 | D25: pg | E25: bradesco cartoes | G25: bradesco conta | H25: habitacao | J25: mercado
A26: mp*lanchonete | B26: 0 | C26: 20 | D26: pg | E26: bradesco cartoes | G26: bradesco conta | J26: Pet | N26: 45354
A27: perrone | B27: 0 | C27: 134.8 | D27: pg | E27: bradesco cartoes | G27: bradesco conta | H27: habitacao | J27: Lazer
A28: auto posto | B28: 0 | C28: 61.21 | D28: pg | E28: bradesco cartoes | G28: bradesco conta | J28: mercado
A29: ichiban japonese food | B29: 0 | C29: 68.28 | D29: pg | E29: bradesco cartoes | G29: bradesco conta | J29: mercado | N29: 45872
A30: auto posto | B30: 0 | C30: 47.88 | D30: pg | E30: bradesco cartoes | G30: bradesco conta | J30: outros | N30: 45993
A31: padaria | B31: 1 | C31: 4 | D31: pg | E31: bradesco cartoes | G31: nubank conta | H31: habitacao | J31: Padaria
A32: lovcafe | B32: 2 | C32: 85 | D32: pg | E32: bradesco cartoes | G32: bradesco conta | J32: farmacia
A33: perrone | B33: 3 | C33: 30.5 | D33: pg | E33: bradesco cartoes | G33: bradesco conta | J33: Pet
A34: purogas | B34: 3 | C34: 50 | D34: pg | E34: bradesco cartoes | G34: bradesco conta | J34: outros
A35: purogas | B35: 3 | C35: 50 | D35: pg | E35: bradesco cartoes | G35: bradesco conta | J35: estacionamentos
A36: novo rio | B36: 4 | C36: 14 | D36: pg | E36: bradesco cartoes | G36: bradesco conta | J36: material escolar
A37: rede economia | B37: 4 | C37: 13.89 | D37: pg | E37: bradesco cartoes | G37: bradesco conta | J37: combustivel
A38: padaria | B38: 5 | C38: 4 | D38: pg | E38: bradesco cartoes | G38: bradesco conta | J38: Padaria | M38: ferias
A39: atacadao | B39: 5 | C39: 257.95 | D39: pg | E39: bradesco cartoes | G39: bradesco conta | J39: farmacia
A40: drogaria pacheco | B40: 6 | C40: 36.47 | D40: pg | E40: bradesco cartoes | G40: bradesco conta | J40: mercado
A41: drogaria tamoio | B41: 6 | C41: 15.99 | D41: pg | E41: bradesco cartoes | G41: bradesco conta | J41: Lazer
A42: drogaria tamoio | B42: 6 | C42: 42.19 | D42: pg | E42: bradesco cartoes | G42: bradesco conta | J42: Vestuario
A43: r a intima lingerie | B43: 6 | C43: 71.96 | D43: pg | E43: bradesco cartoes | G43: bradesco conta | J43: Feira
A44: nova hortifruit | B44: 7 | C44: 18.07 | D44: pg | E44: bradesco cartoes | G44: bradesco conta | J44: Feira
A45: auto posto | B45: 8 | C45: 50 | D45: pg | E45: bradesco cartoes | G45: bradesco conta | J45: Padaria
A46: cinthia de souza andrade | B46: 9 | C46: 25 | D46: pg | E46: bradesco cartoes | G46: bradesco conta | J46: combustivel
A47: lboleria davo | B47: 9 | C47: 45.9 | D47: pg | E47: bradesco cartoes | G47: bradesco conta | J47: farmacia
A48: to aky estacionamento | B48: 9 | C48: 5 | D48: pg | E48: bradesco cartoes | G48: bradesco conta | J48: mercado
A49: riachuelo | B49: 9 | C49: 19.99 | D49: pg | E49: bradesco cartoes | G49: bradesco conta | J49: mercado
A50: padaria | B50: 10 | C50: 4 | D50: pg | E50: bradesco cartoes | G50: bradesco conta | J50: Padaria
... A54: estacionamento | B54: 11 | C54: 5 | D54: pg | E54: bradesco cartoes | G54: bradesco conta | J54: estacionamentos
A55: burguer king | B55: 11 | C55: 46.9 | D55: pg | E55: bradesco cartoes | J55: Lazer
A56: casas pedro | B56: 11 | C56: 136.81 | D56: pg | E56: bradesco cartoes | J56: Padaria
A57: auto posto | B57: 12 | C57: 57.02 | D57: pg | E57: bradesco cartoes | J57: combustivel
A58: padaria | B58: 12 | C58: 4 | D58: pg | E58: bradesco cartoes | J58: Lazer
A59: atacadao | B59: 12 | C59: 276.57 | E59: bradesco cartoes | J59: Padaria
A60: katarynedamotta | B60: 13 | C60: 24 | D60: pg | E60: bradesco cartoes | J60: Feira
A61: silviabatista | B61: 16 | C61: 99.99 | D61: pg | E61: bradesco cartoes | J61: Vestuario
A62: drogaraia | B62: 16 | C62: 11.89 | D62: pg | E62: bradesco cartoes | J62: mercado
A63: estacionamento | B63: 16 | C63: 7 | D63: pg | E63: bradesco cartoes | J63: combustivel
A64: burguer king | B64: 16 | C64: 77.8 | D64: pg | E64: bradesco cartoes | J64: mercado
A65: auto posto | B65: 17 | C65: 61.57 | D65: pg | E65: bradesco cartoes | J65: Lazer
A66: padaria | B66: 17 | C66: 11.5 | D66: pg | E66: bradesco cartoes | J66: Padaria
A67: lovcafe | B67: 17 | C67: 78 | D67: pg | E67: bradesco cartoes | J67: mercado
A68: posto vip | B68: 17 | C68: 50 | D68: pg | E68: bradesco cartoes | J68: Feira
A69: ferart coisa e tal | B69: 18 | C69: 100.99 | D69: pg | E69: pix | J69: boleto
A70: cassel frutas | B70: 42.19 | C70: 51 | D70: pg | E70: nubank card | J70: Pet
A71: atacadao | B71: 18 | C71: 181.03 | D71: pg | E71: nubank card | J71: projetos
... A115: antonio carlos | B115: 20 | C115: 5 | D115: pg | E115: pix | J115: pix aline
B116: 27 | C116: 0 | D116: pg | E116: pix | J116: pix aline
B117: 29 | C117: 0 | D117: pg | E117: pix | J117: estacionamentos
B118: 28 | C118: 0 | E118: nubank card
A120: boleto pessoal | C120: =('Resumo 2023'!C68)*0.3-(250) -> 2899.115
A121: total | C121: =SUM(C2:C118) -> 16481.26 | D121: =('Resumo 2023'!AA68)-C121-C120 -> -8883.325
E132: total pago | F132: =SUMIF(D2:D118,"pg",C2:C118) -> 14391.95
M149: bra

Sheet jul25
A1: Descrição | B1: dia | C1: valor | D1: situacao | E1: forma de pagamento | F1: beneficiado | G1: outcome | H1: subclassificacao | I1: centro de custo | J1: categoria | L1: tipo de despesas | M1: tag
A2: escolar Arthur | B2: 5 | C2: 789 | D2: pg | E2: boleto | F2: Arthur | G2: bradesco conta | H2: despesas pessoais | I2: despesas essenciais | J2: escola/faculdade | L2: fixa
A3: Faculdade Aline | B3: 5 | C3: 850 | D3: pg | E3: boleto | F3: Aline | G3: bradesco conta | H3: despesas pessoais | I3: despesas essenciais | J3: escola/faculdade | L3: fixa
A4: Dentista Arthur | B4: 5 | C4: 140 | D4: pg | E4: Bradesco cartoes | F4: Arthur | G4: bradesco conta | H4: despesas pessoais | I4: despesas essenciais | J4: dentista | L4: fixa
A5: Conta de energia | B5: 14 | C5: 60 | D5: open | E5: boleto | F5: familia | G5: santander conta | H5: habitacao | I5: despesas essenciais | J5: Energia | L5: variavel
A6: internet fixa | B6: 11 | C6: 132.76 | D6: open | E6: boleto | F6: familia | G6: bradesco conta | H6: habitacao | I6: despesas essenciais | J6: Internet | L6: fixa
A7: internet TIM móvel | B7: 25 | C7: 99.9 | D7: open | E7: debito automatico | F7: Alex | G7: bradesco conta | H7: habitacao | I7: despesas essenciais | J7: Internet movel | L7: fixa
A8: streaming HBO | B8: 30 | C8: 19.95 | D8: open | E8: nubank card | F8: familia | G8: nubank conta | H8: habitacao | J8: streaming | L8: fixa
A9: Apple Tv | B9: 16 | C9: 0 | D9: closed | E9: nubank card | F9: familia | G9: nubank conta | H9: habitacao | J9: streaming | L9: fixa
A10: streaming amazonPrime | B10: 5 | C10: 0 | D10: pg | E10: nubank card | F10: familia | G10: nubank conta | H10: habitacao | J10: streaming | L10: fixa
A11: assinatura mercado livre | B11: 2 | C11: 24.9 | D11: pg | E11: nubank card | F11: familia | G11: nubank conta | H11: habitacao | J11: streaming | L11: fixa
A12: contra contabilidade | B12: 15 | C12: 0 | D12: closed | E12: nubank card | F12: Alex | G12: nubank conta | H12: despesas pessoais | J12: contabilidade | L12: fixa
A13: assinatura NETFLIX | B13: 8 | C13: 44.9 | D13: pg | E13: nubank card | F13: familia | G13: nubank conta | H13: habitacao | J13: streaming | L13: fixa
A14: assinatura GamePass | B14: 15 | C14: 0 | D14: open | E14: nubank card | F14: familia | G14: nubank conta | H14: habitacao | J14: streaming | L14: fixa
A15: seguro PIER carro | B15: 27 | C15: 244.12 | D15: open | E15: nubank card | F15: familia | G15: nubank conta | H15: transporte | I15: despesas essenciais | J15: seguro | L15: fixa
A16: curso rocketseatPlus | B16: 2 | C16: 0 | D16: open | E16: nubank card | F16: Alex | G16: nubank conta | H16: educacao | I16: educacao | J16: cursos | L16: fixa | N16: 45992
A17: gympass | B17: 27 | C17: =89.9+139.9 -> 229.8 | D17: open | E17: nubank card | F17: Alex | G17: nubank conta | H17: despesas pessoais | I17: despesas essenciais | J17: academia | L17: fixa
A18: Condominio | B18: 10 | C18: 20 | D18: pg | E18: Pix | F18: familia | G18: nubank conta | H18: habitacao | I18: despesas essenciais | J18: manutenção domiciliar
A19: pix aline | B19: 8 | C19: 500 | D19: pg | E19: Pix | G19: bradesco conta | H19: habitacao | J19: pix aline
A20: Curso Ingles | B20: 5 | C20: 380 | D20: open | E20: Pix | G20: bradesco conta | H20: habitacao | J20: cursos
A21: carrefour Tv 6/8 | B21: 6 | C21: 328.55 | D21: pg | E21: bradesco cartoes | G21: bradesco conta | H21: habitacao | J21: reforma casa
A22: Painel solar 5/12 | B22: 17 | C22: 777.56 | D22: pg | E22: bradesco cartoes | G22: bradesco conta | H22: habitacao | J22: painel solar
A23: Futebol Domingo | B23: 10 | C23: 60 | D23: pg | E23: Pix | G23: bradesco conta | H23: habitacao | J23: Lazer
A24: boleto | B24: 9 | C24: 0 | D24: pg | E24: Pix | G24: bradesco conta | H24: habitacao | J24: boleto | N24: 45324
A25: habibs | B25: 0 | C25: 0 | D25: pg | E25: bradesco cartoes | G25: bradesco conta | H25: habitacao | J25: Lazer
A26: pastel | B26: 0 | C26: 0 | D26: pg | E26: bradesco cartoes | G26: bradesco conta | J26: Lazer | N26: 45354
A27: auto posto t | B27: 0 | C27: 50 | D27: pg | E27: bradesco cartoes | G27: bradesco conta | H27: habitacao | J27: combustivel
A28: petz | B28: 0 | C28: 230.76 | D28: pg | E28: bradesco cartoes | G28: bradesco conta | J28: Pet
A29: cia do doce | B29: 0 | C29: 21.55 | D29: pg | E29: bradesco cartoes | G29: bradesco conta | J29: mercado | N29: 45872
A30: raizes de minas | B30: 0 | C30: 95.8 | D30: pg | E30: bradesco cartoes | G30: bradesco conta | J30: Lazer | N30: 45993
A31: daniel | B31: 0 | C31: 7 | D31: pg | E31: bradesco cartoes | G31: nubank conta | H31: habitacao | J31: Lazer
A32: restaurante partage | B32: 0 | C32: 85.7 | D32: pg | E32: bradesco cartoes | G32: bradesco conta | J32: Lazer
A33: pes e patas | B33: 1 | C33: 103.9 | D33: pg | E33: bradesco cartoes | G33: bradesco conta | J33: Pet
A34: sacolao barateiro | B34: 1 | C34: 25.5 | D34: pg | E34: bradesco cartoes | G34: bradesco conta | J34: Feira
A35: pank motos | B35: 0 | C35: 130 | D35: pg | E35: bradesco cartoes | G35: bradesco conta | J35: gift
A36: casas pedro | B36: 0 | C36: 96.93 | D36: pg | E36: bradesco cartoes | G36: bradesco conta | J36: mercado
A37: jequiti | B37: 0 | C37: 57.8 | D37: pg | E37: bradesco cartoes | G37: bradesco conta | J37: gift
A38: auto posto t | B38: 0 | C38: 65.85 | D38: pg | E38: bradesco cartoes | G38: bradesco conta | J38: combustivel | M38: ferias
A39: pastel | B39: 0 | C39: 24 | D39: pg | E39: bradesco cartoes | G39: bradesco conta | J39: Lazer
A40: genius brasil (habibis) | B40: 0 | C40: 49.54 | D40: pg | E40: bradesco cartoes | G40: bradesco conta | J40: Lazer
A41: padaria | B41: 0 | C41: 4 | D41: pg | E41: bradesco cartoes | G41: bradesco conta | J41: Padaria
A42: atacadao | B42: 0 | C42: 82.96 | D42: pg | E42: bradesco cartoes | G42: bradesco conta | J42: mercado
A43: hortifuit | B43: 0 | C43: 58.32 | D43: pg | E43: bradesco cartoes | G43: bradesco conta | J43: Feira
A44: obotocario | B44: 0 | C44: 54.32 | D44: pg | E44: bradesco cartoes | G44: bradesco conta | J44: gift
A45: petz manilha | B45: 0 | C45: 27.9 | D45: pg | E45: bradesco cartoes | G45: bradesco conta | J45: Pet
A46: katarynedamotta | B46: 2 | C46: 24 | D46: pg | E46: bradesco cartoes | G46: bradesco conta | J46: Feira
A47: samantamenizes dermat | B47: 2 | C47: 230 | D47: pg | E47: bradesco cartoes | G47: bradesco conta | J47: Pet
A48: guanabara | B48: 3 | C48: 109.99 | D48: pg | E48: bradesco cartoes | G48: bradesco conta | J48: mercado
A49: drogarria 3 poderes | B49: 3 | C49: 71.97 | D49: pg | E49: bradesco cartoes | G49: bradesco conta | J49: farmacia
A50: genius brasil (habibis) | B50: 4 | C50: 59.6 | D50: pg | E50: bradesco cartoes | G50: bradesco conta | J50: Lazer
... A54: assai | B54: 6 | C54: 132.79 | D54: pg | E54: bradesco cartoes | G54: bradesco conta | J54: mercado
A55: cassel frutas | B55: 7 | C55: 38.86 | D55: pg | E55: bradesco cartoes | J55: Feira
A56: auto posto t | B56: 8 | C56: 50 | D56: pg | E56: bradesco cartoes | J56: combustivel
A57: rote casa de racoes | B57: 8 | C57: 48.6 | D57: pg | E57: bradesco cartoes | J57: manutenção domiciliar
A58: posto vip | B58: 8 | C58: 50 | D58: pg | E58: bradesco cartoes | J58: combustivel
A59: padaria | B59: 9 | C59: 4 | D59: pg | E59: bradesco cartoes | J59: Padaria
A60: assai | B60: 9 | C60: 178.38 | D60: pg | E60: bradesco cartoes | J60: mercado
A61: burguer king | B61: 9 | C61: 12.4 | D61: pg | E61: bradesco cartoes | J61: Lazer
A62: burguer king | B62: 9 | C62: 72.8 | D62: pg | E62: bradesco cartoes | J62: Lazer
A63: cacula | B63: 9 | C63: 39.97 | D63: pg | E63: bradesco cartoes | J63: material escolar
A64: padaria | B64: 12 | C64: 9 | D64: pg | E64: bradesco cartoes | J64: Padaria
A65: sacolao barateiro | B65: 12 | C65: 20.4 | D65: pg | E65: bradesco cartoes | J65: Feira
A66: katarynedamotta | B66: 12 | C66: 24 | D66: pg | E66: bradesco cartoes | J66: Feira
... A104: mercadopago | B104: 14 | C104: 193 | D104: pg | E104: nubank card | J104: Pet
B105: 23 | C105: 0 | D105: pg | E105: bradesco cartoes | J105: mercado
B106: 24 | C106: 0 | D106: pg | E106: bradesco cartoes | J106: outros
B107: 24 | C107: 0 | D107: pg | E107: bradesco cartoes | J107: Padaria
B108: 24 | C108: 0 | D108: pg | E108: bradesco cartoes | J108: manutencao veicular
B109: 12 | C109: 0 | D109: pg | E109: pix | J109: pix aline
B110: 9 | C110: 0 | D110: pg | E110: pix | J110: pix aline
B111: 15 | C111: 0 | D111: pg | E111: pix | J111: mercado
B112: 15 | C112: 0 | D112: pg | E112: pix | J112: gift
B113: 16 | C113: 0 | D113: pg | E113: pix | J113: outros
B114: 16 | C114: 0 | D114: pg | E114: pix | J114: estacionamentos
B115: 21 | C115: 0 | D115: pg | E115: pix | J115: pix aline
B116: 27 | C116: 0 | D116: pg | E116: pix | J116: pix aline
B117: 29 | C117: 0 | D117: pg | E117: pix | J117: estacionamentos
B118: 28 | C118: 0 | E118: nubank card
A120: boleto pessoal | C120: =('Resumo 2023'!C68)*0.3-(250) -> 2899.115
A121: total | C121: =SUM(C2:C118) -> 10581.7 | D121: =('Resumo 2023'!AA68)-C121-C120 -> -2983.765
E132: total pago | F132: =SUMIF(D2:D118,"pg",C2:C118) -> 9415.17
M149: bra

Sheet jun25
A1: ma | B1: dia | C1: valor | D1: situacao | E1: forma de pagamento | F1: beneficiado | G1: outcome | H1: subclassificacao | I1: centro de custo | J1: categoria | L1: tipo de despesas | M1: tag
A2: escolar Arthur | B2: 5 | C2: 789 | D2: pg | E2: boleto | F2: Arthur | G2: bradesco conta | H2: despesas pessoais | I2: despesas essenciais | J2: escola/faculdade | L2: fixa
A3: Faculdade Aline | B3: 5 | C3: 685.78 | D3: pg | E3: boleto | F3: Aline | G3: bradesco conta | H3: despesas pessoais | I3: despesas essenciais | J3: escola/faculdade | L3: fixa
A4: Dentista Arthur | B4: 5 | C4: 140 | D4: open | E4: Bradesco cartoes | F4: Arthur | G4: bradesco conta | H4: despesas pessoais | I4: despesas essenciais | J4: dentista | L4: fixa
A5: Conta de energia | B5: 14 | C5: 356.67 | D5: pg | E5: boleto | F5: familia | G5: santander conta | H5: habitacao | I5: despesas essenciais | J5: Energia | L5: variavel
A6: internet fixa | B6: 11 | C6: 132.76 | D6: pg | E6: boleto | F6: familia | G6: bradesco conta | H6: habitacao | I6: despesas essenciais | J6: Internet | L6: fixa
A7: internet TIM móvel | B7: 25 | C7: 99.9 | D7: pg | E7: debito automatico | F7: Alex | G7: bradesco conta | H7: habitacao | I7: despesas essenciais | J7: Internet movel | L7: fixa
A8: streaming HBO | B8: 30 | C8: 19.95 | D8: pg | E8: nubank card | F8: familia | G8: nubank conta | H8: habitacao | J8: streaming | L8: fixa
A9: Apple Tv | B9: 16 | C9: 0 | D9: closed | E9: nubank card | F9: familia | G9: nubank conta | H9: habitacao | J9: streaming | L9: fixa
A10: streaming amazonPrime | B10: 5 | C10: 166 | D10: pg | E10: nubank card | F10: familia | G10: nubank conta | H10: habitacao | J10: streaming | L10: fixa
A11: assinatura mercado livre | B11: 2 | C11: 24.9 | D11: pg | E11: nubank card | F11: familia | G11: nubank conta | H11: habitacao | J11: streaming | L11: fixa
A12: contra contabilidade | B12: 15 | C12: 0 | D12: open | E12: nubank card | F12: Alex | G12: nubank conta | H12: despesas pessoais | J12: contabilidade | L12: fixa
A13: assinatura NETFLIX | B13: 8 | C13: 44.9 | D13: pg | E13: nubank card | F13: familia | G13: nubank conta | H13: habitacao | J13: streaming | L13: fixa
A14: assinatura GamePass | B14: 15 | C14: 0 | D14: open | E14: nubank card | F14: familia | G14: nubank conta | H14: habitacao | J14: streaming | L14: fixa
A15: seguro PIER carro | B15: 27 | C15: 244.12 | D15: pg | E15: nubank card | F15: familia | G15: nubank conta | H15: transporte | I15: despesas essenciais | J15: seguro | L15: fixa
A16: curso rocketseatPlus | B16: 2 | C16: 0 | D16: open | E16: nubank card | F16: Alex | G16: nubank conta | H16: educacao | I16: educacao | J16: cursos | L16: fixa | N16: 45992
A17: gympass | B17: 27 | C17: =89.9+139.9 -> 229.8 | D17: pg | E17: nubank card | F17: Alex | G17: nubank conta | H17: despesas pessoais | I17: despesas essenciais | J17: academia | L17: fixa
A18: Condominio | B18: 17 | C18: 20 | D18: pg | E18: Pix | F18: familia | G18: nubank conta | H18: habitacao | I18: despesas essenciais | J18: manutenção domiciliar
A19: estacionamento | B19: 2 | C19: 5 | D19: pg | E19: Pix | G19: bradesco conta | H19: habitacao | J19: estacionamentos
A20: JoseLuiz lopes | B20: 2 | C20: 10 | D20: pg | E20: Pix | G20: bradesco conta | H20: habitacao | J20: outros
A21: parafusos | B21: 6 | C21: 9 | D21: pg | E21: Pix | G21: bradesco conta | H21: habitacao | J21: projetos
A22: Ecoponto pedagio | B22: 9 | C22: 6.2 | D22: pg | E22: Pix | G22: bradesco conta | H22: habitacao | J22: estacionamentos
A23: Recarga claro | B23: 9 | C23: 20 | D23: pg | E23: Pix | G23: bradesco conta | H23: habitacao | J23: Internet movel
A24: Recarga TIm Aline | B24: 9 | C24: 30 | D24: pg | E24: Pix | G24: bradesco conta | H24: habitacao | J24: Internet movel | N24: 45324
A25: Diaval treinamento de 09/06 | B25: 9 | C25: 380.12 | D25: pg | E25: Pix | G25: bradesco conta | H25: habitacao | J25: cursos
A26: Casa valentim | B26: 13 | C26: 3.06 | D26: pg | E26: Pix | G26: bradesco conta | J26: mercado | N26: 45354
A27: ecoponto pedagio | B27: 16 | C27: 6.2 | D27: pg | E27: Pix | G27: bradesco conta | H27: habitacao | J27: estacionamentos
A28: estacionamento | B28: 16 | C28: 5 | D28: pg | E28: Pix | G28: bradesco conta | J28: estacionamentos
A29: Junior e evelyn doce | B29: 16 | C29: 4 | D29: pg | E29: Pix | G29: bradesco conta | J29: Lazer | N29: 45872
A30: fernado esteves 17/06 | B30: 17 | C30: 5 | D30: pg | E30: Pix | G30: bradesco conta | J30: estacionamentos | N30: 45993
A31: parafusos | B31: 18 | C31: 4.8 | D31: pg | E31: Pix | G31: nubank conta | H31: habitacao | J31: projetos
A32: Jose luiz lopes de Ar 19/06 | B32: 20 | C32: 60 | D32: pg | E32: Pix | G32: bradesco conta | J32: outros
A33: Atlas sa | B33: 20 | C33: 133 | D33: pg | E33: Pix | G33: bradesco conta | J33: outros
A34: tapete higienico | B34: 26 | C34: 51.93 | D34: pg | E34: nubank card | G34: bradesco conta | J34: Pet
A35: mercado livre | B35: 19 | C35: 114.62 | D35: pg | E35: nubank card | G35: bradesco conta | J35: outros
A36: presente arthur | B36: 16 | C36: 309.28 | D36: pg | E36: nubank card | G36: bradesco conta | J36: gift
A37: futebol sabado | B37: 28 | C37: 15 | D37: pg | E37: Pix | G37: bradesco conta | J37: Lazer
A38: futebol domingo | B38: 14 | C38: 65 | D38: pg | E38: Pix | G38: bradesco conta | J38: Lazer | M38: ferias
A39: carrefour Tv 5/8 | B39: 6 | C39: 328.55 | D39: pg | E39: bradesco cartoes | G39: bradesco conta | J39: reforma casa
A40: Painel solar 4/12 | B40: 17 | C40: 777.56 | D40: pg | E40: bradesco cartoes | G40: bradesco conta | J40: painel solar
A41: burguer king | B41: 0 | C41: 69.8 | D41: pg | E41: bradesco cartoes | G41: bradesco conta | J41: Lazer
A42: padaria | B42: 0 | C42: 4 | D42: pg | E42: bradesco cartoes | G42: bradesco conta | J42: Padaria
A43: dayse10comerciode | B43: 0 | C43: 10.2 | D43: pg | E43: bradesco cartoes | G43: bradesco conta | J43: Feira
A44: Puro gas | B44: 0 | C44: 40 | D44: pg | E44: bradesco cartoes | G44: bradesco conta | J44: combustivel
A45: spoleto | B45: 0 | C45: 56.8 | D45: pg | E45: bradesco cartoes | G45: bradesco conta | J45: Lazer
A46: atacadao | B46: 0 | C46: 74.65 | D46: pg | E46: bradesco cartoes | G46: bradesco conta | J46: mercado
A47: padaria | B47: 0 | C47: 4 | D47: pg | E47: bradesco cartoes | G47: bradesco conta | J47: Padaria
A48: auto posto T | B48: 0 | C48: 65.03 | D48: pg | E48: bradesco cartoes | G48: bradesco conta | J48: combustivel
A49: china in box | B49: 0 | C49: 74.16 | D49: pg | E49: bradesco cartoes | G49: bradesco conta | J49: Lazer
A50: petz | B50: 0 | C50: 461.53 | D50: pg | E50: bradesco cartoes | G50: bradesco conta | J50: Pet
... A54: cults3d.com | B54: 1 | C54: 9.84 | D54: pg | E54: bradesco cartoes | G54: bradesco conta | J54: outros
A55: padaria | B55: 2 | C55: 9 | D55: pg | E55: Pix | J55: Padaria
A56: katarynedamotta | B56: 2 | C56: 24 | D56: pg | E56: bradesco cartoes | J56: Feira
A57: iof | B57: 2 | C57: 0.34 | D57: pg | E57: bradesco cartoes | J57: outros
A58: hortifruiti | B58: 3 | C58: 27.75 | D58: pg | E58: bradesco cartoes | J58: Feira
A59: padaria | B59: 4 | C59: 4 | D59: pg | E59: bradesco cartoes | J59: Padaria
A60: nova fruit | B60: 5 | C60: 23.48 | D60: pg | E60: bradesco cartoes | J60: Feira
A61: leandromayer | B61: 6 | C61: 70 | D61: pg | E61: bradesco cartoes | J61: outros
A62: padaria | B62: 6 | C62: 4.4 | D62: pg | E62: bradesco cartoes | J62: Padaria
A63: auto posto T | B63: 6 | C63: 60.9 | D63: pg | E63: bradesco cartoes | J63: combustivel
A64: shopee meizitechltda | B64: 6 | C64: 280.89 | D64: pg | E64: bradesco cartoes | J64: gift | M64: Férias
A65: hf studiohair | B65: 7 | C65: 40 | D65: pg | E65: bradesco cartoes | J65: Cabeleireiro | M65: Férias
A66: carrefour alcantara | B66: 7 | C66: 199.52 | D66: pg | E66: bradesco cartoes | J66: mercado | M66: Férias
A67: pes e patas | B67: 7 | C67: 103.9 | D67: pg | E67: bradesco cartoes | J67: Pet | M67: Férias
A68: grupo genius Brasil p | B68: 7 | C68: 49.54 | D68: pg | E68: bradesco cartoes | J68: outros | M68: Férias
A69: affrikagourmet | B69: 8 | C69: 85 | D69: pg | E69: bradesco cartoes | J69: Lazer | M69: Férias
A70: padaria | B70: 8 | C70: 10.9 | D70: pg | E70: bradesco cartoes | J70: Padaria | M70: Férias
A71: Bardana Natural | B71: 8 | C71: 138.27 | D71: pg | E71: bradesco cartoes | J71: Lazer | M71: Férias
A72: Superfacil va | B72: 10 | C72: 14.98 | D72: pg | E72: bradesco cartoes | J72: outros | M72: Férias
A73: cassel frutas | B73: 10 | C73: 20.55 | D73: pg | E73: bradesco cartoes | J73: Feira | M73: Férias
A74: auto posto T | B74: 11 | C74: 50 | D74: pg | E74: bradesco cartoes | J74: combustivel | M74: Férias
A75: padaria | B75: 12 | C75: 4.4 | D75: pg | E75: bradesco cartoes | J75: Padaria | M75: Férias
... A80: Burguer king | B80: 14 | C80: 69.8 | D80: pg | E80: Pix | J80: Lazer | M80: Férias
A81: assai | B81: 14 | C81: 343.96 | D81: pg | E81: Pix | J81: mercado
A82: marisa | B82: 14 | C82: 114.98 | D82: pg | E82: Pix | J82: Vestuario
A83: kifesta | B83: 14 | C83: 7.95 | D83: pg | E83: Pix | J83: utilizades domesticas
A84: soldagreste | B84: 15 | C84: 32 | D84: pg | E84: Pix | J84: Lazer
A85: Pastel Amigao | B85: 15 | C85: 25 | D85: pg | E85: Pix | J85: Lazer
A86: auto posto T | B86: 15 | C86: 50 | D86: pg | E86: Pix | J86: combustivel
A87: mp espetos | B87: 15 | C87: 24 | D87: pg | E87: Pix | J87: Lazer
A88: posto vip caneco Novem | B88: 15 | C88: 50 | D88: pg | E88: bradesco cartoes | J88: combustivel
A89: Amigao | B89: 16 | C89: 9.99 | D89: pg | E89: bradesco cartoes | J89: utilizades domesticas
A90: rafirro empadas | B90: 16 | C90: 21.5 | D90: pg | E90: bradesco cartoes | J90: Lazer
A91: vlc copias e xerox | B91: 16 | C91: 78 | D91: pg | E91: pix | J91: pix aline
A92: padaria | B92: 16 | C92: 3 | D92: pg | E92: pix | J92: Padaria
... A111: mercado livre | B111: 30 | C111: 228.16 | D111: pg | E111: nubank card | J111: academia
B112: 15 | C112: 0 | D112: pg | E112: pix | J112: gift
B113: 16 | C113: 0 | D113: pg | E113: pix | J113: outros
B114: 16 | C114: 0 | D114: pg | E114: pix | J114: estacionamentos
B115: 21 | C115: 0 | D115: pg | E115: pix | J115: pix aline
B116: 27 | C116: 0 | D116: pg | E116: pix | J116: pix aline
B117: 29 | C117: 0 | D117: pg | E117: pix | J117: estacionamentos
B118: 28 | C118: 0 | E118: nubank card
A120: boleto pessoal | C120: =('Resumo 2023'!C68)*0.3-(250) -> 2899.115
A121: total | C121: =SUM(C2:C117) -> 10367.06 | D121: =(9167.28)-C121-C120 -> -4098.895
M149: bra

Sheet mai25
A1: ma | B1: dia | C1: valor | D1: situacao | E1: forma de pagamento | F1: beneficiado | G1: outcome | H1: subclassificacao | I1: centro de custo | J1: categoria | L1: tipo de despesas | M1: tag
A2: escolar Arthur | B2: 5 | C2: 789 | D2: pg | E2: boleto | F2: Arthur | G2: bradesco conta | H2: despesas pessoais | I2: despesas essenciais | J2: escola/faculdade | L2: fixa
A3: Faculdade Aline | B3: 5 | C3: 685 | D3: pg | E3: boleto | F3: Aline | G3: bradesco conta | H3: despesas pessoais | I3: despesas essenciais | J3: escola/faculdade | L3: fixa
A4: Dentista Arthur | B4: 5 | C4: 140 | D4: open | E4: Bradesco cartoes | F4: Arthur | G4: bradesco conta | H4: despesas pessoais | I4: despesas essenciais | J4: dentista | L4: fixa
A5: Conta de energia | B5: 14 | C5: 0 | D5: open | E5: boleto | F5: familia | G5: santander conta | H5: habitacao | I5: despesas essenciais | J5: Energia | L5: variavel
A6: internet fixa | B6: 11 | C6: 132.55 | D6: open | E6: boleto | F6: familia | G6: bradesco conta | H6: habitacao | I6: despesas essenciais | J6: Internet | L6: fixa
A7: internet TIM móvel | B7: 20 | C7: 88 | D7: open | E7: debito automatico | F7: Alex | G7: bradesco conta | H7: habitacao | I7: despesas essenciais | J7: Internet movel | L7: fixa
A8: streaming HBO | B8: 30 | C8: 19.95 | D8: open | E8: nubank card | F8: familia | G8: nubank conta | H8: habitacao | J8: streaming | L8: fixa
A9: Apple Tv | B9: 16 | C9: 0 | D9: closed | E9: nubank card | F9: familia | G9: nubank conta | H9: habitacao | J9: streaming | L9: fixa
A10: streaming amazonPrime | B10: 29 | C10: 0 | D10: open | E10: nubank card | F10: familia | G10: nubank conta | H10: habitacao | J10: streaming | L10: fixa
A11: assinatura mercado livre | B11: 2 | C11: 24.9 | D11: pg | E11: nubank card | F11: familia | G11: nubank conta | H11: habitacao | J11: streaming | L11: fixa
A12: contra contabilidade | B12: 15 | C12: 0 | D12: open | E12: nubank card | F12: Alex | G12: nubank conta | H12: despesas pessoais | J12: contabilidade | L12: fixa
A13: assinatura NETFLIX | B13: 8 | C13: 44.9 | D13: pg | E13: nubank card | F13: familia | G13: nubank conta | H13: habitacao | J13: streaming | L13: fixa
A14: assinatura GamePass | B14: 15 | C14: 0 | D14: open | E14: nubank card | F14: familia | G14: nubank conta | H14: habitacao | J14: streaming | L14: fixa
A15: seguro PIER carro | B15: 27 | C15: 244.12 | D15: open | E15: nubank card | F15: familia | G15: nubank conta | H15: transporte | I15: despesas essenciais | J15: seguro | L15: fixa
A16: curso rocketseatPlus | B16: 2 | C16: 0 | D16: open | E16: nubank card | F16: Alex | G16: nubank conta | H16: educacao | I16: educacao | J16: cursos | L16: fixa | N16: 45992
A17: gympass | B17: 27 | C17: =89.9+139.9 -> 229.8 | D17: open | E17: nubank card | F17: Alex | G17: nubank conta | H17: despesas pessoais | I17: despesas essenciais | J17: academia | L17: fixa
A18: Condominio | B18: 10 | C18: 20 | D18: pg | E18: Pix | F18: familia | G18: nubank conta | H18: habitacao | I18: despesas essenciais | J18: manutenção domiciliar
A19: LGM DISTRIBUIDORA E CO | B19: 0 | C19: 8 | D19: pg | E19: Bradesco cartoes | G19: bradesco conta | H19: habitacao | J19: Padaria
A20: ATACADAO 0202 AS | B20: 0 | C20: 156.63 | D20: pg | E20: Bradesco cartoes | G20: bradesco conta | H20: habitacao | J20: mercado
A21: LGM DISTRIBUIDORA E CO | B21: 0 | C21: 11.4 | D21: pg | E21: Bradesco cartoes | G21: bradesco conta | H21: habitacao | J21: Padaria
A22: ATACADAO 0681 AS | B22: 0 | C22: 250.28 | D22: pg | E22: Bradesco cartoes | G22: bradesco conta | H22: habitacao | J22: mercado
A23: LOJAS AMERICANAS 5228 | B23: 0 | C23: 22.98 | D23: pg | E23: Bradesco cartoes | G23: bradesco conta | H23: habitacao | J23: mercado
A24: CARREFOUR - ALCANTARA | B24: 0 | C24: 61.4 | D24: pg | E24: Bradesco cartoes | G24: bradesco conta | H24: habitacao | J24: mercado | N24: 45324
A25: PADARIA DELICIA DE ITA | B25: 0 | C25: 4 | D25: pg | E25: Bradesco cartoes | G25: bradesco conta | H25: habitacao | J25: Padaria
A26: CONVEM SAO GONCALO RES | B26: 0 | C26: 25.9 | D26: pg | E26: Bradesco cartoes | G26: bradesco conta | J26: outros | N26: 45354
A27: GUANABARA ALCANTARA | B27: 0 | C27: 31.9 | D27: pg | E27: Bradesco cartoes | G27: bradesco conta | H27: habitacao | J27: mercado
A28: filamentos | B28: 0 | C28: 367 | D28: pg | E28: Bradesco cartoes | G28: bradesco conta | J28: projetos
A29: CARREFOUR COM 3/8 | B29: 0 | C29: 328.55 | D29: pg | E29: bradesco cartoes | G29: bradesco conta | J29: reforma casa | N29: 45872
A30: MP*OUROLUXSOLAR 2/12 | B30: 0 | C30: 777.56 | D30: pg | E30: bradesco cartoes | G30: bradesco conta | J30: painel solar | N30: 45993
A31: Tapete higienico Mercado livre | B31: 5 | C31: 51.93 | D31: pg | E31: nubank card | G31: nubank conta | H31: habitacao | J31: Pet
A32: estacionamento | B32: 7 | C32: 5 | D32: pg | E32: Pix | G32: bradesco conta | J32: estacionamentos
A33: recarga Aline | B33: 8 | C33: 30 | D33: pg | E33: Pix | G33: bradesco conta | J33: Internet movel
A34: Poda de arvore(cristiano) | B34: 9 | C34: 400 | D34: pg | E34: Pix | F34: familia | G34: bradesco conta | J34: manutenção domiciliar
A35: telha oberdan | B35: 12 | C35: 75 | D35: pg | E35: Pix | F35: familia | G35: bradesco conta | J35: manutenção domiciliar
A36: PADARIA DELICIA DE ITA | B36: 9 | C36: 4 | D36: pg | E36: bradesco cartoes | G36: bradesco conta | J36: Padaria
A37: o boticario | B37: 9 | C37: 63.08 | D37: pg | E37: bradesco cartoes | G37: bradesco conta | J37: gift
A38: cacula | B38: 10 | C38: 19.99 | D38: pg | E38: bradesco cartoes | G38: bradesco conta | J38: material escolar | M38: ferias
A39: LOJAS AMERICANAS 5228 | B39: 10 | C39: 34.97 | D39: pg | E39: bradesco cartoes | G39: bradesco conta | J39: Lazer
A40: Drogaria tamoio | B40: 10 | C40: 22.35 | D40: pg | E40: bradesco cartoes | G40: bradesco conta | J40: farmacia
A41: Objetiva | B41: 10 | C41: 99.98 | D41: pg | E41: bradesco cartoes | G41: bradesco conta | J41: Vestuario
A42: estacionamento | B42: 10 | C42: 9 | D42: pg | E42: bradesco cartoes | G42: bradesco conta | J42: estacionamentos
A43: auto posto | B43: 2 | C43: 57.46 | D43: pg | E43: bradesco cartoes | G43: bradesco conta | J43: combustivel
A44: katarynedamotta | B44: 2 | C44: 24 | D44: pg | E44: bradesco cartoes | G44: bradesco conta | J44: Feira
A45: grupo gennius brasil p | B45: 2 | C45: 49.54 | D45: pg | E45: bradesco cartoes | G45: bradesco conta | J45: outros
A46: Assai atacadista | B46: 2 | C46: 28.2 | D46: pg | E46: bradesco cartoes | G46: bradesco conta | J46: mercado
A47: veganfit | B47: 3 | C47: 76 | D47: pg | E47: bradesco cartoes | G47: bradesco conta | J47: Lazer
A48: LGM DISTRIBUIDORA E CO | B48: 4 | C48: 3 | D48: pg | E48: bradesco cartoes | G48: bradesco conta | J48: Padaria
A49: chic farma | B49: 5 | C49: 47.91 | D49: pg | E49: bradesco cartoes | G49: bradesco conta | J49: farmacia
A50: drogaria tamoio | B50: 5 | C50: 28.16 | D50: pg | E50: bradesco cartoes | G50: bradesco conta | J50: farmacia
... A54: Personal Aline | B54: 8 | C54: 500 | D54: pg | E54: bradesco cartoes | G54: bradesco conta | J54: academia
A55: Futebol Domingo | B55: 11 | C55: 60 | D55: pg | E55: Pix | J55: Lazer
A56: padaria | B56: 9 | C56: 4 | D56: pg | E56: bradesco cartoes | J56: Padaria
A57: o boticario | B57: 9 | C57: 63.08 | D57: pg | E57: bradesco cartoes | J57: gift
A58: estacionamento | B58: 10 | C58: 9 | D58: pg | E58: bradesco cartoes | J58: estacionamentos
A59: LOJAS AMERICANAS 5228 | B59: 10 | C59: 34.97 | D59: pg | E59: bradesco cartoes | J59: Lazer
A60: Objetiva | B60: 10 | C60: 99.98 | D60: pg | E60: bradesco cartoes | J60: Vestuario
A61: burger king | B61: 10 | C61: 69.8 | D61: pg | E61: bradesco cartoes | J61: Lazer
A62: cacula | B62: 10 | C62: 19.99 | D62: pg | E62: bradesco cartoes | J62: material escolar
A63: drogaria tamoio | B63: 10 | C63: 22.35 | D63: pg | E63: bradesco cartoes | J63: farmacia
A64: drogaria uniao | B64: 11 | C64: 16.99 | D64: pg | E64: bradesco cartoes | J64: farmacia | M64: Férias
A65: leroy merlin | B65: 11 | C65: 8.75 | D65: pg | E65: bradesco cartoes | J65: material escolar | M65: Férias
A66: auto posto | B66: 12 | C66: 64.99 | D66: pg | E66: bradesco cartoes | J66: combustivel | M66: Férias
A67: cassel frutas | B67: 13 | C67: 31.39 | D67: pg | E67: bradesco cartoes | J67: Feira | M67: Férias
A68: katarynedamotta | B68: 15 | C68: 24 | D68: pg | E68: bradesco cartoes | J68: Feira | M68: Férias
A69: Atacadao | B69: 15 | C69: 188.77 | D69: pg | E69: bradesco cartoes | J69: mercado | M69: Férias
A70: leandromayer | B70: 16 | C70: 48 | D70: pg | E70: bradesco cartoes | J70: mercado | M70: Férias
A71: Padaria | B71: 16 | C71: 11.4 | D71: pg | E71: bradesco cartoes | J71: Padaria | M71: Férias
A72: Casa novo alcantara | B72: 16 | C72: 26.1 | D72: pg | E72: bradesco cartoes | J72: Manutenção casa | M72: Férias
A73: carrefour | B73: 17 | C73: 124.37 | D73: pg | E73: bradesco cartoes | J73: mercado | M73: Férias
A74: Atacadao | B74: 18 | C74: 199.45 | D74: pg | E74: bradesco cartoes | J74: mercado | M74: Férias
A75: Posto carrefour | B75: 18 | C75: 50.67 | D75: pg | E75: bradesco cartoes | J75: combustivel | M75: Férias
... A80: rocketseat | B80: 20 | C80: 2077 | D80: pg | E80: Pix | J80: cursos | M80: Férias
A81: Unique ingles | B81: 4 | C81: 380.12 | D81: pg | E81: Pix | J81: cursos
A82: 3d prime | B82: 5 | C82: 367.65 | D82: pg | E82: Pix | J82: projetos
A83: aliexpress | B83: 14 | C83: 523.18 | D83: pg | E83: Pix | J83: projetos
A84: aliexpress | B84: 19 | C84: 122.25 | D84: pg | E84: Pix | J84: projetos
A85: alipay | B85: 15 | C85: 40.92 | D85: pg | E85: Pix | J85: projetos
A86: cartao de memoria | B86: 16 | C86: 33 | D86: pg | E86: Pix | J86: gift
A87: estacionamento | B87: 16 | C87: 5 | D87: pg | E87: Pix | J87: estacionamentos
A88: lanche | B88: 15 | C88: 2.99 | D88: pg | E88: bradesco cartoes | J88: Lazer
A89: ecopay | B89: 12 | C89: 6.2 | D89: pg | E89: bradesco cartoes | J89: Lazer
A90: recarga arthur | B90: 12 | C90: 20 | D90: pg | E90: bradesco cartoes | J90: Internet movel
A91: shoppe | B91: 12 | C91: 433.98 | D91: pg | E91: pix | J91: gift
A92: detran | B92: 14 | C92: 80.38 | D92: pg | E92: pix | J92: manutencao veiculo
... A118: estacionamento | B118: 29 | C118: 5 | D118: pg | E118: pix | J118: estacionamentos
A119: focinheira luna | B119: 28 | C119: 248.56 | E119: nubank card
A121: boleto pessoal | C121: =(5495.73+4139.23)*0.3-(633.9) -> 2256.588
A122: total | C122: =SUM(C2:C118) -> 13314.44 | D122: =(9167.28)-C122-C121 -> -6403.748
M150: bra

Sheet abr25
A1: Descrição | B1: dia | C1: valor | D1: situacao | E1: forma de pagamento | F1: beneficiado | G1: outcome | H1: subclassificacao | I1: centro de custo | J1: categoria | L1: tipo de despesas | M1: tag
A2: escolar Arthur | B2: 5 | C2: 789 | D2: pg | E2: boleto | F2: Arthur | G2: bradesco conta | H2: despesas pessoais | I2: despesas essenciais | J2: escola/faculdade | L2: fixa
A3: Faculdade Aline | B3: 5 | C3: 685 | D3: pg | E3: boleto | F3: Aline | G3: bradesco conta | H3: despesas pessoais | I3: despesas essenciais | J3: escola/faculdade | L3: fixa
A4: Dentista Arthur | B4: 5 | C4: 140 | D4: pg | E4: Bradesco cartoes | F4: Arthur | G4: bradesco conta | H4: despesas pessoais | I4: despesas essenciais | J4: dentista | L4: fixa
A5: Conta de energia | B5: 14 | C5: 600 | D5: pg | E5: boleto | F5: familia | G5: santander conta | H5: habitacao | I5: despesas essenciais | J5: Energia | L5: variavel
A6: internet fixa | B6: 11 | C6: 132.5 | D6: pg | E6: boleto | F6: familia | G6: bradesco conta | H6: habitacao | I6: despesas essenciais | J6: Internet | L6: fixa
A7: internet tim móvel | B7: 20 | C7: 99.9 | D7: pg | E7: debito automatico | F7: Alex | G7: bradesco conta | H7: habitacao | I7: despesas essenciais | J7: Internet movel | L7: fixa
A8: streaming HBO | B8: 30 | C8: 19.95 | D8: open | E8: nubank card | F8: familia | G8: nubank conta | H8: habitacao | J8: streaming | L8: fixa
A9: Apple Tv | B9: 16 | C9: 0 | D9: closed | E9: nubank card | F9: familia | G9: nubank conta | H9: habitacao | J9: streaming | L9: fixa
A10: streaming amazonPrime | B10: 29 | C10: 0 | D10: open | E10: nubank card | F10: familia | G10: nubank conta | H10: habitacao | J10: streaming | L10: fixa
A11: assinatura mercado livre | B11: 2 | C11: 24.9 | D11: open | E11: nubank card | F11: familia | G11: nubank conta | H11: habitacao | J11: streaming | L11: fixa
A12: contra contabilidade | B12: 15 | C12: 0 | D12: open | E12: nubank card | F12: Alex | G12: nubank conta | H12: despesas pessoais | J12: contabilidade | L12: fixa
A13: assinatura NETFLIX | B13: 8 | C13: 44.9 | D13: open | E13: nubank card | F13: familia | G13: nubank conta | H13: habitacao | J13: streaming | L13: fixa
A14: assinatura GamePass | B14: 15 | C14: 0 | D14: open | E14: nubank card | F14: familia | G14: nubank conta | H14: habitacao | J14: streaming | L14: fixa
A15: seguro PIER carro | B15: 27 | C15: 244.12 | D15: open | E15: nubank card | F15: familia | G15: nubank conta | H15: transporte | I15: despesas essenciais | J15: seguro | L15: fixa
A16: curso rocketseatPlus | B16: 2 | C16: 0 | D16: open | E16: nubank card | F16: Alex | G16: nubank conta | H16: educacao | I16: educacao | J16: cursos | L16: fixa
A17: gympass | B17: 27 | C17: =89.9+139.9 -> 229.8 | D17: open | E17: nubank card | F17: Alex | G17: nubank conta | H17: despesas pessoais | I17: despesas essenciais | J17: academia | L17: fixa
A18: Condominio | B18: 10 | C18: 20 | D18: open | E18: Pix | F18: familia | G18: nubank conta | H18: habitacao | I18: despesas essenciais | J18: manutenção domiciliar
A19: Pix Renan | B19: 1 | C19: 58 | D19: open | E19: Pix Bradesco cc | J19: outros
A20: Brownie | B20: 3 | C20: 10 | D20: pg | E20: Pix Bradesco cc | J20: Lazer
A21: Pix Fernando | B21: 3 | C21: 8 | D21: pg | E21: Pix Bradesco cc | J21: estacionamentos
A22: GrupoTudoDeVet | B22: 4 | C22: 103.9 | D22: open | E22: Pix Bradesco cc | J22: Pet
A23: Pix Aline | B23: 7 | C23: 150 | D23: pg | E23: Pix Bradesco cc | J23: pix aline
A24: Recarga | B24: 8 | C24: 30 | D24: pg | E24: pague facil | J24: Internet movel
A25: Pix Aliexpress | B25: 8 | C25: 132.94 | D25: pg | E25: Pix Bradesco cc | J25: gift
A26: Pix Aliexpress | B26: 8 | C26: 327.03 | D26: pg | E26: Pix Bradesco cc | J26: gift
A27: Pix Hebert | B27: 11 | C27: 10 | D27: pg | E27: Pix Bradesco cc | J27: Lazer
A28: Pix AnaPaula | B28: 14 | C28: 8 | D28: pg | E28: Pix Bradesco cc | J28: estacionamentos
A29: Top Arena | B29: 14 | C29: 3 | D29: pg | E29: Pix Bradesco cc | J29: Lazer
A30: Box Athena | B30: 15 | C30: 21 | D30: pg | E30: Pix Bradesco cc | J30: Lazer
... A37: Pix cueca | B37: 28 | C37: 90 | D37: pg | E37: Pix Bradesco cc | J37: Vestuario
A38: Philippe | B38: 29 | C38: -730 | D38: pg | E38: Pix Bradesco cc | J38: Pet | M38: ferias
A39: CARREFOUR COM 3/8 | B39: 0 | C39: 328.55 | D39: pg | E39: bradesco cartoes | J39: gift | N39: 45872
A40: DECATHLON 2/2 | B40: 0 | C40: 149.97 | D40: pg | E40: bradesco cartoes | J40: Vestuario | N40: 45690
A41: MP*OUROLUXSOLAR 2/12 | B41: 0 | C41: 777.56 | D41: pg | E41: bradesco cartoes | J41: painel solar | N41: 45993
A42: AUTO POSTO T | B42: 0 | C42: 53.75 | D42: pg | E42: bradesco cartoes | J42: combustivel
A43: BURGER KING | B43: 0 | C43: 65.8 | D43: pg | E43: bradesco cartoes | J43: Lazer
A44: ASSAI ATACADISTA LJ35 | B44: 0 | C44: 115.28 | D44: pg | E44: bradesco cartoes | J44: mercado
A45: LEANDRO MAYER ALTAFINI 81 | B45: 0 | C45: 60 | D45: pg | E45: bradesco cartoes | J45: outros
A46: AUTO POSTO T | B46: 24 | C46: 49.68 | D46: pg | E46: bradesco cartoes | J46: combustivel
A47: SACOLAO DO BARATEIRO | B47: 24 | C47: 27.8 | D47: pg | E47: bradesco cartoes | J47: Feira
A48: HORTIFRUTI MARQUES DE | B48: 23 | C48: 26.98 | D48: pg | E48: bradesco cartoes | J48: Feira
A49: HORTIFRUTI MARQUES DE | B49: 23 | C49: 37.68 | D49: pg | E49: bradesco cartoes | J49: Feira
A50: ATACADAO 0681 AS | B50: 23 | C50: 50.37 | D50: pg | E50: bradesco cartoes | J50: mercado
A51: PETZ CARREFOUR MANILHA | B51: 23 | C51: 26.37 | D51: pg | E51: bradesco cartoes | J51: Pet
A52: LGM DISTRIBUIDORA E CO | B52: 22 | C52: 12.4 | D52: pg | E52: bradesco cartoes | J52: Padaria
A53: SUPERMERCADO GUANABARA | B53: 19 | C53: 251.72 | D53: pg | E53: bradesco cartoes | J53: mercado
... A63: PADARIA DELICIA DE ITA | B63: 15 | C63: 4 | D63: pg | E63: bradesco cartoes | J63: Padaria
A64: SACOLAO DO BARATEIRO | B64: 15 | C64: 8.96 | D64: pg | E64: bradesco cartoes | J64: Feira | M64: Férias
A65: CP *AMIGAO 26 SH S GON | B65: 13 | C65: 68.95 | D65: pg | E65: bradesco cartoes | J65: utilizades domesticas | L65: 45323 | M65: Férias
A66: CASSEL FRUTAS | B66: 12 | C66: 23.11 | D66: pg | E66: bradesco cartoes | J66: Feira | M66: Férias
A67: ASSAI ATACADISTA LJ35 | B67: 12 | C67: 171.78 | D67: pg | E67: bradesco cartoes | J67: mercado | M67: Férias
A68: CASAS PEDRO | B68: 12 | C68: 61.67 | D68: pg | E68: bradesco cartoes | J68: mercado | M68: Férias
A69: MATCON MAT CONSTRUCAO | B69: 12 | C69: 109 | D69: pg | E69: nubank card | J69: Manutenção casa | M69: Férias
A70: AUTO POSTO T | B70: 12 | C70: 60.33 | D70: pg | E70: bradesco cartoes | J70: combustivel | M70: Férias
A71: KataryneDaMotta | B71: 12 | C71: 24 | D71: pg | E71: bradesco cartoes | J71: outros | M71: Férias
A72: LGM DISTRIBUIDORA E CO | B72: 12 | C72: 7 | D72: pg | E72: bradesco cartoes | H72: educacao | I72: educacao | J72: Padaria | K72: 44959 | M72: Férias
A73: SACOLAO DO BARATEIRO | B73: 10 | C73: 14.6 | D73: pg | E73: bradesco cartoes | J73: Feira | M73: Férias
A74: LEANDRO MAYER ALTAFINI 81 | B74: 10 | C74: 42 | D74: pg | E74: bradesco cartoes | J74: outros | M74: Férias
A75: PURO GAS | B75: 9 | C75: 40 | D75: pg | E75: bradesco cartoes | J75: combustivel | M75: Férias
A76: PADARIA DELICIA DE ITA | B76: 9 | C76: 3 | D76: pg | E76: bradesco cartoes | J76: Padaria | M76: Férias
A77: BURGER KING | B77: 8 | C77: 65.8 | D77: pg | E77: bradesco cartoes | J77: Lazer | M77: Férias
A78: LGM DISTRIBUIDORA E CO | B78: 7 | C78: 4 | D78: pg | E78: bradesco cartoes | J78: Padaria | M78: Férias
A79: PETZ DIGITAL | B79: 6 | C79: 461.53 | D79: pg | E79: bradesco cartoes | J79: Pet
A80: FARMACIA APOLO X | B80: 5 | C80: 84.87 | D80: pg | E80: bradesco cartoes | J80: farmacia
A81: DoceEnergia | B81: 5 | C81: 9.5 | D81: pg | E81: bradesco cartoes | J81: Lazer
A82: BELLA FLOR PANIFICACAO | B82: 4 | C82: 6.83 | D82: pg | E82: bradesco cartoes | J82: Padaria
A83: DROGARIA FARMELHOR | B83: 4 | C83: 40.49 | D83: pg | E83: bradesco cartoes | J83: farmacia
A84: DROGARIAS PACHECO | B84: 4 | C84: 45.98 | D84: pg | E84: bradesco cartoes | J84: farmacia
A85: LOJAS AMERICANAS 5228 | B85: 4 | C85: 20.98 | D85: pg | E85: bradesco cartoes | J85: Lazer
A86: LEANDRO MAYER ALTAFINI 81 | B86: 3 | C86: 37 | D86: pg | E86: bradesco cartoes | J86: outros
A87: POSTO VIP CANECO NOVEN | B87: 1 | C87: 50 | D87: pg | E87: bradesco cartoes | J87: combustivel
A88: AUTO POSTO T | B88: 1 | C88: 57.42 | D88: pg | E88: bradesco cartoes | J88: combustivel
A89: NOVA FRUTI | B89: 1 | C89: 34.31 | D89: pg | E89: bradesco cartoes | J89: Feira
A90: ATACADAO 0202 AS | B90: 0 | C90: 93.24 | D90: pg | E90: bradesco cartoes | J90: mercado
... A104: Pix ProjetoPainelSolar | B104: 28 | C104: 5669.2 | D104: pg | E104: Pix Santander | J104: painel solar
A106: boleto pessoal | C106: =9167.28*0.3-(633.9) -> 2116.284
A107: total | C107: =SUM(C2:C100) -> 10512.24 | D107: =(9167.28)-C107-C106 -> -3461.244
M138: bra
B159: =9167.28-B155 -> 7972.4

Sheet jan25
A1: Descricao | B1: dia | C1: valor | D1: situacao | E1: forma de pagamento | F1: beneficiado | G1: outcome | H1: subclassificacao | I1: centro de custo | J1: categoria | L1: tipo de despesas | M1: tag
A2: escolar Arthur | B2: 5 | C2: 895 | D2: pg | E2: boleto | F2: Arthur | G2: bradesco conta | H2: despesas pessoais | I2: despesas essenciais | J2: escola/faculdade | L2: fixa
A3: Faculdade Aline | B3: 5 | C3: 834.94 | D3: pg | E3: boleto | F3: Aline | G3: bradesco conta | H3: despesas pessoais | I3: despesas essenciais | J3: escola/faculdade | L3: fixa
A4: dentista Arthur | B4: 5 | C4: 140 | E4: Pix | F4: Arthur | J4: farmacia | L4: fixa
A5: Faculdade Alex | B5: 26 | C5: 0 | D5: pg | E5: boleto | F5: Alex | G5: santander conta | H5: despesas pessoais | I5: despesas essenciais | J5: escola/faculdade | L5: fixa
A6: Conta de energia | B6: 14 | C6: 600 | D6: pg | E6: boleto | F6: familia | G6: santander conta | H6: habitacao | I6: despesas essenciais | J6: Energia | L6: variavel
A7: internet fixa | B7: 11 | C7: 129 | D7: pg | E7: boleto | F7: familia | G7: bradesco conta | H7: habitacao | I7: despesas essenciais | J7: Internet | L7: fixa
A8: internet oi móvel | B8: 20 | C8: 88 | D8: pg | E8: debito automatico | F8: Alex | G8: bradesco conta | H8: habitacao | I8: despesas essenciais | J8: Internet movel | L8: fixa
A9: streaming HBO | B9: 30 | C9: 19.95 | D9: open | E9: nubank card | F9: familia | G9: nubank conta | H9: habitacao | J9: streaming | L9: fixa
A10: Apple Tv | B10: 16 | C10: 0 | D10: closed | E10: nubank card | F10: familia | G10: nubank conta | H10: habitacao | J10: streaming | L10: fixa
A11: streaming amazonPrime | B11: 29 | C11: 0 | D11: open | E11: nubank card | F11: familia | G11: nubank conta | H11: habitacao | J11: streaming | L11: fixa
A12: assinatura mercado livre | B12: 2 | C12: 27.99 | D12: open | E12: nubank card | F12: familia | G12: nubank conta | H12: habitacao | J12: streaming | L12: fixa
A13: contra contabilidade | B13: 15 | C13: 0 | D13: open | E13: nubank card | F13: Alex | G13: nubank conta | H13: despesas pessoais | J13: contabilidade | L13: fixa
A14: assinatura NETFLIX | B14: 8 | C14: 44.9 | D14: open | E14: nubank card | F14: familia | G14: nubank conta | H14: habitacao | J14: streaming | L14: fixa
A15: assinatura GamePass | B15: 15 | C15: 0 | D15: open | E15: nubank card | F15: familia | G15: nubank conta | H15: habitacao | J15: streaming | L15: fixa
A16: seguro PIER carro | B16: 27 | C16: 244.12 | D16: open | E16: nubank card | F16: familia | G16: nubank conta | H16: transporte | I16: despesas essenciais | J16: seguro | L16: fixa
A17: curso rocketseatPlus | B17: 2 | C17: 0 | D17: open | E17: nubank card | F17: Alex | G17: nubank conta | H17: educacao | I17: educacao | J17: cursos | L17: fixa
A18: gympass | B18: 27 | C18: =85.9+129.9 -> 215.8 | D18: open | E18: nubank card | F18: Alex | G18: nubank conta | H18: despesas pessoais | I18: despesas essenciais | J18: academia | L18: fixa
A19: recarga arthur | B19: 0 | C19: 0 | D19: open | E19: Pix | J19: Internet movel
A20: recarga Aline | B20: 0 | C20: 0 | D20: open | E20: Pix | J20: Internet movel
A21: Futebol Alex | B21: 0 | C21: 60 | D21: open | E21: Pix | J21: Lazer
A22: Combustivel | B22: 0 | C22: 0 | D22: open | E22: Bradesco cartoes | J22: combustivel
A23: Personal | B23: 8 | C23: 500 | D23: pg | E23: Pix | J23: academia
A24: Amazon | B24: 5 | C24: 0 | D24: pg | E24: nubank card | J24: gift | N24: 45324
A25: petz | B25: 8 | C25: 0 | D25: pg | E25: nubank card | J25: Pet
A26: Pag*Steam | B26: 0 | C26: 0 | D26: pg | E26: Bradesco cartoes | J26: gift | N26: 45354
A27: restaurante da familia | B27: 0 | C27: 0 | D27: pg | E27: Bradesco cartoes | J27: mercado
A28: sams club | B28: 0 | C28: 0 | D28: pg | E28: Bradesco cartoes | J28: mercado
A29: lgmdistribuidora | B29: 0 | C29: 0 | D29: pg | E29: bradesco cartoes | J29: Padaria
A30: grupoIdeal | B30: 0 | C30: 0 | D30: pg | E30: bradesco cartoes | J30: outros
A31: Epar | B31: 0 | C31: 0 | D31: pg | E31: bradesco cartoes | J31: outros
A32: Burger king | B32: 0 | C32: 0 | D32: pg | E32: bradesco cartoes | J32: Lazer
A33: padaria | B33: 2 | C33: 0 | D33: pg | E33: bradesco cartoes | J33: Padaria
A34: PostoVipCanecoNoven | B34: 2 | C34: 0 | D34: pg | E34: bradesco cartoes | J34: combustivel
A35: PuroGas | B35: 2 | C35: 0 | D35: pg | E35: bradesco cartoes | J35: combustivel
A36: Denair | B36: 3 | C36: 0 | D36: pg | E36: bradesco cartoes | J36: manutencao veicular
A37: pank motos | B37: 3 | C37: 0 | D37: pg | E37: bradesco cartoes | J37: manutencao veicular
A38: Padaria | B38: 4 | C38: 0 | D38: pg | E38: bradesco cartoes | J38: Padaria | M38: ferias
A39: sacolao do barateiro | B39: 4 | C39: 0 | D39: pg | E39: bradesco cartoes | J39: Feira
A40: StarLink | B40: 4 | C40: 0 | D40: pg | E40: bradesco cartoes | J40: Internet
A41: Iof S/Trans inter Reais | B41: 4 | C41: 0 | D41: pg | E41: bradesco cartoes | J41: Internet movel
A42: Gabriela Marinho | B42: 5 | C42: 0 | D42: pg | E42: bradesco cartoes | J42: Pet
A43: restaurante da familia | B43: 5 | C43: 0 | D43: pg | E43: bradesco cartoes | J43: mercado
A44: Burger king | B44: 5 | C44: 0 | D44: pg | E44: bradesco cartoes | J44: Lazer
A45: casa pedro | B45: 5 | C45: 0 | D45: pg | E45: bradesco cartoes | J45: mercado
A46: Drogaria tamoio | B46: 5 | C46: 0 | D46: pg | E46: bradesco cartoes | J46: farmacia
A47: Drogaria Pacheco | B47: 5 | C47: 0 | D47: pg | E47: bradesco cartoes | J47: farmacia
A48: Nosso Park Estacionamento | B48: 5 | C48: 0 | D48: pg | E48: bradesco cartoes | J48: estacionamentos
A49: Puro gas | B49: 5 | C49: 0 | D49: pg | E49: bradesco cartoes | J49: combustivel
A50: finpet | B50: 5 | C50: 0 | D50: pg | E50: bradesco cartoes | J50: Pet
... A63: cacula sao goncalo | B63: 15 | C63: 0 | D63: pg | E63: bradesco cartoes | J63: manutenção domiciliar
A64: Burger king | B64: 15 | C64: 0 | D64: pg | E64: bradesco cartoes | J64: Lazer | M64: Férias
A65: kik | B65: 15 | C65: 0 | D65: pg | E65: bradesco cartoes | J65: Vestuario | L65: 45323 | M65: Férias
A66: Top Arena | B66: 16 | C66: 0 | D66: pg | E66: bradesco cartoes | J66: Lazer | M66: Férias
A67: padaria | B67: 16 | C67: 0 | D67: pg | E67: bradesco cartoes | J67: Padaria | M67: Férias
A68: hortfruit | B68: 16 | C68: 0 | D68: pg | E68: bradesco cartoes | J68: Feira | M68: Férias
A69: fabrica de bolo vo az | B69: 17 | C69: 0 | D69: pg | E69: nubank card | J69: Lazer | M69: Férias
A70: carrefour manilha | B70: 17 | C70: 0 | D70: pg | E70: bradesco cartoes | J70: mercado | M70: Férias
A71: Lojas Americanas | B71: 17 | C71: 0 | D71: pg | E71: bradesco cartoes | J71: mercado | M71: Férias
A72: Outback | B72: 17 | C72: 0 | D72: pg | E72: bradesco cartoes | H72: educacao | I72: educacao | J72: Lazer | K72: 44959 | M72: Férias
A73: Carrefour Cal 212 | B73: 17 | C73: 0 | D73: pg | E73: bradesco cartoes | J73: mercado | M73: Férias
A74: Grupo Ideal | B74: 18 | C74: 0 | D74: pg | E74: bradesco cartoes | J74: combustivel | M74: Férias
A75: hortfruit | B75: 19 | C75: 0 | D75: pg | E75: bradesco cartoes | J75: Feira | M75: Férias
A76: Assai atacadista | B76: 20 | C76: 0 | D76: pg | E76: bradesco cartoes | J76: mercado | M76: Férias
A77: Grupo genius brasil p | B77: 21 | C77: 0 | D77: pg | E77: bradesco cartoes | J77: combustivel | M77: Férias
A78: Drogaria tamoio | B78: 23 | C78: 0 | D78: pg | E78: bradesco cartoes | J78: Padaria | M78: Férias
A79: Carrefour posto | B79: 23 | C79: 0 | D79: pg | E79: bradesco cartoes | J79: combustivel | M79: Férias
A80: Alexandre | B80: 23 | C80: 0 | D80: pg | E80: bradesco cartoes | J80: Lazer | M80: Férias
A81: edinilzaborges | B81: 23 | C81: 0 | D81: pg | E81: bradesco cartoes | J81: Lazer
A82: ton lehmonada | B82: 23 | C82: 0 | D82: pg | E82: bradesco cartoes | J82: Lazer
A83: ton lehmonada | B83: 23 | C83: 0 | D83: pg | E83: bradesco cartoes | J83: Lazer
A84: edinilzaborges | B84: 23 | C84: 0 | D84: pg | E84: bradesco cartoes | J84: Lazer
A85: Assai atacadista | B85: 23 | C85: 0 | D85: pg | E85: bradesco cartoes | J85: mercado
A86: padaria | B86: 24 | C86: 0 | D86: pg | E86: bradesco cartoes | J86: Padaria
A87: Puro gas | B87: 25 | C87: 0 | D87: pg | E87: bradesco cartoes | J87: Lazer
A88: Alypay Brasil | B88: 26 | C88: 0 | D88: pg | E88: bradesco cartoes | J88: Lazer
A89: Aliexpress | B89: 26 | C89: 0 | D89: pg | E89: bradesco cartoes | J89: estacionamentos
A90: hortfruit | B90: 0 | C90: 0 | D90: pg | E90: bradesco cartoes | J90: Feira
A91: corte arthur | B91: 0 | C91: 0 | D91: pg | E91: pix | J91: mercado
A92: jogo steam | B92: 0 | C92: 0 | D92: pg | E92: pix | J92: mercado
... A102: objetiva | B102: 0 | C102: 0 | D102: pg | E102: bradesco cartoes | J102: Vestuario
A104: boleto pessoal | C104: =9167.28*0.3-(633.9)-C40 -> 2116.284
A105: total | C105: =SUM(C2:C102) -> 3799.7 | D105: =(9167.28)-C105-C104 -> 3251.296
M132: bra
B154: =9167.28-B150 -> 9167.28

Sheet fev25
A1: Descricao | B1: dia | C1: valor | D1: situacao | E1: forma de pagamento | F1: beneficiado | G1: outcome | H1: subclassificacao | I1: centro de custo | J1: categoria | L1: tipo de despesas | M1: tag
A2: escolar Arthur | B2: 5 | C2: 789 | D2: pg | E2: boleto | F2: Arthur | G2: bradesco conta | H2: despesas pessoais | I2: despesas essenciais | J2: escola/faculdade | L2: fixa
A3: Faculdade Aline | B3: 5 | C3: 556.63 | D3: pg | E3: boleto | F3: Aline | G3: bradesco conta | H3: despesas pessoais | I3: despesas essenciais | J3: escola/faculdade | L3: fixa
A4: Dentista Arthur | B4: 5 | C4: 140 | D4: pg | E4: Bradesco cartoes | F4: Arthur | G4: bradesco conta | H4: despesas pessoais | I4: despesas essenciais | J4: dentista | L4: fixa
A5: Conta de energia | B5: 14 | C5: 626.13 | D5: pg | E5: boleto | F5: familia | G5: santander conta | H5: habitacao | I5: despesas essenciais | J5: Energia | L5: variavel
A6: internet fixa | B6: 11 | C6: 132.72 | D6: pg | E6: boleto | F6: familia | G6: bradesco conta | H6: habitacao | I6: despesas essenciais | J6: Internet | L6: fixa
A7: internet TIM móvel | B7: 26 | C7: 101.1 | D7: pg | E7: debito automatico | F7: Alex | G7: bradesco conta | H7: habitacao | I7: despesas essenciais | J7: Internet movel | L7: fixa
A8: streaming HBO | B8: 30 | C8: 19.95 | D8: open | E8: nubank card | F8: familia | G8: nubank conta | H8: habitacao | J8: streaming | L8: fixa
A9: Apple Tv | B9: 16 | C9: 0 | D9: closed | E9: nubank card | F9: familia | G9: nubank conta | H9: habitacao | J9: streaming | L9: fixa
A10: streaming amazonPrime | B10: 29 | C10: 0 | D10: open | E10: nubank card | F10: familia | G10: nubank conta | H10: habitacao | J10: streaming | L10: fixa
A11: assinatura mercado livre | B11: 2 | C11: 27.99 | D11: open | E11: nubank card | F11: familia | G11: nubank conta | H11: habitacao | J11: streaming | L11: fixa
A12: contra contabilidade | B12: 15 | C12: 0 | D12: open | E12: nubank card | F12: Alex | G12: nubank conta | H12: despesas pessoais | J12: contabilidade | L12: fixa
A13: assinatura NETFLIX | B13: 8 | C13: 44.9 | D13: open | E13: nubank card | F13: familia | G13: nubank conta | H13: habitacao | J13: streaming | L13: fixa
A14: assinatura GamePass | B14: 15 | C14: 0 | D14: open | E14: nubank card | F14: familia | G14: nubank conta | H14: habitacao | J14: streaming | L14: fixa
A15: seguro PIER carro | B15: 27 | C15: 244.12 | D15: open | E15: nubank card | F15: familia | G15: nubank conta | H15: transporte | I15: despesas essenciais | J15: seguro | L15: fixa
A16: curso rocketseatPlus | B16: 2 | C16: 0 | D16: open | E16: nubank card | F16: Alex | G16: nubank conta | H16: educacao | I16: educacao | J16: cursos | L16: fixa
A17: gympass | B17: 27 | C17: =85.9+129.9 -> 215.8 | D17: open | E17: nubank card | F17: Alex | G17: nubank conta | H17: despesas pessoais | I17: despesas essenciais | J17: academia | L17: fixa
A18: Condominio | B18: 10 | C18: 20 | D18: open | E18: Pix | F18: familia | G18: nubank conta | H18: habitacao | I18: despesas essenciais | J18: manutenção domiciliar
A19: Recarga | B19: 3 | C19: 30 | D19: pg | E19: Bradesco cc | J19: Internet movel
A20: transferencia p Alex 01/02 | B20: 3 | C20: 50 | D20: pg | E20: Bradesco cc | J20: Internet movel
A21: Sefaz 03/03 | B21: 3 | C21: 208.46 | D21: pg | E21: Bradesco cc | J21: manutenção domiciliar
A22: Shopee | B22: 4 | C22: 243 | D22: pg | E22: Pix Bradesco cc | J22: gift
A23: Parafusos | B23: 5 | C23: 20 | D23: pg | E23: Bradesco debito | J23: projetos
A24: instalacao Ar condicionado | B24: 5 | C24: 434 | D24: pg | E24: Pix Bradesco cc | J24: manutenção domiciliar | N24: 45324
A25: Grupo Ideal | B25: 6 | C25: 10 | D25: pg | E25: Bradesco debito | J25: Feira
A26: Shopee | B26: 7 | C26: 89.8 | D26: pg | E26: Bradesco debito | J26: gift | N26: 45354
A27: Guanabara Alcantara | B27: 10 | C27: 4.5 | D27: pg | E27: Bradesco Visa Electron | J27: mercado
A28: transferencia p Aline | B28: 13 | C28: 100 | D28: pg | E28: Pix Bradesco cc | J28: pix aline
A29: Enel | B29: 14 | C29: 534.01 | D29: pg | E29: Pix Bradesco cc | J29: Energia
A30: DoceEnergia | B30: 17 | C30: 7 | D30: pg | E30: Bradesco Visa Electron | J30: Lazer
A31: Cia do Doce | B31: 17 | C31: 40 | D31: pg | E31: Pix Bradesco cc | J31: mercado
A32: Estacionamento | B32: 17 | C32: 5 | D32: pg | E32: Pix Bradesco cc | J32: estacionamentos
A33: Purogas Mutua GNV | B33: 17 | C33: 61.55 | D33: pg | E33: Pix Bradesco cc | J33: combustivel
A34: Shopee | B34: 17 | C34: 26.9 | D34: pg | E34: Pix Bradesco cc | J34: gift
A35: Shopee | B35: 17 | C35: 89.99 | D35: pg | E35: Pix Bradesco cc | J35: gift
A36: Shopee | B36: 18 | C36: 42.9 | D36: pg | E36: Pix Bradesco cc | J36: gift | M36: ferias
A37: Estacionamento | B37: 24 | C37: 5 | D37: pg | E37: Bradesco Visa Electron | J37: estacionamentos
A38: Philippe pix | B38: 28 | C38: -730 | D38: pg | E38: Pix Bradesco cc | J38: Pet
A39: Aledson Pix | B39: 28 | C39: 28 | D39: pg | E39: Pix Bradesco cc | J39: outros
A40: Purogas | B40: 22 | C40: 81.36 | D40: pg | E40: bradesco cartoes | J40: combustivel
A41: HORTIFRUTI MARQUES DE | B41: 22 | C41: 46.77 | D41: pg | E41: bradesco cartoes | J41: Feira
A42: PETZ CARREFOUR MANILHA | B42: 22 | C42: 514.95 | D42: pg | E42: bradesco cartoes | J42: Pet
A43: CHINA IN BOX | B43: 22 | C43: 72.62 | D43: pg | E43: bradesco cartoes | J43: Lazer
A44: LGM DISTRIBUIDORA E CO | B44: 21 | C44: 9 | D44: pg | E44: bradesco cartoes | J44: Padaria
A45: ASSAI ATACADISTA LJ35 | B45: 20 | C45: 193.01 | D45: pg | E45: bradesco cartoes | J45: mercado
A46: CASAS PEDRO | B46: 20 | C46: 48.95 | D46: pg | E46: bradesco cartoes | J46: mercado
A47: LGM DISTRIBUIDORA E CO | B47: 19 | C47: 4 | D47: pg | E47: bradesco cartoes | J47: Padaria
A48: SUPERMERCADO GUANABARA | B48: 18 | C48: 117.27 | D48: pg | E48: bradesco cartoes | J48: mercado
... A61: PADARIA DELICIA DE ITA | B61: 12 | C61: 4 | D61: pg | E61: bradesco cartoes | J61: Padaria
A62: POSTO DE GASOLINA HALL | B62: 11 | C62: 53.15 | D62: pg | E62: bradesco cartoes | J62: combustivel | M62: Férias
A63: RamonAdrianoPrado | B63: 11 | C63: 12 | D63: pg | E63: bradesco cartoes | J63: outros | L63: 45323 | M63: Férias
A64: PADARIA DELICIA DE ITA | B64: 10 | C64: 4 | D64: pg | E64: bradesco cartoes | J64: Padaria | M64: Férias
A65: MUNDO DA REFRIGERACAO | B65: 8 | C65: 89.9 | D65: pg | E65: bradesco cartoes | J65: manutenção domiciliar | M65: Férias
A66: J PEDRO DESCARTAVEIS | B66: 8 | C66: 33.5 | D66: pg | E66: bradesco cartoes | J66: utilizades domesticas | M66: Férias
A67: CARREFOUR COM 01/08 | B67: 7 | C67: 328.57 | D67: pg | E67: bradesco cartoes | J67: reforma casa | M67: Férias
A68: EdineyGuimaraesDe | B68: 7 | C68: 32 | D68: pg | E68: bradesco cartoes | J68: Feira | M68: Férias
A69: BURGER KING | B69: 6 | C69: 63.8 | D69: pg | E69: bradesco cartoes | J69: Lazer | M69: Férias
A70: POSTO DE GASOLINA HALL | B70: 6 | C70: 56.07 | D70: pg | E70: bradesco cartoes | H70: educacao | I70: educacao | J70: combustivel | K70: 44959 | M70: Férias
A71: LANCHONETE PATIO DAS D | B71: 6 | C71: 24.99 | D71: pg | E71: bradesco cartoes | J71: Lazer | M71: Férias
A72: BOLERIA DAVO ED. | B72: 6 | C72: 41 | D72: pg | E72: bradesco cartoes | J72: gift | M72: Férias
A73: PADARIA DELICIA DE ITA | B73: 5 | C73: 4 | D73: pg | E73: bradesco cartoes | J73: Padaria | M73: Férias
A74: EdineyGuimaraesDe | B74: 4 | C74: 32 | D74: pg | E74: bradesco cartoes | J74: Feira | M74: Férias
A75: POSTO CARREFOUR - MANI | B75: 2 | C75: 33.46 | D75: pg | E75: bradesco cartoes | J75: combustivel | M75: Férias
A76: ATACADAO 0681 AS | B76: 2 | C76: 93.76 | D76: pg | E76: bradesco cartoes | J76: mercado | M76: Férias
A77: PETZ *PETZ | B77: 2 | C77: 877.35 | D77: pg | E77: bradesco cartoes | J77: Pet | M77: Férias
A78: CarrefourManilha | B78: 2 | C78: 18.99 | D78: pg | E78: bradesco cartoes | J78: mercado | M78: Férias
A79: PES PATAS | B79: 1 | C79: 34.9 | D79: pg | E79: bradesco cartoes | J79: Pet
A80: CARREFOUR - ALCANTARA | B80: 1 | C80: 107.45 | D80: pg | E80: bradesco cartoes | J80: mercado
A81: CASSEL FRUTAS | B81: 1 | C81: 7.11 | D81: pg | E81: bradesco cartoes | J81: Feira
A82: DROGARIAS PACHECO | B82: 1 | C82: 25.33 | D82: pg | E82: bradesco cartoes | J82: farmacia
A83: LOJAS AMERICANAS 5228 | B83: 1 | C83: 30.97 | D83: pg | E83: bradesco cartoes | J83: Lazer
A84: D RODRIGUES | B84: 1 | C84: 7 | D84: pg | E84: bradesco cartoes | J84: outros
A85: ATACADAO 0202 AS | B85: 0 | C85: 190.31 | D85: pg | E85: bradesco cartoes | J85: mercado
A86: CANTINA ALF BACKER | B86: 0 | C86: 1638 | D86: pg | E86: bradesco cartoes | J86: material escolar
A87: ASSAI ATACADISTA LJ35 | B87: 0 | C87: 11.06 | D87: pg | E87: bradesco cartoes | J87: mercado
A88: EletroMouraLtda | B88: 0 | C88: 27 | D88: pg | E88: bradesco cartoes | J88: manutenção domiciliar
A89: BURGER KING | B89: 0 | C89: 63.8 | D89: pg | E89: bradesco cartoes | J89: Lazer
A90: ASSAI ATACADISTA LJ26 | B90: 0 | C90: 207.43 | D90: pg | E90: bradesco cartoes | J90: mercado
... A103: Pix Aline | B103: 10 | C103: 500 | D103: pg | E103: Pix Santander | J103: pix aline
A105: boleto pessoal | C105: =9167.28*0.3-(633.9) -> 2116.284
A106: total | C106: =SUM(C2:C100) -> 10857.06 | D106: =(9167.28)-C106-C105 -> -3806.064
M137: bra
B159: =9167.28-B155 -> 7821.65

Sheet mar25
A1: Descricao | B1: dia | C1: valor | D1: situacao | E1: forma de pagamento | F1: beneficiado | G1: outcome | H1: subclassificacao | I1: centro de custo | J1: categoria | L1: tipo de despesas | M1: tag
A2: escolar Arthur | B2: 5 | C2: 789 | D2: pg | E2: boleto | F2: Arthur | G2: bradesco conta | H2: despesas pessoais | I2: despesas essenciais | J2: escola/faculdade | L2: fixa
A3: Faculdade Aline | B3: 5 | C3: 695.78 | D3: pg | E3: boleto | F3: Aline | G3: bradesco conta | H3: despesas pessoais | I3: despesas essenciais | J3: escola/faculdade | L3: fixa
A4: Dentista Arthur | B4: 5 | C4: 140 | D4: pg | E4: Bradesco cartoes | F4: Arthur | G4: bradesco conta | H4: despesas pessoais | I4: despesas essenciais | J4: dentista | L4: fixa
A5: Conta de energia | B5: 14 | C5: 0 | D5: pg | E5: boleto | F5: familia | G5: santander conta | H5: habitacao | I5: despesas essenciais | J5: Energia | L5: variavel
A6: internet fixa | B6: 11 | C6: 132.55 | D6: pg | E6: boleto | F6: familia | G6: bradesco conta | H6: habitacao | I6: despesas essenciais | J6: Internet | L6: fixa
A7: internet TIM móvel | B7: 25 | C7: 99.9 | D7: pg | E7: debito automatico | F7: Alex | G7: bradesco conta | H7: habitacao | I7: despesas essenciais | J7: Internet movel | L7: fixa
A8: streaming HBO | B8: 30 | C8: 19.95 | D8: open | E8: nubank card | F8: familia | G8: nubank conta | H8: habitacao | J8: streaming | L8: fixa
A9: Apple Tv | B9: 16 | C9: 0 | D9: closed | E9: nubank card | F9: familia | G9: nubank conta | H9: habitacao | J9: streaming | L9: fixa
A10: streaming amazonPrime | B10: 29 | C10: 0 | D10: open | E10: nubank card | F10: familia | G10: nubank conta | H10: habitacao | J10: streaming | L10: fixa
A11: assinatura mercado livre | B11: 2 | C11: 27.99 | D11: open | E11: nubank card | F11: familia | G11: nubank conta | H11: habitacao | J11: streaming | L11: fixa
A12: contra contabilidade | B12: 15 | C12: 0 | D12: open | E12: nubank card | F12: Alex | G12: nubank conta | H12: despesas pessoais | J12: contabilidade | L12: fixa
A13: assinatura NETFLIX | B13: 8 | C13: 44.9 | D13: open | E13: nubank card | F13: familia | G13: nubank conta | H13: habitacao | J13: streaming | L13: fixa
A14: assinatura GamePass | B14: 15 | C14: 0 | D14: open | E14: nubank card | F14: familia | G14: nubank conta | H14: habitacao | J14: streaming | L14: fixa
A15: seguro PIER carro | B15: 27 | C15: 244.12 | D15: open | E15: nubank card | F15: familia | G15: nubank conta | H15: transporte | I15: despesas essenciais | J15: seguro | L15: fixa
A16: curso rocketseatPlus | B16: 2 | C16: 0 | D16: open | E16: nubank card | F16: Alex | G16: nubank conta | H16: educacao | I16: educacao | J16: cursos | L16: fixa
A17: gympass | B17: 27 | C17: =85.9+129.9 -> 215.8 | D17: open | E17: nubank card | F17: Alex | G17: nubank conta | H17: despesas pessoais | I17: despesas essenciais | J17: academia | L17: fixa
A18: Condominio | B18: 10 | C18: 20 | D18: open | E18: Pix | F18: familia | G18: nubank conta | H18: habitacao | I18: despesas essenciais | J18: manutenção domiciliar
A19: Recarga | B19: 6 | C19: 30 | D19: pg | E19: Bradesco cc | J19: Internet movel
A20: Pix Aline | B20: 10 | C20: 630 | D20: pg | E20: Pix Bradesco cc | J20: pix aline
A21: Brownie | B21: 10 | C21: 10 | D21: pg | E21: Pix Bradesco cc | J21: Lazer
A22: Latam Gateway | B22: 10 | C22: 200 | D22: pg | E22: Pix Bradesco cc | J22: outros
A23: Casa linda | B23: 11 | C23: 68.5 | D23: pg | E23: Bradesco Visa Electron | J23: Manutenção casa
A24: Bazar agroverde | B24: 11 | C24: 12.9 | D24: pg | E24: Bradesco Visa Electron | J24: Manutenção casa | N24: 45324
A25: Universidadedasco | B25: 12 | C25: 8 | D25: pg | E25: Bradesco Visa Electron | J25: estacionamentos
A26: Sefaz | B26: 13 | C26: 208.46 | D26: pg | E26: Pix Bradesco cc | J26: manutencao veicular | N26: 45354
A27: Doce Energia | B27: 14 | C27: 7 | D27: pg | E27: Bradesco Visa Electron | J27: Lazer
A28: Brownie | B28: 14 | C28: 10 | D28: pg | E28: Pix Bradesco cc | J28: Lazer
A29: TudoDeVet | B29: 18 | C29: 95.4 | D29: pg | E29: Pix Bradesco cc | J29: Pet
A30: Sacolao barateiro | B30: 20 | C30: 6.95 | D30: pg | E30: Bradesco Visa Electron | J30: Feira
A31: ObraTelhadoPainelSolar | B31: 20 | C31: 700 | D31: pg | E31: Pix Bradesco cc | J31: painel solar
A32: ObraTelhadoPainelSolar | B32: 25 | C32: 700 | D32: pg | E32: Pix Bradesco cc | J32: painel solar
A33: Pix Philippe | B33: 31 | C33: -730 | D33: pg | E33: bradesco cartoes | J33: Pet
A34: Aliexpress | B34: 31 | C34: 178.84 | D34: pg | E34: bradesco cartoes | J34: outros
A35: Aliexpress | B35: 31 | C35: 102 | D35: pg | E35: bradesco cartoes | J35: outros
A36: Recarga Arthur | B36: 31 | C36: 20 | D36: pg | E36: bradesco cartoes | J36: Internet movel
A37: PADARIA DELICIA DE ITA | B37: 25 | C37: 4 | D37: pg | E37: bradesco cartoes | J37: Padaria | M37: ferias
A38: MERCADO NOVO RIO | B38: 24 | C38: 39 | D38: pg | E38: bradesco cartoes | J38: mercado
A39: REDE ECONOMIA | B39: 23 | C39: 23.75 | D39: pg | E39: bradesco cartoes | J39: mercado
A40: GLADIADOR PET SHOP | B40: 22 | C40: 133.9 | D40: pg | E40: bradesco cartoes | J40: Pet
A41: CASAS PEDRO | B41: 22 | C41: 36.27 | D41: pg | E41: bradesco cartoes | J41: mercado
A42: HORTIFRUTI MARQUES DE | B42: 22 | C42: 35.06 | D42: pg | E42: bradesco cartoes | J42: Feira
A43: MAGAZINE TORRA TORRA L | B43: 22 | C43: 14.99 | D43: pg | E43: bradesco cartoes | J43: Vestuario
A44: LOJAS AMERICANAS 87 | B44: 22 | C44: 53.44 | D44: pg | E44: bradesco cartoes | J44: gift
A45: PADARIA DELICIA DE ITA | B45: 22 | C45: 4 | D45: pg | E45: bradesco cartoes | J45: Padaria
A46: PES E PATAS COMERCIO D | B46: 20 | C46: 100.2 | D46: pg | E46: bradesco cartoes | J46: Pet
A47: PADARIA DELICIA DE ITA | B47: 20 | C47: 9 | D47: pg | E47: bradesco cartoes | J47: Padaria
A48: ATACADAO 0202 AS | B48: 19 | C48: 207.98 | D48: pg | E48: bradesco cartoes | J48: mercado
A49: POSTO DE GASOLINA HALL | B49: 19 | C49: 52.38 | D49: pg | E49: bradesco cartoes | J49: combustivel
... A61: GrupoIdeal | B61: 11 | C61: 24 | D61: pg | E61: bradesco cartoes | J61: Feira
A62: CASSEL FRUTAS | B62: 10 | C62: 36.56 | D62: pg | E62: bradesco cartoes | J62: Feira | L62: 45323 | M62: Férias
A63: RAIA3421 | B63: 9 | C63: 79.88 | D63: pg | E63: bradesco cartoes | J63: farmacia | M63: Férias
A64: CIA DO DOCE | B64: 8 | C64: 78.5 | D64: pg | E64: bradesco cartoes | J64: mercado | M64: Férias
A65: CIA DO DOCE | B65: 8 | C65: 12.38 | D65: pg | E65: bradesco cartoes | J65: mercado | M65: Férias
A66: BURGER KING | B66: 8 | C66: 68.8 | D66: pg | E66: bradesco cartoes | J66: Lazer | M66: Férias
A67: LGM DISTRIBUIDORA E CO | B67: 8 | C67: 4 | D67: pg | E67: bradesco cartoes | J67: Padaria | M67: Férias
A68: MURALHA | B68: 8 | C68: 10 | D68: pg | E68: bradesco cartoes | J68: outros | M68: Férias
A69: HF STUDIOHAIR | B69: 7 | C69: 40 | D69: pg | E69: bradesco cartoes | H69: educacao | I69: educacao | J69: Cabeleireiro | K69: 44959 | M69: Férias
A70: POSTO VIP CANECO NOVEN | B70: 6 | C70: 40 | D70: pg | E70: bradesco cartoes | J70: combustivel | M70: Férias
A71: PADARIA DELICIA DE ITA | B71: 5 | C71: 4 | D71: pg | E71: bradesco cartoes | J71: Padaria | M71: Férias
A72: LGM DISTRIBUIDORA E CO | B72: 3 | C72: 4 | D72: pg | E72: bradesco cartoes | J72: Padaria | M72: Férias
A73: PES E PATAS COMERCIO D | B73: 2 | C73: 286.9 | D73: pg | E73: bradesco cartoes | J73: Pet | M73: Férias
A74: KAMARO RACOES | B74: 2 | C74: 23.1 | D74: pg | E74: bradesco cartoes | J74: Pet | M74: Férias
A75: MERCADO NOVO RIO | B75: 2 | C75: 23 | D75: pg | E75: bradesco cartoes | J75: mercado | M75: Férias
A76: PET SHOP VOVO ZUZU | B76: 1 | C76: 35 | D76: pg | E76: bradesco cartoes | J76: Pet | M76: Férias
A77: SUPERMERCADO GUANABARA | B77: 1 | C77: 155.39 | D77: pg | E77: bradesco cartoes | J77: mercado | M77: Férias
A78: PADARIA DELICIA DE ITA | B78: 0 | C78: 4 | D78: pg | E78: bradesco cartoes | J78: Padaria
A79: DOCE ENERGIA | B79: 0 | C79: 7 | D79: pg | E79: bradesco cartoes | J79: Lazer
A80: POSTO DE GASOLINA HALL | B80: 0 | C80: 64.86 | D80: pg | E80: bradesco cartoes | J80: combustivel
A81: ATACADAO 0202 AS | B81: 0 | C81: 45.94 | D81: pg | E81: bradesco cartoes | J81: mercado
A82: PURO GAS | B82: 0 | C82: 60 | D82: pg | E82: bradesco cartoes | J82: combustivel
A83: PES E PATAS COMERCIO D | B83: 0 | C83: 44.9 | D83: pg | E83: bradesco cartoes | J83: Pet
A84: CARREFOUR - ALCANTARA | B84: 0 | C84: 93.58 | D84: pg | E84: bradesco cartoes | J84: mercado
A85: O BOTICARIO | B85: 0 | C85: 144.7 | D85: pg | E85: bradesco cartoes | J85: gift
A86: SACOLAO DO BARATEIRO | B86: 0 | C86: 8.11 | D86: pg | E86: bradesco cartoes | J86: Feira
A87: GrupoIdeal | B87: 0 | C87: 15 | D87: pg | E87: bradesco cartoes | J87: Feira
A88: LGM DISTRIBUIDORA E CO | B88: 0 | C88: 4 | D88: pg | E88: bradesco cartoes | J88: Padaria
A89: KI CHOPP | B89: 0 | C89: 119.69 | D89: pg | E89: bradesco cartoes | J89: Lazer
... A99: Pix Enel | B99: 19 | C99: 2445.98 | D99: pg | E99: Pix Santander | J99: Energia
A101: boleto pessoal | C101: =9634*0.3-(633.9) -> 2256.3
A102: total | C102: =SUM(C2:C98) -> 10427.69 | D102: =(9167.28)-C102-C101 -> -3516.71
M133: bra
B155: =9167.28-B151 -> 7991.76

Sheet set24
A1: Descricao | B1: dia | C1: valor | D1: situacao | E1: forma de pagamento | F1: beneficiado | G1: outcome | H1: subclassificacao | I1: centro de custo | J1: categoria | L1: tipo de despesas | M1: tag
A2: escolar Arthur | B2: 5 | C2: 695 | D2: pg | E2: boleto | F2: Arthur | G2: bradesco conta | H2: despesas pessoais | I2: despesas essenciais | J2: escola/faculdade | L2: fixa
A3: Faculdade Aline | B3: 5 | C3: 795.22 | D3: pg | E3: boleto | F3: Aline | G3: bradesco conta | H3: despesas pessoais | I3: despesas essenciais | J3: escola/faculdade | L3: fixa
A4: Faculdade Alex | B4: 26 | C4: 0 | D4: pg | E4: boleto | F4: Alex | G4: santander conta | H4: despesas pessoais | I4: despesas essenciais | J4: escola/faculdade | L4: fixa
A5: Conta de energia | B5: 14 | C5: 521.44 | D5: pg | E5: boleto | F5: familia | G5: santander conta | H5: habitacao | I5: despesas essenciais | J5: Energia | L5: variavel
A6: internet fixa | B6: 11 | C6: 129 | D6: pg | E6: boleto | F6: familia | G6: bradesco conta | H6: habitacao | I6: despesas essenciais | J6: Internet | L6: fixa
A7: internet oi móvel | B7: 20 | C7: 88 | D7: pg | E7: debito automatico | F7: Alex | G7: bradesco conta | H7: habitacao | I7: despesas essenciais | J7: Internet movel | L7: fixa
A8: streaming HBO | B8: 30 | C8: 19.95 | D8: open | E8: nubank card | F8: familia | G8: nubank conta | H8: habitacao | J8: streaming | L8: fixa
A9: Apple Tv | B9: 16 | C9: 0 | D9: closed | E9: nubank card | F9: familia | G9: nubank conta | H9: habitacao | J9: streaming | L9: fixa
A10: streaming amazonPrime | B10: 29 | C10: 0 | D10: open | E10: nubank card | F10: familia | G10: nubank conta | H10: habitacao | J10: streaming | L10: fixa
A11: assinatura mercado livre | B11: 2 | C11: 17.99 | D11: open | E11: nubank card | F11: familia | G11: nubank conta | H11: habitacao | J11: streaming | L11: fixa
A12: contra contabilidade | B12: 15 | C12: 100.46 | D12: open | E12: nubank card | F12: Alex | G12: nubank conta | H12: despesas pessoais | J12: contabilidade | L12: fixa
A13: assinatura NETFLIX | B13: 8 | C13: 44.9 | D13: open | E13: nubank card | F13: familia | G13: nubank conta | H13: habitacao | J13: streaming | L13: fixa
A14: assinatura GamePass | B14: 15 | C14: 0 | D14: open | E14: nubank card | F14: familia | G14: nubank conta | H14: habitacao | J14: streaming | L14: fixa
A15: seguro PIER carro | B15: 27 | C15: 218.5 | D15: open | E15: nubank card | F15: familia | G15: nubank conta | H15: transporte | I15: despesas essenciais | J15: seguro | L15: fixa
A16: curso rocketseatPlus | B16: 2 | C16: 0 | D16: open | E16: nubank card | F16: Alex | G16: nubank conta | H16: educacao | I16: educacao | J16: cursos | L16: fixa
A17: gympass | B17: 27 | C17: =85.9+129.9 -> 215.8 | D17: open | E17: nubank card | F17: Alex | G17: nubank conta | H17: despesas pessoais | I17: despesas essenciais | J17: academia | L17: fixa
A18: recarga arthur | B18: 0 | C18: 0 | D18: open | E18: Pix | J18: Internet movel
A19: recarga Aline | B19: 0 | C19: 0 | D19: open | E19: Pix | J19: Internet movel
A20: Futebol Alex | B20: 0 | C20: 65 | D20: open | E20: Pix | J20: Lazer
A21: Combustivel | B21: 0 | C21: 0 | D21: open | E21: Bradesco cartoes | J21: combustivel
A22: Personal | B22: 8 | C22: 480 | D22: pg | E22: Pix | J22: academia
A23: Amazon | B23: 5 | C23: 63.5 | D23: pg | E23: nubank card | J23: gift | N23: 45324
A24: petz | B24: 8 | C24: 379.52 | D24: pg | E24: nubank card | J24: Pet
A25: Pag*Steam | B25: 0 | C25: 61.29 | D25: pg | E25: Bradesco cartoes | J25: gift | N25: 45354
A26: restaurante da familia | B26: 0 | C26: 32 | D26: pg | E26: Bradesco cartoes | J26: mercado
A27: sams club | B27: 0 | C27: 163.94 | D27: pg | E27: Bradesco cartoes | J27: mercado
A28: lgmdistribuidora | B28: 0 | C28: 7 | D28: pg | E28: bradesco cartoes | J28: Padaria
A29: grupoIdeal | B29: 0 | C29: 24 | D29: pg | E29: bradesco cartoes | J29: outros
A30: Epar | B30: 0 | C30: 17 | D30: pg | E30: bradesco cartoes | J30: outros
A31: Burger king | B31: 0 | C31: 54.9 | D31: pg | E31: bradesco cartoes | J31: Lazer
A32: padaria | B32: 2 | C32: 4 | D32: pg | E32: bradesco cartoes | J32: Padaria
A33: PostoVipCanecoNoven | B33: 2 | C33: 50 | D33: pg | E33: bradesco cartoes | J33: combustivel
A34: PuroGas | B34: 2 | C34: 64.97 | D34: pg | E34: bradesco cartoes | J34: combustivel
A35: Denair | B35: 3 | C35: 116 | D35: pg | E35: bradesco cartoes | J35: manutencao veicular
A36: pank motos | B36: 3 | C36: 295 | D36: pg | E36: bradesco cartoes | J36: manutencao veicular
A37: Padaria | B37: 4 | C37: 8 | D37: pg | E37: bradesco cartoes | J37: Padaria | M37: ferias
A38: sacolao do barateiro | B38: 4 | C38: 8 | D38: pg | E38: bradesco cartoes | J38: Feira
A39: StarLink | B39: 4 | C39: 1696.42 | D39: pg | E39: bradesco cartoes | J39: Internet
A40: Iof S/Trans inter Reais | B40: 4 | C40: 74.3 | D40: pg | E40: bradesco cartoes | J40: Internet movel
A41: Gabriela Marinho | B41: 5 | C41: 200 | D41: pg | E41: bradesco cartoes | J41: Pet
A42: restaurante da familia | B42: 5 | C42: 32 | D42: pg | E42: bradesco cartoes | J42: mercado
A43: Burger king | B43: 5 | C43: 50 | D43: pg | E43: bradesco cartoes | J43: Lazer
A44: casa pedro | B44: 5 | C44: 84.35 | D44: pg | E44: bradesco cartoes | J44: mercado
A45: Drogaria tamoio | B45: 5 | C45: 24.1 | D45: pg | E45: bradesco cartoes | J45: farmacia
A46: Drogaria Pacheco | B46: 5 | C46: 45.44 | D46: pg | E46: bradesco cartoes | J46: farmacia
A47: Nosso Park Estacionamento | B47: 5 | C47: 5 | D47: pg | E47: bradesco cartoes | J47: estacionamentos
A48: Puro gas | B48: 5 | C48: 9 | D48: pg | E48: bradesco cartoes | J48: combustivel
A49: finpet | B49: 5 | C49: 230 | D49: pg | E49: bradesco cartoes | J49: Pet
... A62: cacula sao goncalo | B62: 15 | C62: 0 | D62: pg | E62: bradesco cartoes | J62: manutenção domiciliar
A63: Burger king | B63: 15 | C63: 0 | D63: pg | E63: bradesco cartoes | J63: Lazer | M63: Férias
A64: kik | B64: 15 | C64: 0 | D64: pg | E64: bradesco cartoes | J64: Vestuario | L64: 45323 | M64: Férias
A65: Top Arena | B65: 16 | C65: 0 | D65: pg | E65: bradesco cartoes | J65: Lazer | M65: Férias
A66: padaria | B66: 16 | C66: 0 | D66: pg | E66: bradesco cartoes | J66: Padaria | M66: Férias
A67: hortfruit | B67: 16 | C67: 0 | D67: pg | E67: bradesco cartoes | J67: Feira | M67: Férias
A68: fabrica de bolo vo az | B68: 17 | C68: 0 | D68: pg | E68: nubank card | J68: Lazer | M68: Férias
A69: carrefour manilha | B69: 17 | C69: 0 | D69: pg | E69: bradesco cartoes | J69: mercado | M69: Férias
A70: Lojas Americanas | B70: 17 | C70: 0 | D70: pg | E70: bradesco cartoes | J70: mercado | M70: Férias
A71: Outback | B71: 17 | C71: 0 | D71: pg | E71: bradesco cartoes | H71: educacao | I71: educacao | J71: Lazer | K71: 44959 | M71: Férias
A72: Carrefour Cal 212 | B72: 17 | C72: 0 | D72: pg | E72: bradesco cartoes | J72: mercado | M72: Férias
A73: Grupo Ideal | B73: 18 | C73: 0 | D73: pg | E73: bradesco cartoes | J73: combustivel | M73: Férias
A74: hortfruit | B74: 19 | C74: 0 | D74: pg | E74: bradesco cartoes | J74: Feira | M74: Férias
A75: Assai atacadista | B75: 20 | C75: 0 | D75: pg | E75: bradesco cartoes | J75: mercado | M75: Férias
A76: Grupo genius brasil p | B76: 21 | C76: 0 | D76: pg | E76: bradesco cartoes | J76: combustivel | M76: Férias
A77: Drogaria tamoio | B77: 23 | C77: 0 | D77: pg | E77: bradesco cartoes | J77: Padaria | M77: Férias
A78: Carrefour posto | B78: 23 | C78: 0 | D78: pg | E78: bradesco cartoes | J78: combustivel | M78: Férias
A79: Alexandre | B79: 23 | C79: 0 | D79: pg | E79: bradesco cartoes | J79: Lazer | M79: Férias
A80: edinilzaborges | B80: 23 | C80: 0 | D80: pg | E80: bradesco cartoes | J80: Lazer
A81: ton lehmonada | B81: 23 | C81: 0 | D81: pg | E81: bradesco cartoes | J81: Lazer
A82: ton lehmonada | B82: 23 | C82: 0 | D82: pg | E82: bradesco cartoes | J82: Lazer
A83: edinilzaborges | B83: 23 | C83: 0 | D83: pg | E83: bradesco cartoes | J83: Lazer
A84: Assai atacadista | B84: 23 | C84: 0 | D84: pg | E84: bradesco cartoes | J84: mercado
A85: padaria | B85: 24 | C85: 0 | D85: pg | E85: bradesco cartoes | J85: Padaria
A86: Puro gas | B86: 25 | C86: 0 | D86: pg | E86: bradesco cartoes | J86: Lazer
A87: Alypay Brasil | B87: 26 | C87: 0 | D87: pg | E87: bradesco cartoes | J87: Lazer
A88: Aliexpress | B88: 26 | C88: 0 | D88: pg | E88: bradesco cartoes | J88: estacionamentos
A89: hortfruit | B89: 0 | C89: 0 | D89: pg | E89: bradesco cartoes | J89: Feira
A90: corte arthur | B90: 0 | C90: 0 | D90: pg | E90: pix | J90: mercado
A91: jogo steam | B91: 0 | C91: 0 | D91: pg | E91: pix | J91: mercado
... A101: objetiva | B101: 0 | C101: 0 | D101: pg | E101: bradesco cartoes | J101: Vestuario
A103: boleto pessoal | C103: =9167.28*0.3-(633.9)-C39 -> 419.864
A104: total | C104: =SUM(C2:C101) -> 7670.66 | D104: =(9167.28)-C104-C103 -> 1076.756
M131: bra
B153: =9167.28-B149 -> 9167.28

Sheet jun24
A1: Descricao | B1: dia | C1: valor | D1: situacao | E1: forma de pagamento | F1: beneficiado | G1: outcome | H1: subclassificacao | I1: centro de custo | J1: categoria | L1: tipo de despesas | M1: tag
A2: escolar Arthur | B2: 5 | C2: 695 | D2: pg | E2: boleto | F2: Arthur | G2: bradesco conta | H2: despesas pessoais | I2: despesas essenciais | J2: escola/faculdade | L2: fixa
A3: Faculdade Aline | B3: 5 | C3: 1113.31 | D3: pg | E3: boleto | F3: Aline | G3: bradesco conta | H3: despesas pessoais | I3: despesas essenciais | J3: escola/faculdade | L3: fixa
A4: Faculdade Alex | B4: 26 | C4: 0 | D4: pg | E4: boleto | F4: Alex | G4: santander conta | H4: despesas pessoais | I4: despesas essenciais | J4: escola/faculdade | L4: fixa
A5: Conta de energia | B5: 14 | C5: 696.36 | D5: pg | E5: boleto | F5: familia | G5: santander conta | H5: habitacao | I5: despesas essenciais | J5: Energia | L5: variavel
A6: internet fixa | B6: 11 | C6: 129 | D6: pg | E6: boleto | F6: familia | G6: bradesco conta | H6: habitacao | I6: despesas essenciais | J6: Internet | L6: fixa
A7: internet oi móvel | B7: 20 | C7: 88 | D7: pg | E7: debito automatico | F7: Alex | G7: bradesco conta | H7: habitacao | I7: despesas essenciais | J7: Internet movel | L7: fixa
A8: streaming HBO | B8: 30 | C8: 17.45 | D8: open | E8: nubank card | F8: familia | G8: nubank conta | H8: habitacao | J8: streaming | L8: fixa
A9: Apple Tv | B9: 16 | C9: 0 | D9: closed | E9: nubank card | F9: familia | G9: nubank conta | H9: habitacao | J9: streaming | L9: fixa
A10: streaming amazonPrime | B10: 29 | C10: 166.66 | D10: open | E10: nubank card | F10: familia | G10: nubank conta | H10: habitacao | J10: streaming | L10: fixa
A11: assinatura mercado livre | B11: 2 | C11: 17.99 | D11: open | E11: nubank card | F11: familia | G11: nubank conta | H11: habitacao | J11: streaming | L11: fixa
A12: contra contabilidade | B12: 15 | C12: 100.46 | D12: open | E12: nubank card | F12: Alex | G12: nubank conta | H12: despesas pessoais | J12: contabilidade | L12: fixa
A13: assinatura NETFLIX | B13: 8 | C13: 39.9 | D13: open | E13: nubank card | F13: familia | G13: nubank conta | H13: habitacao | J13: streaming | L13: fixa
A14: assinatura GamePass | B14: 15 | C14: 0 | D14: open | E14: nubank card | F14: familia | G14: nubank conta | H14: habitacao | J14: streaming | L14: fixa
A15: seguro PIER carro | B15: 27 | C15: 218.5 | D15: open | E15: nubank card | F15: familia | G15: nubank conta | H15: transporte | I15: despesas essenciais | J15: seguro | L15: fixa
A16: curso rocketseatPlus | B16: 2 | C16: 0 | D16: open | E16: nubank card | F16: Alex | G16: nubank conta | H16: educacao | I16: educacao | J16: cursos | L16: fixa
A17: gympass | B17: 27 | C17: =79.9+119.9 -> 199.8 | D17: open | E17: nubank card | F17: Alex | G17: nubank conta | H17: despesas pessoais | I17: despesas essenciais | J17: academia | L17: fixa
A18: recarga arthur | B18: 0 | C18: 0 | D18: open | E18: Pix | J18: Internet movel
A19: recarga Aline | B19: 0 | C19: 0 | D19: open | E19: Pix | J19: Internet movel
A20: Futebol Alex | B20: 0 | C20: 65 | D20: open | E20: Pix | J20: Lazer
A21: Combustivel | B21: 0 | C21: 0 | D21: open | E21: Bradesco cartoes | J21: combustivel
A22: Personal | B22: 8 | C22: 480 | D22: pg | E22: Pix | J22: academia
A23: padaria | B23: 0 | C23: 4 | D23: pg | E23: Bradesco cartoes | J23: Padaria
A24: Puro gas | B24: 0 | C24: 30 | D24: pg | E24: Bradesco cartoes | J24: combustivel
A25: Riachuelo | B25: 0 | C25: 169.7 | D25: pg | E25: Bradesco cartoes | J25: Vestuario
A26: Burger king | B26: 0 | C26: 57.9 | D26: pg | E26: Bradesco cartoes | J26: Lazer
A27: padaria | B27: 0 | C27: 4 | D27: pg | E27: Bradesco cartoes | J27: Padaria
A28: hortfruit | B28: 0 | C28: 15.85 | D28: pg | E28: bradesco cartoes | J28: Feira
A29: padaria | B29: 0 | C29: 4 | D29: pg | E29: bradesco cartoes | J29: Padaria
... A36: padaria | B36: 2 | C36: 9 | D36: pg | E36: bradesco cartoes | J36: Padaria
A37: Alipay | B37: 4 | C37: -33.88 | D37: pg | E37: bradesco cartoes | J37: projetos | M37: ferias
A38: padaria | B38: 5 | C38: 4 | D38: pg | E38: bradesco cartoes | J38: Padaria
A39: Drogarias Pacheco | B39: 5 | C39: 36.47 | D39: pg | E39: bradesco cartoes | J39: farmacia
A40: intercont Supermac | B40: 6 | C40: 5.24 | D40: pg | E40: bradesco cartoes | J40: mercado
A41: padaria | B41: 7 | C41: 4 | D41: pg | E41: bradesco cartoes | J41: Padaria | L41: 45323
A42: Esfirra trindade | B42: 8 | C42: 53 | D42: pg | E42: bradesco cartoes | J42: Lazer
A43: ton acai | B43: 8 | C43: 12 | D43: pg | E43: bradesco cartoes | J43: Lazer
A44: padaria | B44: 8 | C44: 4 | D44: pg | E44: bradesco cartoes | J44: Padaria
A45: lj23 sh sao goncalo | B45: 8 | C45: 112.94 | D45: pg | E45: bradesco cartoes | J45: gift
A46: Auto Posto Monteiros D | B46: 8 | C46: 62.13 | D46: pg | E46: bradesco cartoes | J46: combustivel
A47: cia do doce | B47: 8 | C47: 54.19 | D47: pg | E47: bradesco cartoes | J47: mercado
A48: boticario | B48: 11 | C48: 116.9 | D48: pg | E48: bradesco cartoes | J48: gift
A49: Carrefour 212 | B49: 11 | C49: 181.14 | D49: pg | E49: bradesco cartoes | J49: mercado
A50: pes e patas | B50: 11 | C50: 97.9 | D50: pg | E50: bradesco cartoes | J50: Pet
A51: padaria | B51: 12 | C51: 4 | D51: pg | E51: bradesco cartoes | J51: Padaria
A52: hortfruit | B52: 12 | C52: 44.15 | D52: pg | E52: bradesco cartoes | J52: Feira
A53: golden fruit itauna | B53: 12 | C53: 17.8 | D53: pg | E53: bradesco cartoes | J53: Feira
... A62: cacula sao goncalo | B62: 15 | C62: 41.99 | D62: pg | E62: bradesco cartoes | J62: manutenção domiciliar
A63: Burger king | B63: 15 | C63: 54.9 | D63: pg | E63: bradesco cartoes | J63: Lazer | M63: Férias
A64: kik | B64: 15 | C64: 34.99 | D64: pg | E64: bradesco cartoes | J64: Vestuario | L64: 45323 | M64: Férias
A65: Top Arena | B65: 16 | C65: 9 | D65: pg | E65: bradesco cartoes | J65: Lazer | M65: Férias
A66: padaria | B66: 16 | C66: 9 | D66: pg | E66: bradesco cartoes | J66: Padaria | M66: Férias
A67: hortfruit | B67: 16 | C67: 24.28 | D67: pg | E67: bradesco cartoes | J67: Feira | M67: Férias
